Workbook

Sheet Parameters
A1: Simulation Name | B1: Simulation Name | C1: Test unlimited | D1: Test unlimited | E1: Test unlimited | F1: Test unlimited | G1: Test unlimited | H1: Test unlimited | I1: Test unlimited | J1: Test unlimited | K1: Test unlimited
A2: Simulation Comment | B2: Simulation Comment
A3: BridgeCare Rules Creator: | B3: Central Office | J3: Simulation Last Run: | K3: 1/15/2026
A4: BridgeCare Rules Date: | B4: 1/15/2026
A6: Network Name | B6: Network Name
A7: Network: | B7: 2024 Q2 Base Data
A9: Parameters are based on the criteria editor inputs
A10: NHS | B10: NHS | F10: Investment: | G10: Investment: | H10: Investment: | L10: Analysis: | M10: Analysis: | N10: Analysis: | O10: Analysis:
A11: NHS | B11: N
A12: Non-NHS | B12: Y | F12: Start Year: | G12: Start Year: | H12: 2026 | L12: Optimization: | M12: Optimization: | N12: BenefitToCostRatio | O12: BenefitToCostRatio
A14: 6A19 BPN | B14: 6A19 BPN | F14: Analysis Period: | G14: Analysis Period: | H14: 11 | L14: Budget: | M14: Budget: | N14: UnlimitedSpending | O14: UnlimitedSpending
A15: 1 | B15: N
A16: 2 | B16: N | F16: Inflation Rate: | G16: Inflation Rate: | H16: 3 | L16: Weighting: | M16: Weighting: | N16: RISK_SCORE | O16: RISK_SCORE
A17: 3 | B17: N
A18: 4 | B18: N | D18: 5A21 Owner | E18: 5A21 Owner | F18: 5A21 Owner | H18: 5C22 Functional Class | I18: 5C22 Functional Class | J18: 5C22 Functional Class | L18: Benefit: | M18: Benefit: | N18: CONDITIONINDEX | O18: CONDITIONINDEX
A19: H | B19: N | D19: 01 - State Highway Agency | E19: 01 - State Highway Agency | F19: N | H19: Rural | I19: Rural | J19: Rural
A20: L | B20: Y | D20: 02 - County Highway Agency | E20: 02 - County Highway Agency | F20: Y | H20: 01 - Rural - Principal Arterial - Interstate | I20: 01 - Rural - Principal Arterial - Interstate | J20: N | L20: Jurisdiction Criteria: | M20: Jurisdiction Criteria: | N20: ([DISTRICT]='04' AND [INTERNET_REPORT]='Local' AND [COUNTY]='Pike' AND [NBISLEN]='Y' AND ([CULV_SEEDED]<'5' OR [DECK_SEEDED]<'5' OR [SUB_SEEDED]<'5' OR [SUP_SEEDED]<'5')) | O20: ([DISTRICT]='04' AND [INTERNET_REPORT]='Local' AND [COUNTY]='Pike' AND [NBISLEN]='Y' AND ([CULV_SEEDED]<'5' OR [DECK_SEEDED]<'5' OR [SUB_SEEDED]<'5' OR [SUP_SEEDED]<'5')) | P20: ([DISTRICT]='04' AND [INTERNET_REPORT]='Local' AND [COUNTY]='Pike' AND [NBISLEN]='Y' AND ([CULV_SEEDED]<'5' OR [DECK_SEEDED]<'5' OR [SUB_SEEDED]<'5' OR [SUP_SEEDED]<'5')) | Q20: ([DISTRICT]='04' AND [INTERNET_REPORT]='Local' AND [COUNTY]='Pike' AND [NBISLEN]='Y' AND ([CULV_SEEDED]<'5' OR [DECK_SEEDED]<'5' OR [SUB_SEEDED]<'5' OR [SUP_SEEDED]<'5')) | R20: ([DISTRICT]='04' AND [INTERNET_REPORT]='Local' AND [COUNTY]='Pike' AND [NBISLEN]='Y' AND ([CULV_SEEDED]<'5' OR [DECK_SEEDED]<'5' OR [SUB_SEEDED]<'5' OR [SUP_SEEDED]<'5')) | S20: ([DISTRICT]='04' AND [INTERNET_REPORT]='Local' AND [COUNTY]='Pike' AND [NBISLEN]='Y' AND ([CULV_SEEDED]<'5' OR [DECK_SEEDED]<'5' OR [SUB_SEEDED]<'5' OR [SUP_SEEDED]<'5')) | T20: ([DISTRICT]='04' AND [INTERNET_REPORT]='Local' AND [COUNTY]='Pike' AND [NBISLEN]='Y' AND ([CULV_SEEDED]<'5' OR [DECK_SEEDED]<'5' OR [SUB_SEEDED]<'5' OR [SUP_SEEDED]<'5')) | U20: ([DISTRICT]='04' AND [INTERNET_REPORT]='Local' AND [COUNTY]='Pike' AND [NBISLEN]='Y' AND ([CULV_SEEDED]<'5' OR [DECK_SEEDED]<'5' OR [SUB_SEEDED]<'5' OR [SUP_SEEDED]<'5')) | V20: ([DISTRICT]='04' AND [INTERNET_REPORT]='Local' AND [COUNTY]='Pike' AND [NBISLEN]='Y' AND ([CULV_SEEDED]<'5' OR [DECK_SEEDED]<'5' OR [SUB_SEEDED]<'5' OR [SUP_SEEDED]<'5')) | W20: ([DISTRICT]='04' AND [INTERNET_REPORT]='Local' AND [COUNTY]='Pike' AND [NBISLEN]='Y' AND ([CULV_SEEDED]<'5' OR [DECK_SEEDED]<'5' OR [SUB_SEEDED]<'5' OR [SUP_SEEDED]<'5')) | X20: ([DISTRICT]='04' AND [INTERNET_REPORT]='Local' AND [COUNTY]='Pike' AND [NBISLEN]='Y' AND ([CULV_SEEDED]<'5' OR [DECK_SEEDED]<'5' OR [SUB_SEEDED]<'5' OR [SUP_SEEDED]<'5')) | Y20: ([DISTRICT]='04' AND [INTERNET_REPORT]='Local' AND [COUNTY]='Pike' AND [NBISLEN]='Y' AND ([CULV_SEEDED]<'5' OR [DECK_SEEDED]<'5' OR [SUB_SEEDED]<'5' OR [SUP_SEEDED]<'5')) | Z20: ([DISTRICT]='04' AND [INTERNET_REPORT]='Local' AND [COUNTY]='Pike' AND [NBISLEN]='Y' AND ([CULV_SEEDED]<'5' OR [DECK_SEEDED]<'5' OR [SUB_SEEDED]<'5' OR [SUP_SEEDED]<'5'))
A21: T | B21: N | D21: 03 - Town or Township Highway Agency | E21: 03 - Town or Township Highway Agency | F21: Y | H21: 02 - Rural - Principal Arterial - Other | I21: 02 - Rural - Principal Arterial - Other | J21: N
A22: D | B22: N | D22: 04 - City, Municipal Highway Agency or Borough | E22: 04 - City, Municipal Highway Agency or Borough | F22: N | H22: 03 - Rural - Other Freeway/Expressway | I22: 03 - Rural - Other Freeway/Expressway | J22: N
A23: N | B23: N | D23: 11 - State Park, Forest or Reservation Agency | E23: 11 - State Park, Forest or Reservation Agency | F23: N | H23: 06 - Rural - Minor Arterial | I23: 06 - Rural - Minor Arterial | J23: N | L23: Number | M23: Criteria: | N23: Analysis Priorites: | O23: Analysis Priorites: | P23: Analysis Priorites: | Q23: Analysis Priorites: | R23: Analysis Priorites: | S23: Analysis Priorites: | T23: Analysis Priorites: | U23: Analysis Priorites: | V23: Analysis Priorites: | W23: Analysis Priorites: | X23: Analysis Priorites: | Y23: Analysis Priorites: | Z23: Analysis Priorites:
A24: Blank | B24: N | D24: 12 - Local Park, Forest or Reservation Agency | E24: 12 - Local Park, Forest or Reservation Agency | F24: N | H24: 07 - Rural - Major Collector | I24: 07 - Rural - Major Collector | J24: N
D25: 21 - Other State Agency | E25: 21 - Other State Agency | F25: N | H25: 08 - Rural - Minor Collector | I25: 08 - Rural - Minor Collector | J25: N | L25: 1 | M25: (([BRIDGE_TYPE]='B' AND ([DECK_SEEDED]<='3.5' OR [SUP_SEEDED]<='3.5' OR [SUB_SEEDED]<='3.5')) OR ([BRIDGE_TYPE]='C' AND [CULV_SEEDED]<='3.5')) AND ([NHS_IND]='1' OR ([NHS_IND]='0' AND [RISK_SCORE]>='15000'))
D26: 25 - Other local Agency | E26: 25 - Other local Agency | F26: N | H26: 09 - Rural - Local | I26: 09 - Rural - Local | J26: Y | L26: 2 | M26: ([POST_STATUS]<>'CLOSED' AND ([DECK_SEEDED]<'3.0' OR [SUP_SEEDED]<'3.0' OR [SUB_SEEDED]<'3.0'))
A27: Bridge Length | B27: Bridge Length | D27: 26 - Private (Other than Railroad) | E27: 26 - Private (Other than Railroad) | F27: N | H27: NN - Other | I27: NN - Other | J27: N | L27: 3 | M27: [BRIDGE_TYPE]='C' OR [BRIDGE_TYPE]='B'
A28: 8-20 | B28: N | D28: 27 - Railroad | E28: 27 - Railroad | F28: N | H28: Urban | I28: Urban | J28: Urban
A29: NBIS Length | B29: Y | D29: 31 - State Toll Authority | E29: 31 - State Toll Authority | F29: N | H29: 11 - Urban - Principal Arterial - Interstate | I29: 11 - Urban - Principal Arterial - Interstate | J29: N | L29: Budget Split Criteria
D30: 32 - Local Toll Authority | E30: 32 - Local Toll Authority | F30: N | H30: 12 - Urban - Principal Arterial - Other Freeway & Expressways | I30: 12 - Urban - Principal Arterial - Other Freeway & Expressways | J30: N | L30: Rank | M30: Amount | N30: Percentage
A31: Status | B31: Status | D31: 60 - Other Federal Agencies | E31: 60 - Other Federal Agencies | F31: N | H31: 14 - Urban - Other Principal Arterial | I31: 14 - Urban - Other Principal Arterial | J31: N | L31: 1 | M31: 5000000 | N31: 100
A32: Open | B32: Y | D32: 62 - Bureau of Indian Affairs | E32: 62 - Bureau of Indian Affairs | F32: N | H32: 16 - Urban - Minor Arterial | I32: 16 - Urban - Minor Arterial | J32: N | L32: 2 | M32: 30000000 | N32: 50/50
A33: Closed | B33: N | D33: 64 - U.S. Forest Service | E33: 64 - U.S. Forest Service | F33: N | H33: 17 - Urban - Collector | I33: 17 - Urban - Collector | J33: N | L33: 3 | M33: 50000000 | N33: 33/33/34
A34: P3 | B34: N | D34: 66 - National Park Service | E34: 66 - National Park Service | F34: N | H34: 19 - Urban - Local | I34: 19 - Urban - Local | J34: N | L34: 4 | M34: 100000000 | N34: 25/25/25/25
A35: Posted | B35: Y | D35: 68 - Bureau of Land Management | E35: 68 - Bureau of Land Management | F35: N | H35: NN - Other | I35: NN - Other | J35: N | L35: 5 | M35: 100000001 | N35: 20/20/20/20/20
D36: 69 - Bureau of Reclamation | E36: 69 - Bureau of Reclamation | F36: N | H36: 99 - Urban - Ramp | I36: 99 - Urban - Ramp | J36: N
A37: Treatments in Simulations | B37: Treatments in Simulations | D37: 70 - Military Reservation Corps Engineers | E37: 70 - Military Reservation Corps Engineers | F37: N
A38: BAMS | B38: MPMS | D38: 80 - Unknown | E38: 80 - Unknown | F38: N
A39: Bituminous Overlay | D39: XX - Demolished/Replaced | E39: XX - Demolished/Replaced | F39: N
A40: Bridge Replacement
A41: Culvert Rehab (Other)
A42: Culvert Replacement (Box Frame
A43: Culvert Replacement (Other)
A44: Culvert Replacement (Pipe)
A45: Deck Replacement
A46: Epoxy Joint Glands Coatings
A47: General Preservation
A48: Leaking Deck Joint Replacement
A49: Maintenance
A50: No Treatment
A51: Painting (Full)
... A60: Superstructure Rep Rehab
A62: Years | B62: Total Funding
B63: WAYNE_BRIP | C63: LLTS_185 | D63: WAYNE_STU | E63: N TIER_185 | F63: WAYNE_STP | G63: NEPA_581 | H63: LLTS_STU | I63: LLTS_BOF | J63: N TIER_NHPP | K63: NEPA_SPIKE | L63: N TIER_581 | M63: NEPA_BOF | N63: NEPA_185 | O63: NEPA_STU | P63: WAYNE_BOF | Q63: LUZ_MAINT | R63: LLTS_BRIP | S63: N TIER_STP | T63: N TIER_BRIP | U63: INTERSTATE | V63: SUSQ_MAINT | W63: WAYNE_185 | X63: NEPA_BRIP | Y63: NEPA_NHPP | Z63: LLTS_STP | AA63: N TIER_STU | AB63: LACK_MAINT | AC63: WAYNE_MAINT | AD63: WAYNE_NHPP | AE63: PIKE_MAINT | AF63: LLTS_581 | AG63: WAYNE_581 | AH63: N TIER_BOF | AI63: WYO_MAINT | AJ63: LLTS_NHPP | AK63: LLTS_SPIKE | AL63: WAYNE_SPIKE | AM63: NEPA_STP | AN63: N TIER_SPIKE
A64: 2026 | B64: 703500 | C64: 6879600 | D64: 1 | E64: 1660400 | F64: 1295700 | G64: 1048600 | H64: 6027700 | I64: 3852100 | J64: 993300 | K64: 1 | L64: 3686200 | M64: 548800 | N64: 581700 | O64: 1 | P64: 886900 | Q64: 1 | R64: 6341300 | S64: 2330300 | T64: 1694000 | U64: 1 | V64: 1 | W64: 753200 | X64: 544600 | Y64: 242200 | Z64: 5350100 | AA64: 1 | AB64: 1 | AC64: 1 | AD64: 1 | AE64: 1 | AF64: 8318100 | AG64: 2097900 | AH64: 1923600 | AI64: 1 | AJ64: 9836400 | AK64: 1 | AL64: 1 | AM64: 894600 | AN64: 1
A65: 2027 | B65: 703500 | C65: 6767600 | D65: 1 | E65: 1626800 | F65: 1295000 | G65: 1180900 | H65: 6027700 | I65: 3852100 | J65: 879200 | K65: 1 | L65: 4186700 | M65: 548800 | N65: 572600 | O65: 1 | P65: 886900 | Q65: 1 | R65: 6341300 | S65: 2329600 | T65: 1694000 | U65: 1 | V65: 1 | W65: 739900 | X65: 544600 | Y65: 214900 | Z65: 5348000 | AA65: 1 | AB65: 1 | AC65: 1 | AD65: 1 | AE65: 1 | AF65: 9368100 | AG65: 2367400 | AH65: 1923600 | AI65: 1 | AJ65: 8708700 | AK65: 1 | AL65: 1 | AM65: 894600 | AN65: 1
A66: 2028 | B66: 703500 | C66: 6766900 | D66: 1 | E66: 1625400 | F66: 1295000 | G66: 1292200 | H66: 6027700 | I66: 3852100 | J66: 794500 | K66: 1 | L66: 4607400 | M66: 548800 | N66: 572600 | O66: 1 | P66: 886900 | Q66: 1 | R66: 6341300 | S66: 2328900 | T66: 1694000 | U66: 1 | V66: 1 | W66: 739900 | X66: 544600 | Y66: 193900 | Z66: 5346600 | AA66: 1 | AB66: 1 | AC66: 1 | AD66: 1 | AE66: 1 | AF66: 10250800 | AG66: 2594200 | AH66: 1923600 | AI66: 1 | AJ66: 7868700 | AK66: 1 | AL66: 1 | AM66: 893900 | AN66: 1
A67: 2029 | B67: 703500 | C67: 6766900 | D67: 1 | E67: 1624700 | F67: 1295000 | G67: 1292200 | H67: 6027700 | I67: 3852100 | J67: 794500 | K67: 1 | L67: 4606700 | M67: 548800 | N67: 572600 | O67: 1 | P67: 886900 | Q67: 1 | R67: 6341300 | S67: 2328900 | T67: 1694000 | U67: 1 | V67: 1 | W67: 739200 | X67: 544600 | Y67: 193900 | Z67: 5346600 | AA67: 1 | AB67: 1 | AC67: 1 | AD67: 1 | AE67: 1 | AF67: 10250800 | AG67: 2594200 | AH67: 1923600 | AI67: 1 | AJ67: 7868700 | AK67: 1 | AL67: 1 | AM67: 893900 | AN67: 1
A68: 2030 | B68: 703500 | C68: 6766200 | D68: 1 | E68: 1623300 | F68: 1295000 | G68: 1292200 | H68: 6027700 | I68: 3852100 | J68: 794500 | K68: 1 | L68: 4605300 | M68: 548800 | N68: 571900 | O68: 1 | P68: 886900 | Q68: 1 | R68: 6341300 | S68: 2328900 | T68: 1694000 | U68: 1 | V68: 1 | W68: 739200 | X68: 544600 | Y68: 193900 | Z68: 5346600 | AA68: 1 | AB68: 1 | AC68: 1 | AD68: 1 | AE68: 1 | AF68: 10250100 | AG68: 2593500 | AH68: 1923600 | AI68: 1 | AJ68: 7868700 | AK68: 1 | AL68: 1 | AM68: 893900 | AN68: 1
A69: 2031 | B69: 703500 | C69: 6765500 | D69: 1 | E69: 1621900 | F69: 1295000 | G69: 1292200 | H69: 6027700 | I69: 3852100 | J69: 794500 | K69: 1 | L69: 4603900 | M69: 548800 | N69: 571900 | O69: 1 | P69: 886900 | Q69: 1 | R69: 6341300 | S69: 2328900 | T69: 1694000 | U69: 1 | V69: 1 | W69: 739200 | X69: 544600 | Y69: 193900 | Z69: 5346600 | AA69: 1 | AB69: 1 | AC69: 1 | AD69: 1 | AE69: 1 | AF69: 10249400 | AG69: 2593500 | AH69: 1923600 | AI69: 1 | AJ69: 7868700 | AK69: 1 | AL69: 1 | AM69: 893900 | AN69: 1
A70: 2032 | B70: 703500 | C70: 6764800 | D70: 1 | E70: 1620500 | F70: 1295000 | G70: 1292200 | H70: 6027700 | I70: 3852100 | J70: 794500 | K70: 1 | L70: 4602500 | M70: 548800 | N70: 571900 | O70: 1 | P70: 886900 | Q70: 1 | R70: 6341300 | S70: 2328900 | T70: 1694000 | U70: 1 | V70: 1 | W70: 738500 | X70: 544600 | Y70: 193900 | Z70: 5346600 | AA70: 1 | AB70: 1 | AC70: 1 | AD70: 1 | AE70: 1 | AF70: 10248700 | AG70: 2592800 | AH70: 1923600 | AI70: 1 | AJ70: 7868700 | AK70: 1 | AL70: 1 | AM70: 893900 | AN70: 1
A71: 2033 | B71: 703500 | C71: 6764100 | D71: 1 | E71: 1619800 | F71: 1295000 | G71: 1292200 | H71: 6027700 | I71: 3852100 | J71: 794500 | K71: 1 | L71: 4601800 | M71: 548800 | N71: 571900 | O71: 1 | P71: 886900 | Q71: 1 | R71: 6341300 | S71: 2328900 | T71: 1694000 | U71: 1 | V71: 1 | W71: 738500 | X71: 544600 | Y71: 193900 | Z71: 5346600 | AA71: 1 | AB71: 1 | AC71: 1 | AD71: 1 | AE71: 1 | AF71: 10248000 | AG71: 2592800 | AH71: 1923600 | AI71: 1 | AJ71: 7868700 | AK71: 1 | AL71: 1 | AM71: 893900 | AN71: 1
A72: 2034 | B72: 703500 | C72: 6763400 | D72: 1 | E72: 1617700 | F72: 1295000 | G72: 1292200 | H72: 6027700 | I72: 3852100 | J72: 794500 | K72: 1 | L72: 4599700 | M72: 548800 | N72: 571900 | O72: 1 | P72: 886900 | Q72: 1 | R72: 6341300 | S72: 2328900 | T72: 1694000 | U72: 1 | V72: 1 | W72: 737800 | X72: 544600 | Y72: 193900 | Z72: 5346600 | AA72: 1 | AB72: 1 | AC72: 1 | AD72: 1 | AE72: 1 | AF72: 10247300 | AG72: 2592100 | AH72: 1923600 | AI72: 1 | AJ72: 7868700 | AK72: 1 | AL72: 1 | AM72: 893900 | AN72: 1
A73: 2035 | B73: 703500 | C73: 6762700 | D73: 1 | E73: 1616300 | F73: 1295000 | G73: 1291500 | H73: 6027700 | I73: 3852100 | J73: 794500 | K73: 1 | L73: 4598300 | M73: 548800 | N73: 571900 | O73: 1 | P73: 886900 | Q73: 1 | R73: 6341300 | S73: 2328900 | T73: 1694000 | U73: 1 | V73: 1 | W73: 737800 | X73: 544600 | Y73: 193900 | Z73: 5346600 | AA73: 1 | AB73: 1 | AC73: 1 | AD73: 1 | AE73: 1 | AF73: 10246600 | AG73: 2592100 | AH73: 1923600 | AI73: 1 | AJ73: 7868700 | AK73: 1 | AL73: 1 | AM73: 893900 | AN73: 1
A74: 2036 | B74: 703500 | C74: 6762000 | D74: 1 | E74: 1614900 | F74: 1295000 | G74: 1291500 | H74: 6027700 | I74: 3852100 | J74: 794500 | K74: 1 | L74: 4596900 | M74: 548800 | N74: 571900 | O74: 1 | P74: 886900 | Q74: 1 | R74: 6341300 | S74: 2328900 | T74: 1694000 | U74: 1 | V74: 1 | W74: 737100 | X74: 544600 | Y74: 193900 | Z74: 5346600 | AA74: 1 | AB74: 1 | AC74: 1 | AD74: 1 | AE74: 1 | AF74: 10245900 | AG74: 2591400 | AH74: 1923600 | AI74: 1 | AJ74: 7868700 | AK74: 1 | AL74: 1 | AM74: 893900 | AN74: 1
A77: Budget Criteria
A78: Budget Name | B78: Criteria
A79: WAYNE_BRIP | B79: ([MPO_NAME]='Wayne County' AND ([FUNC_CLASS]='01' OR [FUNC_CLASS]='02' OR [FUNC_CLASS]='03' OR [FUNC_CLASS]='06' OR [FUNC_CLASS]='07' OR [FUNC_CLASS]='11' OR [FUNC_CLASS]='12' OR [FUNC_CLASS]='14' OR [FUNC_CLASS]='16' OR [FUNC_CLASS]='17' OR [FUNC_CLASS]='18') AND [LENGTH]>='20')
A80: LLTS_185 | B80: [MPO_NAME]='Scranton-WB MPO' AND [INTERSTATE]='N'
A81: WAYNE_STU | B81: ([MPO_NAME]='Wayne County' AND [FUNC_CLASS]='16') OR ([MPO_NAME]='Wayne County' AND [FUNC_CLASS]='17')
A82: N TIER_185 | B82: ([MPO_NAME]='Northern Tier RPO' AND [DISTRICT]='04') AND [INTERSTATE]='N'
A83: WAYNE_STP | B83: ([MPO_NAME]='Wayne County' AND [FUNC_CLASS]='06') OR ([MPO_NAME]='Wayne County' AND [FUNC_CLASS]='07') OR ([MPO_NAME]='Wayne County' AND [FUNC_CLASS]='16') OR ([MPO_NAME]='Wayne County' AND [FUNC_CLASS]='17')
A84: NEPA_581 | B84: ([MPO_NAME]='NEPA RPO' AND [DISTRICT]='04') AND [INTERSTATE]='N'
A85: LLTS_STU | B85: ([MPO_NAME]='Scranton-WB MPO' AND [FUNC_CLASS]='16') OR ([MPO_NAME]='Scranton-WB MPO' AND [FUNC_CLASS]='17')
A86: LLTS_BOF | B86: ([MPO_NAME]='Scranton-WB MPO' AND [FUNC_CLASS]='08' AND [LENGTH]>='20') OR ([MPO_NAME]='Scranton-WB MPO' AND [FUNC_CLASS]='09' AND [LENGTH]>='20') OR ([MPO_NAME]='Scranton-WB MPO' AND [FUNC_CLASS]='19' AND [LENGTH]>='20')
A87: N TIER_NHPP | B87: ([MPO_NAME]='Northern Tier RPO' AND [DISTRICT]='04' AND [FUNC_CLASS]='02') OR ([MPO_NAME]='Northern Tier RPO' AND [DISTRICT]='04' AND [FUNC_CLASS]='12') OR ([MPO_NAME]='Northern Tier RPO' AND [DISTRICT]='04' AND [FUNC_CLASS]='14')
A88: NEPA_SPIKE | B88: ([MPO_NAME]='NEPA RPO' AND [DISTRICT]='04')
A89: N TIER_581 | B89: ([MPO_NAME]='Northern Tier RPO' AND [DISTRICT]='04') AND [INTERSTATE]='N'
... A117: N TIER_SPIKE | B117: ([MPO_NAME]='Northern Tier RPO' AND [DISTRICT]='04')

Sheet Legend
A1: Color Key | B1: Color Key | I1: Tab Definitions
E2: Posted / Closed Bridge Condition Range | F2: Posted / Closed Bridge Condition Range | G2: Posted / Closed Bridge Condition Range | I2: Parameters: Summary of simulation data inputs.
A3: Work Done Columns | B3: Work Done Columns | E3: Posted / Closed Bridge Condition Range | F3: Posted / Closed Bridge Condition Range | G3: Posted / Closed Bridge Condition Range | I3: Bridge Data: Complete recommended treatments for all structures throughout the analysis period
A4: Bridge project is being cashed flowed. | B4: Bridge project is being cashed flowed. | E4: Posted Condition < | F4: Posted Condition < | G4: 4.1 | I4: Funded Treatment List: Provides a list of funded treatments for the analysis period
A5: MPMS Project is being Cash Flowed. | B5: MPMS Project is being Cash Flowed. | E5: Closed Condition < | F5: Closed Condition < | G5: 3 | I5: Unfunded Treatment — Final List: First year of unfunded treatments by BRKEY.
I6: Unfunded Treatment — Time: List of unfunded treatments through time.
A7: Details Columns | B7: Details Columns | I7: Bridge Work Summary: Summary of projected costs for treatments throughout simulation period for all structures. Summary of projected condition changes throughout analysis period.
A8: Bridge project is being cashed flowed. | B8: Bridge project is being cashed flowed. | E8: Condition Limits | F8: Condition Limits | G8: Condition Limits | I8: Bridge Work Summary by Budget: Summary of projected costs for treatments throughout simulation period for all bridges by specific budget.
A9: MPMS Project is being Cash Flowed. | B9: MPMS Project is being Cash Flowed. | E9: Good Min Cond > | F9: Good Min Cond > | G9: 7 | I9: District Totals: Projected spending per district each year throughout analysis period.
A10: Min Condition is less than or equal to 3.5 | B10: Min Condition is less than or equal to 3.5 | E10: Poor Min Cond < | F10: Poor Min Cond < | G10: 5 | I10: NHS Count: Graph of projected bridge conditions for structures on the NHS by bridge count.
I11: NHS DA: Graph of projected bridge conditions for structures on the NHS by deck area.
I12: Non-NHS Count: Graph of projected bridge conditions for structures not on the NHS by bridge count.
A13: example: | I13: Non-NHS DA: Graph of projected bridge conditions for structures not on the NHS by deck area.
I14: Combined Count: Graph of projected bridge conditions for all structures by bridge count.
A15: 2021 | B15: 2022 | C15: 2023 | I15: Combined DA: Graph of projected bridge conditions for all structures by deck area.
A16: Brdg_Repl | B16: Brdg_Repl | C16: Brdg_Repl | I16: Poor Count: Graph showing projected number of structures to be in poor condition throughout analysis period.
A17: Bridge replacement is cash flowed over 3 years. | I17: Poor DA: Graph showing projected deck area of structures to be in poor condition throughout analysis period.
I18: Poor DA by BPN: Graph showing projected deck area of structures to be in poor condition, by BPN, throughout analysis period.
I19: Posted BPN Count: Graph showing projected number of structures to be posted based on the GCR Super and not by load capacity calculations. Since it is not possible to perform load calculations at this level, this can be considered a proxy and should be used only for only long-term evaluation.
I20: Posted BPN DA: Graph showing projected deck area of structures to be posted based on the GCR Super and not by load capacity calculations. Since it is not possible to perform load calculations at this level, this can be considered a proxy and should be used only for long-term evaluation.
I21: Closed BPN Count: Graph showing the projected number of structures to be closed based on the min GCR. In order to be considered closed the Min GCR value must be less than 3
I22: Closed BPN DA: Graph showing projected deck area to be closed based on the min GCR. In order to be considered closed the Min GCR value must be less than 3
I23: Combined Posted and Closed: Graph showing the combined number of structures that are projected to be closed and posted
I24: $ Needed DA BPN: Graph showing the amount of money spent by BPN
A26: • For individual bridge column definitions, please see Pub 100A | B26: • For individual bridge column definitions, please see Pub 100A | C26: • For individual bridge column definitions, please see Pub 100A | D26: • For individual bridge column definitions, please see Pub 100A | E26: • For individual bridge column definitions, please see Pub 100A | F26: • For individual bridge column definitions, please see Pub 100A | G26: • For individual bridge column definitions, please see Pub 100A | H26: • For individual bridge column definitions, please see Pub 100A
A27: • For other publications please see below, | B27: • For other publications please see below, | C27: • For other publications please see below, | D27: • For other publications please see below, | E27: • For other publications please see below, | F27: • For other publications please see below, | G27: • For other publications please see below, | H27: • For other publications please see below,
A28: ==HYPERLINK("https://docs.penndot.pa.gov/Public/Bureaus/BOO/AMPortal/", "PennDOT-Asset Management Portal") | B28: ==HYPERLINK("https://docs.penndot.pa.gov/Public/Bureaus/BOO/AMPortal/", "PennDOT-Asset Management Portal") | C28: ==HYPERLINK("https://docs.penndot.pa.gov/Public/Bureaus/BOO/AMPortal/", "PennDOT-Asset Management Portal") | D28: ==HYPERLINK("https://docs.penndot.pa.gov/Public/Bureaus/BOO/AMPortal/", "PennDOT-Asset Management Portal") | E28: ==HYPERLINK("https://docs.penndot.pa.gov/Public/Bureaus/BOO/AMPortal/", "PennDOT-Asset Management Portal") | F28: ==HYPERLINK("https://docs.penndot.pa.gov/Public/Bureaus/BOO/AMPortal/", "PennDOT-Asset Management Portal") | G28: ==HYPERLINK("https://docs.penndot.pa.gov/Public/Bureaus/BOO/AMPortal/", "PennDOT-Asset Management Portal") | H28: ==HYPERLINK("https://docs.penndot.pa.gov/Public/Bureaus/BOO/AMPortal/", "PennDOT-Asset Management Portal")
A29: This software is provided on “as is” basis, and by using the software you acknowledge and agree that you are doing so at your own risk. While reasonable efforts have been made to ensure the accuracy and reliability of the software, no guarantee is made regarding the correctness, completeness, or suitability of any models, predictions or results it generates. Under no circumstances shall the software developers or distributors be held liable for any loss, damage, or other consequences arising from the use of the software or its outputs. Users assume full responsibility for any decisions made based on software use. | B29: This software is provided on “as is” basis, and by using the software you acknowledge and agree that you are doing so at your own risk. While reasonable efforts have been made to ensure the accuracy and reliability of the software, no guarantee is made regarding the correctness, completeness, or suitability of any models, predictions or results it generates. Under no circumstances shall the software developers or distributors be held liable for any loss, damage, or other consequences arising from the use of the software or its outputs. Users assume full responsibility for any decisions made based on software use. | C29: This software is provided on “as is” basis, and by using the software you acknowledge and agree that you are doing so at your own risk. While reasonable efforts have been made to ensure the accuracy and reliability of the software, no guarantee is made regarding the correctness, completeness, or suitability of any models, predictions or results it generates. Under no circumstances shall the software developers or distributors be held liable for any loss, damage, or other consequences arising from the use of the software or its outputs. Users assume full responsibility for any decisions made based on software use. | D29: This software is provided on “as is” basis, and by using the software you acknowledge and agree that you are doing so at your own risk. While reasonable efforts have been made to ensure the accuracy and reliability of the software, no guarantee is made regarding the correctness, completeness, or suitability of any models, predictions or results it generates. Under no circumstances shall the software developers or distributors be held liable for any loss, damage, or other consequences arising from the use of the software or its outputs. Users assume full responsibility for any decisions made based on software use. | E29: This software is provided on “as is” basis, and by using the software you acknowledge and agree that you are doing so at your own risk. While reasonable efforts have been made to ensure the accuracy and reliability of the software, no guarantee is made regarding the correctness, completeness, or suitability of any models, predictions or results it generates. Under no circumstances shall the software developers or distributors be held liable for any loss, damage, or other consequences arising from the use of the software or its outputs. Users assume full responsibility for any decisions made based on software use. | F29: This software is provided on “as is” basis, and by using the software you acknowledge and agree that you are doing so at your own risk. While reasonable efforts have been made to ensure the accuracy and reliability of the software, no guarantee is made regarding the correctness, completeness, or suitability of any models, predictions or results it generates. Under no circumstances shall the software developers or distributors be held liable for any loss, damage, or other consequences arising from the use of the software or its outputs. Users assume full responsibility for any decisions made based on software use. | G29: This software is provided on “as is” basis, and by using the software you acknowledge and agree that you are doing so at your own risk. While reasonable efforts have been made to ensure the accuracy and reliability of the software, no guarantee is made regarding the correctness, completeness, or suitability of any models, predictions or results it generates. Under no circumstances shall the software developers or distributors be held liable for any loss, damage, or other consequences arising from the use of the software or its outputs. Users assume full responsibility for any decisions made based on software use. | H29: This software is provided on “as is” basis, and by using the software you acknowledge and agree that you are doing so at your own risk. While reasonable efforts have been made to ensure the accuracy and reliability of the software, no guarantee is made regarding the correctness, completeness, or suitability of any models, predictions or results it generates. Under no circumstances shall the software developers or distributors be held liable for any loss, damage, or other consequences arising from the use of the software or its outputs. Users assume full responsibility for any decisions made based on software use.
A30: This software is provided on “as is” basis, and by using the software you acknowledge and agree that you are doing so at your own risk. While reasonable efforts have been made to ensure the accuracy and reliability of the software, no guarantee is made regarding the correctness, completeness, or suitability of any models, predictions or results it generates. Under no circumstances shall the software developers or distributors be held liable for any loss, damage, or other consequences arising from the use of the software or its outputs. Users assume full responsibility for any decisions made based on software use. | B30: This software is provided on “as is” basis, and by using the software you acknowledge and agree that you are doing so at your own risk. While reasonable efforts have been made to ensure the accuracy and reliability of the software, no guarantee is made regarding the correctness, completeness, or suitability of any models, predictions or results it generates. Under no circumstances shall the software developers or distributors be held liable for any loss, damage, or other consequences arising from the use of the software or its outputs. Users assume full responsibility for any decisions made based on software use. | C30: This software is provided on “as is” basis, and by using the software you acknowledge and agree that you are doing so at your own risk. While reasonable efforts have been made to ensure the accuracy and reliability of the software, no guarantee is made regarding the correctness, completeness, or suitability of any models, predictions or results it generates. Under no circumstances shall the software developers or distributors be held liable for any loss, damage, or other consequences arising from the use of the software or its outputs. Users assume full responsibility for any decisions made based on software use. | D30: This software is provided on “as is” basis, and by using the software you acknowledge and agree that you are doing so at your own risk. While reasonable efforts have been made to ensure the accuracy and reliability of the software, no guarantee is made regarding the correctness, completeness, or suitability of any models, predictions or results it generates. Under no circumstances shall the software developers or distributors be held liable for any loss, damage, or other consequences arising from the use of the software or its outputs. Users assume full responsibility for any decisions made based on software use. | E30: This software is provided on “as is” basis, and by using the software you acknowledge and agree that you are doing so at your own risk. While reasonable efforts have been made to ensure the accuracy and reliability of the software, no guarantee is made regarding the correctness, completeness, or suitability of any models, predictions or results it generates. Under no circumstances shall the software developers or distributors be held liable for any loss, damage, or other consequences arising from the use of the software or its outputs. Users assume full responsibility for any decisions made based on software use. | F30: This software is provided on “as is” basis, and by using the software you acknowledge and agree that you are doing so at your own risk. While reasonable efforts have been made to ensure the accuracy and reliability of the software, no guarantee is made regarding the correctness, completeness, or suitability of any models, predictions or results it generates. Under no circumstances shall the software developers or distributors be held liable for any loss, damage, or other consequences arising from the use of the software or its outputs. Users assume full responsibility for any decisions made based on software use. | G30: This software is provided on “as is” basis, and by using the software you acknowledge and agree that you are doing so at your own risk. While reasonable efforts have been made to ensure the accuracy and reliability of the software, no guarantee is made regarding the correctness, completeness, or suitability of any models, predictions or results it generates. Under no circumstances shall the software developers or distributors be held liable for any loss, damage, or other consequences arising from the use of the software or its outputs. Users assume full responsibility for any decisions made based on software use. | H30: This software is provided on “as is” basis, and by using the software you acknowledge and agree that you are doing so at your own risk. While reasonable efforts have been made to ensure the accuracy and reliability of the software, no guarantee is made regarding the correctness, completeness, or suitability of any models, predictions or results it generates. Under no circumstances shall the software developers or distributors be held liable for any loss, damage, or other consequences arising from the use of the software or its outputs. Users assume full responsibility for any decisions made based on software use.
A31: This software is provided on “as is” basis, and by using the software you acknowledge and agree that you are doing so at your own risk. While reasonable efforts have been made to ensure the accuracy and reliability of the software, no guarantee is made regarding the correctness, completeness, or suitability of any models, predictions or results it generates. Under no circumstances shall the software developers or distributors be held liable for any loss, damage, or other consequences arising from the use of the software or its outputs. Users assume full responsibility for any decisions made based on software use. | B31: This software is provided on “as is” basis, and by using the software you acknowledge and agree that you are doing so at your own risk. While reasonable efforts have been made to ensure the accuracy and reliability of the software, no guarantee is made regarding the correctness, completeness, or suitability of any models, predictions or results it generates. Under no circumstances shall the software developers or distributors be held liable for any loss, damage, or other consequences arising from the use of the software or its outputs. Users assume full responsibility for any decisions made based on software use. | C31: This software is provided on “as is” basis, and by using the software you acknowledge and agree that you are doing so at your own risk. While reasonable efforts have been made to ensure the accuracy and reliability of the software, no guarantee is made regarding the correctness, completeness, or suitability of any models, predictions or results it generates. Under no circumstances shall the software developers or distributors be held liable for any loss, damage, or other consequences arising from the use of the software or its outputs. Users assume full responsibility for any decisions made based on software use. | D31: This software is provided on “as is” basis, and by using the software you acknowledge and agree that you are doing so at your own risk. While reasonable efforts have been made to ensure the accuracy and reliability of the software, no guarantee is made regarding the correctness, completeness, or suitability of any models, predictions or results it generates. Under no circumstances shall the software developers or distributors be held liable for any loss, damage, or other consequences arising from the use of the software or its outputs. Users assume full responsibility for any decisions made based on software use. | E31: This software is provided on “as is” basis, and by using the software you acknowledge and agree that you are doing so at your own risk. While reasonable efforts have been made to ensure the accuracy and reliability of the software, no guarantee is made regarding the correctness, completeness, or suitability of any models, predictions or results it generates. Under no circumstances shall the software developers or distributors be held liable for any loss, damage, or other consequences arising from the use of the software or its outputs. Users assume full responsibility for any decisions made based on software use. | F31: This software is provided on “as is” basis, and by using the software you acknowledge and agree that you are doing so at your own risk. While reasonable efforts have been made to ensure the accuracy and reliability of the software, no guarantee is made regarding the correctness, completeness, or suitability of any models, predictions or results it generates. Under no circumstances shall the software developers or distributors be held liable for any loss, damage, or other consequences arising from the use of the software or its outputs. Users assume full responsibility for any decisions made based on software use. | G31: This software is provided on “as is” basis, and by using the software you acknowledge and agree that you are doing so at your own risk. While reasonable efforts have been made to ensure the accuracy and reliability of the software, no guarantee is made regarding the correctness, completeness, or suitability of any models, predictions or results it generates. Under no circumstances shall the software developers or distributors be held liable for any loss, damage, or other consequences arising from the use of the software or its outputs. Users assume full responsibility for any decisions made based on software use. | H31: This software is provided on “as is” basis, and by using the software you acknowledge and agree that you are doing so at your own risk. While reasonable efforts have been made to ensure the accuracy and reliability of the software, no guarantee is made regarding the correctness, completeness, or suitability of any models, predictions or results it generates. Under no circumstances shall the software developers or distributors be held liable for any loss, damage, or other consequences arising from the use of the software or its outputs. Users assume full responsibility for any decisions made based on software use.
A32: This software is provided on “as is” basis, and by using the software you acknowledge and agree that you are doing so at your own risk. While reasonable efforts have been made to ensure the accuracy and reliability of the software, no guarantee is made regarding the correctness, completeness, or suitability of any models, predictions or results it generates. Under no circumstances shall the software developers or distributors be held liable for any loss, damage, or other consequences arising from the use of the software or its outputs. Users assume full responsibility for any decisions made based on software use. | B32: This software is provided on “as is” basis, and by using the software you acknowledge and agree that you are doing so at your own risk. While reasonable efforts have been made to ensure the accuracy and reliability of the software, no guarantee is made regarding the correctness, completeness, or suitability of any models, predictions or results it generates. Under no circumstances shall the software developers or distributors be held liable for any loss, damage, or other consequences arising from the use of the software or its outputs. Users assume full responsibility for any decisions made based on software use. | C32: This software is provided on “as is” basis, and by using the software you acknowledge and agree that you are doing so at your own risk. While reasonable efforts have been made to ensure the accuracy and reliability of the software, no guarantee is made regarding the correctness, completeness, or suitability of any models, predictions or results it generates. Under no circumstances shall the software developers or distributors be held liable for any loss, damage, or other consequences arising from the use of the software or its outputs. Users assume full responsibility for any decisions made based on software use. | D32: This software is provided on “as is” basis, and by using the software you acknowledge and agree that you are doing so at your own risk. While reasonable efforts have been made to ensure the accuracy and reliability of the software, no guarantee is made regarding the correctness, completeness, or suitability of any models, predictions or results it generates. Under no circumstances shall the software developers or distributors be held liable for any loss, damage, or other consequences arising from the use of the software or its outputs. Users assume full responsibility for any decisions made based on software use. | E32: This software is provided on “as is” basis, and by using the software you acknowledge and agree that you are doing so at your own risk. While reasonable efforts have been made to ensure the accuracy and reliability of the software, no guarantee is made regarding the correctness, completeness, or suitability of any models, predictions or results it generates. Under no circumstances shall the software developers or distributors be held liable for any loss, damage, or other consequences arising from the use of the software or its outputs. Users assume full responsibility for any decisions made based on software use. | F32: This software is provided on “as is” basis, and by using the software you acknowledge and agree that you are doing so at your own risk. While reasonable efforts have been made to ensure the accuracy and reliability of the software, no guarantee is made regarding the correctness, completeness, or suitability of any models, predictions or results it generates. Under no circumstances shall the software developers or distributors be held liable for any loss, damage, or other consequences arising from the use of the software or its outputs. Users assume full responsibility for any decisions made based on software use. | G32: This software is provided on “as is” basis, and by using the software you acknowledge and agree that you are doing so at your own risk. While reasonable efforts have been made to ensure the accuracy and reliability of the software, no guarantee is made regarding the correctness, completeness, or suitability of any models, predictions or results it generates. Under no circumstances shall the software developers or distributors be held liable for any loss, damage, or other consequences arising from the use of the software or its outputs. Users assume full responsibility for any decisions made based on software use. | H32: This software is provided on “as is” basis, and by using the software you acknowledge and agree that you are doing so at your own risk. While reasonable efforts have been made to ensure the accuracy and reliability of the software, no guarantee is made regarding the correctness, completeness, or suitability of any models, predictions or results it generates. Under no circumstances shall the software developers or distributors be held liable for any loss, damage, or other consequences arising from the use of the software or its outputs. Users assume full responsibility for any decisions made based on software use.
A33: This software is provided on “as is” basis, and by using the software you acknowledge and agree that you are doing so at your own risk. While reasonable efforts have been made to ensure the accuracy and reliability of the software, no guarantee is made regarding the correctness, completeness, or suitability of any models, predictions or results it generates. Under no circumstances shall the software developers or distributors be held liable for any loss, damage, or other consequences arising from the use of the software or its outputs. Users assume full responsibility for any decisions made based on software use. | B33: This software is provided on “as is” basis, and by using the software you acknowledge and agree that you are doing so at your own risk. While reasonable efforts have been made to ensure the accuracy and reliability of the software, no guarantee is made regarding the correctness, completeness, or suitability of any models, predictions or results it generates. Under no circumstances shall the software developers or distributors be held liable for any loss, damage, or other consequences arising from the use of the software or its outputs. Users assume full responsibility for any decisions made based on software use. | C33: This software is provided on “as is” basis, and by using the software you acknowledge and agree that you are doing so at your own risk. While reasonable efforts have been made to ensure the accuracy and reliability of the software, no guarantee is made regarding the correctness, completeness, or suitability of any models, predictions or results it generates. Under no circumstances shall the software developers or distributors be held liable for any loss, damage, or other consequences arising from the use of the software or its outputs. Users assume full responsibility for any decisions made based on software use. | D33: This software is provided on “as is” basis, and by using the software you acknowledge and agree that you are doing so at your own risk. While reasonable efforts have been made to ensure the accuracy and reliability of the software, no guarantee is made regarding the correctness, completeness, or suitability of any models, predictions or results it generates. Under no circumstances shall the software developers or distributors be held liable for any loss, damage, or other consequences arising from the use of the software or its outputs. Users assume full responsibility for any decisions made based on software use. | E33: This software is provided on “as is” basis, and by using the software you acknowledge and agree that you are doing so at your own risk. While reasonable efforts have been made to ensure the accuracy and reliability of the software, no guarantee is made regarding the correctness, completeness, or suitability of any models, predictions or results it generates. Under no circumstances shall the software developers or distributors be held liable for any loss, damage, or other consequences arising from the use of the software or its outputs. Users assume full responsibility for any decisions made based on software use. | F33: This software is provided on “as is” basis, and by using the software you acknowledge and agree that you are doing so at your own risk. While reasonable efforts have been made to ensure the accuracy and reliability of the software, no guarantee is made regarding the correctness, completeness, or suitability of any models, predictions or results it generates. Under no circumstances shall the software developers or distributors be held liable for any loss, damage, or other consequences arising from the use of the software or its outputs. Users assume full responsibility for any decisions made based on software use. | G33: This software is provided on “as is” basis, and by using the software you acknowledge and agree that you are doing so at your own risk. While reasonable efforts have been made to ensure the accuracy and reliability of the software, no guarantee is made regarding the correctness, completeness, or suitability of any models, predictions or results it generates. Under no circumstances shall the software developers or distributors be held liable for any loss, damage, or other consequences arising from the use of the software or its outputs. Users assume full responsibility for any decisions made based on software use. | H33: This software is provided on “as is” basis, and by using the software you acknowledge and agree that you are doing so at your own risk. While reasonable efforts have been made to ensure the accuracy and reliability of the software, no guarantee is made regarding the correctness, completeness, or suitability of any models, predictions or results it generates. Under no circumstances shall the software developers or distributors be held liable for any loss, damage, or other consequences arising from the use of the software or its outputs. Users assume full responsibility for any decisions made based on software use.
A34: This software is provided on “as is” basis, and by using the software you acknowledge and agree that you are doing so at your own risk. While reasonable efforts have been made to ensure the accuracy and reliability of the software, no guarantee is made regarding the correctness, completeness, or suitability of any models, predictions or results it generates. Under no circumstances shall the software developers or distributors be held liable for any loss, damage, or other consequences arising from the use of the software or its outputs. Users assume full responsibility for any decisions made based on software use. | B34: This software is provided on “as is” basis, and by using the software you acknowledge and agree that you are doing so at your own risk. While reasonable efforts have been made to ensure the accuracy and reliability of the software, no guarantee is made regarding the correctness, completeness, or suitability of any models, predictions or results it generates. Under no circumstances shall the software developers or distributors be held liable for any loss, damage, or other consequences arising from the use of the software or its outputs. Users assume full responsibility for any decisions made based on software use. | C34: This software is provided on “as is” basis, and by using the software you acknowledge and agree that you are doing so at your own risk. While reasonable efforts have been made to ensure the accuracy and reliability of the software, no guarantee is made regarding the correctness, completeness, or suitability of any models, predictions or results it generates. Under no circumstances shall the software developers or distributors be held liable for any loss, damage, or other consequences arising from the use of the software or its outputs. Users assume full responsibility for any decisions made based on software use. | D34: This software is provided on “as is” basis, and by using the software you acknowledge and agree that you are doing so at your own risk. While reasonable efforts have been made to ensure the accuracy and reliability of the software, no guarantee is made regarding the correctness, completeness, or suitability of any models, predictions or results it generates. Under no circumstances shall the software developers or distributors be held liable for any loss, damage, or other consequences arising from the use of the software or its outputs. Users assume full responsibility for any decisions made based on software use. | E34: This software is provided on “as is” basis, and by using the software you acknowledge and agree that you are doing so at your own risk. While reasonable efforts have been made to ensure the accuracy and reliability of the software, no guarantee is made regarding the correctness, completeness, or suitability of any models, predictions or results it generates. Under no circumstances shall the software developers or distributors be held liable for any loss, damage, or other consequences arising from the use of the software or its outputs. Users assume full responsibility for any decisions made based on software use. | F34: This software is provided on “as is” basis, and by using the software you acknowledge and agree that you are doing so at your own risk. While reasonable efforts have been made to ensure the accuracy and reliability of the software, no guarantee is made regarding the correctness, completeness, or suitability of any models, predictions or results it generates. Under no circumstances shall the software developers or distributors be held liable for any loss, damage, or other consequences arising from the use of the software or its outputs. Users assume full responsibility for any decisions made based on software use. | G34: This software is provided on “as is” basis, and by using the software you acknowledge and agree that you are doing so at your own risk. While reasonable efforts have been made to ensure the accuracy and reliability of the software, no guarantee is made regarding the correctness, completeness, or suitability of any models, predictions or results it generates. Under no circumstances shall the software developers or distributors be held liable for any loss, damage, or other consequences arising from the use of the software or its outputs. Users assume full responsibility for any decisions made based on software use. | H34: This software is provided on “as is” basis, and by using the software you acknowledge and agree that you are doing so at your own risk. While reasonable efforts have been made to ensure the accuracy and reliability of the software, no guarantee is made regarding the correctness, completeness, or suitability of any models, predictions or results it generates. Under no circumstances shall the software developers or distributors be held liable for any loss, damage, or other consequences arising from the use of the software or its outputs. Users assume full responsibility for any decisions made based on software use.
A35: This software is provided on “as is” basis, and by using the software you acknowledge and agree that you are doing so at your own risk. While reasonable efforts have been made to ensure the accuracy and reliability of the software, no guarantee is made regarding the correctness, completeness, or suitability of any models, predictions or results it generates. Under no circumstances shall the software developers or distributors be held liable for any loss, damage, or other consequences arising from the use of the software or its outputs. Users assume full responsibility for any decisions made based on software use. | B35: This software is provided on “as is” basis, and by using the software you acknowledge and agree that you are doing so at your own risk. While reasonable efforts have been made to ensure the accuracy and reliability of the software, no guarantee is made regarding the correctness, completeness, or suitability of any models, predictions or results it generates. Under no circumstances shall the software developers or distributors be held liable for any loss, damage, or other consequences arising from the use of the software or its outputs. Users assume full responsibility for any decisions made based on software use. | C35: This software is provided on “as is” basis, and by using the software you acknowledge and agree that you are doing so at your own risk. While reasonable efforts have been made to ensure the accuracy and reliability of the software, no guarantee is made regarding the correctness, completeness, or suitability of any models, predictions or results it generates. Under no circumstances shall the software developers or distributors be held liable for any loss, damage, or other consequences arising from the use of the software or its outputs. Users assume full responsibility for any decisions made based on software use. | D35: This software is provided on “as is” basis, and by using the software you acknowledge and agree that you are doing so at your own risk. While reasonable efforts have been made to ensure the accuracy and reliability of the software, no guarantee is made regarding the correctness, completeness, or suitability of any models, predictions or results it generates. Under no circumstances shall the software developers or distributors be held liable for any loss, damage, or other consequences arising from the use of the software or its outputs. Users assume full responsibility for any decisions made based on software use. | E35: This software is provided on “as is” basis, and by using the software you acknowledge and agree that you are doing so at your own risk. While reasonable efforts have been made to ensure the accuracy and reliability of the software, no guarantee is made regarding the correctness, completeness, or suitability of any models, predictions or results it generates. Under no circumstances shall the software developers or distributors be held liable for any loss, damage, or other consequences arising from the use of the software or its outputs. Users assume full responsibility for any decisions made based on software use. | F35: This software is provided on “as is” basis, and by using the software you acknowledge and agree that you are doing so at your own risk. While reasonable efforts have been made to ensure the accuracy and reliability of the software, no guarantee is made regarding the correctness, completeness, or suitability of any models, predictions or results it generates. Under no circumstances shall the software developers or distributors be held liable for any loss, damage, or other consequences arising from the use of the software or its outputs. Users assume full responsibility for any decisions made based on software use. | G35: This software is provided on “as is” basis, and by using the software you acknowledge and agree that you are doing so at your own risk. While reasonable efforts have been made to ensure the accuracy and reliability of the software, no guarantee is made regarding the correctness, completeness, or suitability of any models, predictions or results it generates. Under no circumstances shall the software developers or distributors be held liable for any loss, damage, or other consequences arising from the use of the software or its outputs. Users assume full responsibility for any decisions made based on software use. | H35: This software is provided on “as is” basis, and by using the software you acknowledge and agree that you are doing so at your own risk. While reasonable efforts have been made to ensure the accuracy and reliability of the software, no guarantee is made regarding the correctness, completeness, or suitability of any models, predictions or results it generates. Under no circumstances shall the software developers or distributors be held liable for any loss, damage, or other consequences arising from the use of the software or its outputs. Users assume full responsibility for any decisions made based on software use.

Sheet Bridge Data
A2: Asset ID | E2: Ownership | O2: Structure | W2: Network | AB2: Asset Attributes | AO2: Funding
A3: Internet Report | B3: Bridge (B/C) | C3: BridgeID (5A01) | D3: BRKey (5A03) | E3: District (5A04) | F3: County (5A05) | G3: Owner Code (5A21) | H3: Submitting Agency (6A06) | I3: Planning Partner (5A13) | J3: City / Town / Place (5A06) | K3: Feature Intersected (5A07) | L3: Facility Carried (5A08) | M3: Location / Structure Name (5A02) | N3: Maintenance Responsibility (5A20) | O3: Structure Length (5B18) | P3: Deck Area (5B19) | Q3: Large Bridge | R3: Span Type | S3: Bridge Family | T3: Struct Type (6A26-29) | U3: Fractural Critical | V3: Parallel Structure (5E02) | W3: Functional Class (5C22) | X3: NHS (5C29) | Y3: NBIS Len (5E01) | Z3: BPN (6A19) | AA3: Interstate | AB3: Deck Surface Type (5B02) | AC3: Wearing Surface Cond (6B40) | AD3: Paint Cond (6B36) | AE3: Paint Ext (6B37) | AF3: Year Built (5A15) | AG3: Age | AH3: ADTT (5C10) | AI3: Risk Score | AJ3: Detour Length (5C15) | AK3: Posting Status (VP02) | AL3: Suff Rating (4A13) | AM3: Leaking Joints | AN3: Scour Critical | AO3: HBRR Elig (6B41) | AP3: P3 (5E24) | AQ3: Federal Aid (6C06) | AR3: Bridge Funding | AX3: Work Done 2026 | AZ3: Work Done 2027 | BB3: Work Done 2028 | BD3: Work Done 2029 | BF3: Work Done 2030 | BH3: Work Done 2031 | BJ3: Work Done 2032 | BL3: Work Done 2033 | BN3: Work Done 2034 | BP3: Work Done 2035 | BR3: Work Done 2036 | BT3: Work Done Y/N | BU3: Work Done > 1 | BV3: Total Work Done > 1 | BW3: Poor On/Off Rate | CI3: 2025 | CU3: 2026 | DO3: 2027 | EI3: 2028 | FC3: 2029 | FW3: 2030 | GQ3: 2031 | HK3: 2032 | IE3: 2033 | IY3: 2034 | JS3: 2035 | KM3: 2036
AR4: NHPP | AS4: STP | AT4: BOF | AU4: BRIP | AV4: State | AW4: N/A | CI4: GCR Deck | CJ4: GCR Sup | CK4: GCR Sub | CL4: GCR Culv | CM4: Deck Dur | CN4: Super Dur | CO4: Sub Dur | CP4: Culv Dur | CQ4: Min GCR | CR4: Poor | CS4: Posted | CU4: GCR Deck | CV4: GCR Sup | CW4: GCR Sub | CX4: GCR Culv | CY4: Deck Dur | CZ4: Super Dur | DA4: Sub Dur | DB4: Culv Dur | DC4: Min GCR | DD4: Poor | DE4: Posted | DF4: Project Pick | DG4: Project Id | DH4: Budget | DI4: Recommended Treatment | DJ4: Cost | DK4: Superseded Treatments | DL4: FHWA Work Types | DM4: Comments | DO4: GCR Deck | DP4: GCR Sup | DQ4: GCR Sub | DR4: GCR Culv | DS4: Deck Dur | DT4: Super Dur | DU4: Sub Dur | DV4: Culv Dur | DW4: Min GCR | DX4: Poor | DY4: Posted | DZ4: Project Pick | EA4: Project Id | EB4: Budget | EC4: Recommended Treatment | ED4: Cost | EE4: Superseded Treatments | EF4: FHWA Work Types | EG4: Comments | EI4: GCR Deck | EJ4: GCR Sup | EK4: GCR Sub | EL4: GCR Culv | EM4: Deck Dur | EN4: Super Dur | EO4: Sub Dur | EP4: Culv Dur | EQ4: Min GCR | ER4: Poor | ES4: Posted | ET4: Project Pick | EU4: Project Id | EV4: Budget | EW4: Recommended Treatment | EX4: Cost | EY4: Superseded Treatments | EZ4: FHWA Work Types | FA4: Comments | FC4: GCR Deck | FD4: GCR Sup | FE4: GCR Sub | FF4: GCR Culv | FG4: Deck Dur | FH4: Super Dur | FI4: Sub Dur | FJ4: Culv Dur | FK4: Min GCR | FL4: Poor | FM4: Posted | FN4: Project Pick | FO4: Project Id | FP4: Budget | FQ4: Recommended Treatment | FR4: Cost | FS4: Superseded Treatments | FT4: FHWA Work Types | FU4: Comments | FW4: GCR Deck | FX4: GCR Sup | FY4: GCR Sub | FZ4: GCR Culv | GA4: Deck Dur | GB4: Super Dur | GC4: Sub Dur | GD4: Culv Dur | GE4: Min GCR | GF4: Poor | GG4: Posted | GH4: Project Pick | GI4: Project Id | GJ4: Budget | GK4: Recommended Treatment | GL4: Cost | GM4: Superseded Treatments | GN4: FHWA Work Types | GO4: Comments | GQ4: GCR Deck | GR4: GCR Sup | GS4: GCR Sub | GT4: GCR Culv | GU4: Deck Dur | GV4: Super Dur | GW4: Sub Dur | GX4: Culv Dur | GY4: Min GCR | GZ4: Poor | HA4: Posted | HB4: Project Pick | HC4: Project Id | HD4: Budget | HE4: Recommended Treatment | HF4: Cost | HG4: Superseded Treatments | HH4: FHWA Work Types | HI4: Comments | HK4: GCR Deck | HL4: GCR Sup | HM4: GCR Sub | HN4: GCR Culv | HO4: Deck Dur | HP4: Super Dur | HQ4: Sub Dur | HR4: Culv Dur | HS4: Min GCR | HT4: Poor | HU4: Posted | HV4: Project Pick | HW4: Project Id | HX4: Budget | HY4: Recommended Treatment | HZ4: Cost | IA4: Superseded Treatments | IB4: FHWA Work Types | IC4: Comments | IE4: GCR Deck | IF4: GCR Sup | IG4: GCR Sub | IH4: GCR Culv | II4: Deck Dur | IJ4: Super Dur | IK4: Sub Dur | IL4: Culv Dur | IM4: Min GCR | IN4: Poor | IO4: Posted | IP4: Project Pick | IQ4: Project Id | IR4: Budget | IS4: Recommended Treatment | IT4: Cost | IU4: Superseded Treatments | IV4: FHWA Work Types | IW4: Comments | IY4: GCR Deck | IZ4: GCR Sup | JA4: GCR Sub | JB4: GCR Culv | JC4: Deck Dur | JD4: Super Dur | JE4: Sub Dur | JF4: Culv Dur | JG4: Min GCR | JH4: Poor | JI4: Posted | JJ4: Project Pick | JK4: Project Id | JL4: Budget | JM4: Recommended Treatment | JN4: Cost | JO4: Superseded Treatments | JP4: FHWA Work Types | JQ4: Comments | JS4: GCR Deck | JT4: GCR Sup | JU4: GCR Sub | JV4: GCR Culv | JW4: Deck Dur | JX4: Super Dur | JY4: Sub Dur | JZ4: Culv Dur | KA4: Min GCR | KB4: Poor | KC4: Posted | KD4: Project Pick | KE4: Project Id | KF4: Budget | KG4: Recommended Treatment | KH4: Cost | KI4: Superseded Treatments | KJ4: FHWA Work Types | KK4: Comments | KM4: GCR Deck | KN4: GCR Sup | KO4: GCR Sub | KP4: GCR Culv | KQ4: Deck Dur | KR4: Super Dur | KS4: Sub Dur | KT4: Culv Dur | KU4: Min GCR | KV4: Poor | KW4: Posted | KX4: Project Pick | KY4: Project Id | KZ4: Budget | LA4: Recommended Treatment | LB4: Cost | LC4: Superseded Treatments | LD4: FHWA Work Types | LE4: Comments
AX5: Work | AY5: Cost | AZ5: Work | BA5: Cost | BB5: Work | BC5: Cost | BD5: Work | BE5: Cost | BF5: Work | BG5: Cost | BH5: Work | BI5: Cost | BJ5: Work | BK5: Cost | BL5: Work | BM5: Cost | BN5: Work | BO5: Cost | BP5: Work | BQ5: Cost | BR5: Work | BS5: Cost | BV5: 2 | BW5: 2026 | BX5: 2027 | BY5: 2028 | BZ5: 2029 | CA5: 2030 | CB5: 2031 | CC5: 2032 | CD5: 2033 | CE5: 2034 | CF5: 2035 | CG5: 2036
A6: Local | B6: B | C6: 51720104100102 | D6: 30015 | E6: 04 | F6: Pike | G6: 02 - County Highway Agency | H6: 051 | I6: NEPA RPO | K6: SHOHOLA CREEK | L6: SPRING ROAD | M6: PIERSON BRIDGE, PIKE COUNTY BRIDGE #2 | N6: County Highway Agency | O6: 21 | P6: 342.3 | Q6: N | R6: Single | S6: 2 | T6: Steel, I beams | U6: N | V6: N | W6: 09 - Rural - Local | X6: N | Y6: Y | Z6: L | AA6: N | AB6: 06 - Bituminous (applies only to structures with no deck) | AC6: 8 | AD6: 3 | AE6: 4 | AF6: 1924 | AG6: 103 | AH6: 10 | AI6: 117 | AJ6: 99 | AK6: POSTED | AL6: 43 | AM6: N | AN6: D | AO6: P | AP6: N | AQ6: 0 - Not on Federal Route | AR6: N | AS6: N | AT6: Y | AU6: N | AV6: Y | AW6: N | AX6: culvert replacement (box frame | AY6: 900000 | AZ6: -- | BA6: 0 | BB6: -- | BC6: 0 | BD6: -- | BE6: 0 | BF6: -- | BG6: 0 | BH6: -- | BI6: 0 | BJ6: -- | BK6: 0 | BL6: -- | BM6: 0 | BN6: -- | BO6: 0 | BP6: -- | BQ6: 0 | BR6: -- | BS6: 0 | BT6: Yes | BU6: -- | BW6: Off | BX6: -- | BY6: -- | BZ6: -- | CA6: -- | CB6: -- | CC6: -- | CD6: -- | CE6: -- | CF6: -- | CG6: -- | CI6: 4.724 | CJ6: 5.827 | CK6: 4.448 | CL6: N | CM6: 4 | CN6: 4 | CO6: 12 | CP6: N | CQ6: 4.448 | CR6: Y | CS6: Y | CU6: 9.99 | CV6: 9.99 | CW6: 9.99 | CX6: N | CY6: 1 | CZ6: 1 | DA6: 1 | DB6: N | DC6: 9.99 | DD6: N | DE6: Y | DF6: BAMS Pick | DH6: NEPA_581 | DI6: Culvert Replacement (Box Frame | DJ6: 900000 | DL6: Replacement | DO6: 9.847 | DP6: 9.879 | DQ6: 9.79 | DR6: N | DS6: 2 | DT6: 2 | DU6: 2 | DV6: N | DW6: 9.79 | DX6: N | DY6: Y | DZ6: BAMS Pick | EC6: No Treatment | ED6: 0 | EF6: Maintenance | EI6: 9.704 | EJ6: 9.768 | EK6: 9.59 | EL6: N | EM6: 3 | EN6: 3 | EO6: 3 | EP6: N | EQ6: 9.59 | ER6: N | ES6: Y | ET6: BAMS Pick | EW6: No Treatment | EX6: 0 | EZ6: Maintenance | FC6: 9.561 | FD6: 9.657 | FE6: 9.39 | FF6: N | FG6: 4 | FH6: 4 | FI6: 4 | FJ6: N | FK6: 9.39 | FL6: N | FM6: Y | FN6: BAMS Pick | FQ6: No Treatment | FR6: 0 | FT6: Maintenance | FW6: 9.418 | FX6: 9.546 | FY6: 9.19 | FZ6: N | GA6: 5 | GB6: 5 | GC6: 5 | GD6: N | GE6: 9.19 | GF6: N | GG6: Y | GH6: BAMS Pick | GK6: No Treatment | GL6: 0 | GN6: Maintenance | GQ6: 9.275 | GR6: 9.435 | GS6: 8.99285 | GT6: N | GU6: 6 | GV6: 6 | GW6: 1 | GX6: N | GY6: 8.99285 | GZ6: N | HA6: Y | HB6: BAMS Pick | HE6: No Treatment | HF6: 0 | HH6: Maintenance | HK6: 9.132 | HL6: 9.324 | HM6: 8.84985 | HN6: N | HO6: 7 | HP6: 7 | HQ6: 2 | HR6: N | HS6: 8.84985 | HT6: N | HU6: Y | HV6: BAMS Pick | HY6: No Treatment | HZ6: 0 | IB6: Maintenance | IE6: 8.9912378 | IF6: 9.213 | IG6: 8.70685 | IH6: N | II6: 1 | IJ6: 8 | IK6: 3 | IL6: N | IM6: 8.70685 | IN6: N | IO6: Y | IP6: BAMS Pick | IS6: No Treatment | IT6: 0 | IV6: Maintenance | IY6: 8.8802378 | IZ6: 9.102 | JA6: 8.56385 | JB6: N | JC6: 2 | JD6: 9 | JE6: 4 | JF6: N | JG6: 8.56385 | JH6: N | JI6: Y | JJ6: BAMS Pick | JM6: No Treatment | JN6: 0 | JP6: Maintenance | JS6: 8.7692378 | JT6: 8.9946036 | JU6: 8.42085 | JV6: N | JW6: 3 | JX6: 1 | JY6: 5 | JZ6: N | KA6: 8.42085 | KB6: N | KC6: Y | KD6: BAMS Pick | KG6: No Treatment | KH6: 0 | KJ6: Maintenance | KM6: 8.6582378 | KN6: 8.9236036 | KO6: 8.27785 | KP6: N | KQ6: 4 | KR6: 2 | KS6: 6 | KT6: N | KU6: 8.27785 | KV6: N | KW6: Y | KX6: BAMS Pick | LA6: No Treatment | LB6: 0 | LD6: Maintenance
A7: Local | B7: B | C7: 51720104140101 | D7: 30016 | E7: 04 | F7: Pike | G7: 02 - County Highway Agency | H7: 051 | I7: NEPA RPO | K7: BLOOMING GROVE CREEK | L7: CHRISTOPHER WAY | M7: Co Br #1 (Blooming Grove Twp) | N7: County Highway Agency | O7: 53 | P7: 1287.9 | Q7: N | R7: Single | S7: 5 | T7: P/S, Box beam - adj | U7: N | V7: N | W7: 09 - Rural - Local | X7: N | Y7: Y | Z7: L | AA7: N | AB7: 06 - Bituminous (applies only to structures with no deck) | AC7: 5 | AD7: N | AE7: N | AF7: 1956 | AG7: 71 | AH7: 150 | AI7: 440 | AJ7: 1 | AK7: OPEN | AL7: 53 | AM7: N | AN7: -- | AO7: H | AP7: N | AQ7: 0 - Not on Federal Route | AR7: N | AS7: N | AT7: Y | AU7: N | AV7: Y | AW7: N | AX7: superstructure rep rehab | AY7: 579555 | AZ7: -- | BA7: 0 | BB7: -- | BC7: 0 | BD7: -- | BE7: 0 | BF7: -- | BG7: 0 | BH7: -- | BI7: 0 | BJ7: -- | BK7: 0 | BL7: -- | BM7: 0 | BN7: -- | BO7: 0 | BP7: -- | BQ7: 0 | BR7: -- | BS7: 0 | BT7: Yes | BU7: -- | BW7: Off | BX7: -- | BY7: -- | BZ7: -- | CA7: -- | CB7: -- | CC7: -- | CD7: -- | CE7: -- | CF7: -- | CG7: -- | CI7: 4.294 | CJ7: 4.303 | CK7: 5.748 | CL7: N | CM7: 12 | CN7: 12 | CO7: 4 | CP7: N | CQ7: 4.294 | CR7: Y | CS7: N | CU7: 9.99 | CV7: 9.99 | CW7: 6.99 | CX7: N | CY7: 1 | CZ7: 1 | DA7: 1 | DB7: N | DC7: 6.99 | DD7: N | DE7: N | DF7: BAMS Pick | DH7: NEPA_581 | DI7: Superstructure Rep Rehab | DJ7: 579555 | DL7: Rehabilitation | DO7: 9.79 | DP7: 9.79 | DQ7: 6.931 | DR7: N | DS7: 2 | DT7: 2 | DU7: 2 | DV7: N | DW7: 6.931 | DX7: N | DY7: N | DZ7: BAMS Pick | EC7: No Treatment | ED7: 0 | EF7: Maintenance | EI7: 9.59 | EJ7: 9.59 | EK7: 6.872 | EL7: N | EM7: 3 | EN7: 3 | EO7: 3 | EP7: N | EQ7: 6.872 | ER7: N | ES7: N | ET7: BAMS Pick | EW7: No Treatment | EX7: 0 | EZ7: Maintenance | FC7: 9.39 | FD7: 9.39 | FE7: 6.813 | FF7: N | FG7: 4 | FH7: 4 | FI7: 4 | FJ7: N | FK7: 6.813 | FL7: N | FM7: N | FN7: BAMS Pick | FQ7: No Treatment | FR7: 0 | FT7: Maintenance | FW7: 9.19 | FX7: 9.19 | FY7: 6.754 | FZ7: N | GA7: 5 | GB7: 5 | GC7: 5 | GD7: N | GE7: 6.754 | GF7: N | GG7: N | GH7: BAMS Pick | GK7: No Treatment | GL7: 0 | GN7: Maintenance | GQ7: 8.99375 | GR7: 8.99685 | GS7: 6.695 | GT7: N | GU7: 1 | GV7: 1 | GW7: 6 | GX7: N | GY7: 6.695 | GZ7: N | HA7: N | HB7: BAMS Pick | HE7: No Treatment | HF7: 0 | HH7: Maintenance | HK7: 8.86875 | HL7: 8.93385 | HM7: 6.636 | HN7: N | HO7: 2 | HP7: 2 | HQ7: 7 | HR7: N | HS7: 6.636 | HT7: N | HU7: N | HV7: BAMS Pick | HY7: No Treatment | HZ7: 0 | IB7: Maintenance | IE7: 8.74375 | IF7: 8.87085 | IG7: 6.577 | IH7: N | II7: 3 | IJ7: 3 | IK7: 8 | IL7: N | IM7: 6.577 | IN7: N | IO7: N | IP7: BAMS Pick | IS7: No Treatment | IT7: 0 | IV7: Maintenance | IY7: 8.61875 | IZ7: 8.80785 | JA7: 6.518 | JB7: N | JC7: 4 | JD7: 4 | JE7: 9 | JF7: N | JG7: 6.518 | JH7: N | JI7: N | JJ7: BAMS Pick | JM7: No Treatment | JN7: 0 | JP7: Maintenance | JS7: 8.49375 | JT7: 8.74485 | JU7: 6.459 | JV7: N | JW7: 5 | JX7: 5 | JY7: 10 | JZ7: N | KA7: 6.459 | KB7: N | KC7: N | KD7: BAMS Pick | KG7: No Treatment | KH7: 0 | KJ7: Maintenance | KM7: 8.36875 | KN7: 8.68185 | KO7: 6.4 | KP7: N | KQ7: 6 | KR7: 6 | KS7: 11 | KT7: N | KU7: 6.4 | KV7: N | KW7: N | KX7: BAMS Pick | LA7: No Treatment | LB7: 0 | LD7: Maintenance
A8: Local | B8: B | C8: 51720203140005 | D8: 30018 | E8: 04 | F8: Pike | G8: 03 - Town or Township Highway Agency | H8: 202 | I8: NEPA RPO | K8: HORNBECKS CREEK | L8: T314 LOG & TWIG RD | M8: T-314, Delaware Twp | N8: Town or Township Highway Agency | O8: 39 | P8: 947.7 | Q8: N | R8: Single | S8: 5 | T8: P/S, Box beam - adj | U8: N | V8: N | W8: 09 - Rural - Local | X8: N | Y8: Y | Z8: L | AA8: N | AB8: 06 - Bituminous (applies only to structures with no deck) | AC8: 8 | AD8: N | AE8: N | AF8: 1956 | AG8: 71 | AH8: 290 | AI8: 524 | AJ8: 5 | AK8: POSTED | AL8: 45 | AM8: N | AN8: -- | AO8: P | AP8: N | AQ8: 0 - Not on Federal Route | AR8: N | AS8: N | AT8: Y | AU8: N | AV8: Y | AW8: N | AX8: superstructure rep rehab | AY8: 426465 | AZ8: -- | BA8: 0 | BB8: -- | BC8: 0 | BD8: -- | BE8: 0 | BF8: -- | BG8: 0 | BH8: -- | BI8: 0 | BJ8: -- | BK8: 0 | BL8: -- | BM8: 0 | BN8: -- | BO8: 0 | BP8: -- | BQ8: 0 | BR8: -- | BS8: 0 | BT8: Yes | BU8: -- | BW8: Off | BX8: -- | BY8: -- | BZ8: -- | CA8: -- | CB8: -- | CC8: -- | CD8: -- | CE8: -- | CF8: -- | CG8: -- | CI8: 4.588 | CJ8: 4.584 | CK8: 5.639 | CL8: N | CM8: 6 | CN8: 6 | CO8: 8 | CP8: N | CQ8: 4.584 | CR8: Y | CS8: Y | CU8: 9.99 | CV8: 9.99 | CW8: 6.99 | CX8: N | CY8: 1 | CZ8: 1 | DA8: 1 | DB8: N | DC8: 6.99 | DD8: N | DE8: Y | DF8: BAMS Pick | DH8: NEPA_581 | DI8: Superstructure Rep Rehab | DJ8: 426465 | DL8: Rehabilitation | DO8: 9.79 | DP8: 9.79 | DQ8: 6.931 | DR8: N | DS8: 2 | DT8: 2 | DU8: 2 | DV8: N | DW8: 6.931 | DX8: N | DY8: Y | DZ8: BAMS Pick | EC8: No Treatment | ED8: 0 | EF8: Maintenance | EI8: 9.59 | EJ8: 9.59 | EK8: 6.872 | EL8: N | EM8: 3 | EN8: 3 | EO8: 3 | EP8: N | EQ8: 6.872 | ER8: N | ES8: Y | ET8: BAMS Pick | EW8: No Treatment | EX8: 0 | EZ8: Maintenance | FC8: 9.39 | FD8: 9.39 | FE8: 6.813 | FF8: N | FG8: 4 | FH8: 4 | FI8: 4 | FJ8: N | FK8: 6.813 | FL8: N | FM8: Y | FN8: BAMS Pick | FQ8: No Treatment | FR8: 0 | FT8: Maintenance | FW8: 9.19 | FX8: 9.19 | FY8: 6.754 | FZ8: N | GA8: 5 | GB8: 5 | GC8: 5 | GD8: N | GE8: 6.754 | GF8: N | GG8: Y | GH8: BAMS Pick | GK8: No Treatment | GL8: 0 | GN8: Maintenance | GQ8: 8.99375 | GR8: 8.99685 | GS8: 6.695 | GT8: N | GU8: 1 | GV8: 1 | GW8: 6 | GX8: N | GY8: 6.695 | GZ8: N | HA8: Y | HB8: BAMS Pick | HE8: No Treatment | HF8: 0 | HH8: Maintenance | HK8: 8.86875 | HL8: 8.93385 | HM8: 6.636 | HN8: N | HO8: 2 | HP8: 2 | HQ8: 7 | HR8: N | HS8: 6.636 | HT8: N | HU8: Y | HV8: BAMS Pick | HY8: No Treatment | HZ8: 0 | IB8: Maintenance | IE8: 8.74375 | IF8: 8.87085 | IG8: 6.577 | IH8: N | II8: 3 | IJ8: 3 | IK8: 8 | IL8: N | IM8: 6.577 | IN8: N | IO8: Y | IP8: BAMS Pick | IS8: No Treatment | IT8: 0 | IV8: Maintenance | IY8: 8.61875 | IZ8: 8.80785 | JA8: 6.518 | JB8: N | JC8: 4 | JD8: 4 | JE8: 9 | JF8: N | JG8: 6.518 | JH8: N | JI8: Y | JJ8: BAMS Pick | JM8: No Treatment | JN8: 0 | JP8: Maintenance | JS8: 8.49375 | JT8: 8.74485 | JU8: 6.459 | JV8: N | JW8: 5 | JX8: 5 | JY8: 10 | JZ8: N | KA8: 6.459 | KB8: N | KC8: Y | KD8: BAMS Pick | KG8: No Treatment | KH8: 0 | KJ8: Maintenance | KM8: 8.36875 | KN8: 8.68185 | KO8: 6.4 | KP8: N | KQ8: 6 | KR8: 6 | KS8: 11 | KT8: N | KU8: 6.4 | KV8: N | KW8: Y | KX8: BAMS Pick | LA8: No Treatment | LB8: 0 | LD8: Maintenance
A9: Local | B9: B | C9: 51720304240105 | D9: 30026 | E9: 04 | F9: Pike | G9: 02 - County Highway Agency | H9: 051 | I9: NEPA RPO | K9: RATTLESNAKE CREEK | L9: SPRING BROOK ROAD | M9: PIKE COUNTY BRIDGE #5 | N9: County Highway Agency | O9: 33 | P9: 574.2 | Q9: N | R9: Single | S9: 1 | T9: Concr. encased steel, I beams | U9: N | V9: N | W9: 09 - Rural - Local | X9: N | Y9: Y | Z9: L | AA9: N | AB9: 06 - Bituminous (applies only to structures with no deck) | AC9: 4 | AD9: N | AE9: N | AF9: 1916 | AG9: 111 | AH9: 110 | AI9: 503 | AJ9: 99 | AK9: OPEN | AL9: 45 | AM9: N | AN9: B | AO9: P | AP9: N | AQ9: 0 - Not on Federal Route | AR9: N | AS9: N | AT9: Y | AU9: N | AV9: Y | AW9: N | AX9: -- | AY9: 0 | AZ9: -- | BA9: 0 | BB9: -- | BC9: 0 | BD9: -- | BE9: 0 | BF9: -- | BG9: 0 | BH9: -- | BI9: 0 | BJ9: -- | BK9: 0 | BL9: -- | BM9: 0 | BN9: -- | BO9: 0 | BP9: -- | BQ9: 0 | BR9: bridge replacement | BS9: 1209524.7 | BT9: Yes | BU9: -- | BW9: -- | BX9: -- | BY9: -- | BZ9: -- | CA9: -- | CB9: -- | CC9: -- | CD9: -- | CE9: -- | CF9: -- | CG9: Off | CI9: 6.051 | CJ9: 5.347 | CK9: 4.705 | CL9: N | CM9: 40 | CN9: 22 | CO9: 4 | CP9: N | CQ9: 4.705 | CR9: Y | CS9: N | CU9: 6.051 | CV9: 5.347 | CW9: 4.705 | CX9: N | CY9: 40 | CZ9: 22 | DA9: 4 | DB9: N | DC9: 4.705 | DD9: Y | DE9: N | DF9: BAMS Pick | DI9: No Treatment | DJ9: 0 | DL9: Maintenance | DO9: 6.00136 | DP9: 5.299 | DQ9: 4.634 | DR9: N | DS9: 41 | DT9: 23 | DU9: 5 | DV9: N | DW9: 4.634 | DX9: Y | DY9: N | DZ9: BAMS Pick | EC9: No Treatment | ED9: 0 | EF9: Maintenance | EI9: 5.95336 | EJ9: 5.251 | EK9: 4.563 | EL9: N | EM9: 1 | EN9: 24 | EO9: 6 | EP9: N | EQ9: 4.563 | ER9: Y | ES9: N | ET9: BAMS Pick | EW9: No Treatment | EX9: 0 | EZ9: Maintenance | FC9: 5.90536 | FD9: 5.203 | FE9: 4.492 | FF9: N | FG9: 2 | FH9: 25 | FI9: 7 | FJ9: N | FK9: 4.492 | FL9: Y | FM9: N | FN9: BAMS Pick | FQ9: No Treatment | FR9: 0 | FT9: Maintenance | FW9: 5.85736 | FX9: 5.155 | FY9: 4.421 | FZ9: N | GA9: 3 | GB9: 26 | GC9: 8 | GD9: N | GE9: 4.421 | GF9: Y | GG9: N | GH9: BAMS Pick | GK9: No Treatment | GL9: 0 | GN9: Maintenance | GQ9: 5.80936 | GR9: 5.107 | GS9: 4.35 | GT9: N | GU9: 4 | GV9: 27 | GW9: 9 | GX9: N | GY9: 4.35 | GZ9: Y | HA9: N | HB9: BAMS Pick | HE9: No Treatment | HF9: 0 | HH9: Maintenance | HK9: 5.76136 | HL9: 5.059 | HM9: 4.279 | HN9: N | HO9: 5 | HP9: 28 | HQ9: 10 | HR9: N | HS9: 4.279 | HT9: Y | HU9: N | HV9: BAMS Pick | HY9: No Treatment | HZ9: 0 | IB9: Maintenance | IE9: 5.71336 | IF9: 5.011 | IG9: 4.208 | IH9: N | II9: 6 | IJ9: 29 | IK9: 11 | IL9: N | IM9: 4.208 | IN9: Y | IO9: N | IP9: BAMS Pick | IS9: No Treatment | IT9: 0 | IV9: Maintenance | IY9: 5.66536 | IZ9: 4.9578542 | JA9: 4.137 | JB9: N | JC9: 7 | JD9: 1 | JE9: 12 | JF9: N | JG9: 4.137 | JH9: Y | JI9: N | JJ9: BAMS Pick | JM9: No Treatment | JN9: 0 | JP9: Maintenance | JS9: 5.61736 | JT9: 4.8908542 | JU9: 4.066 | JV9: N | JW9: 8 | JX9: 2 | JY9: 13 | JZ9: N | KA9: 4.066 | KB9: Y | KC9: N | KD9: BAMS Pick | KG9: No Treatment | KH9: 0 | KJ9: Maintenance | KM9: 9.99 | KN9: 9.99 | KO9: 9.99 | KP9: N | KQ9: 1 | KR9: 1 | KS9: 1 | KT9: N | KU9: 9.99 | KV9: N | KW9: N | KX9: BAMS Pick | KZ9: NEPA_581 | LA9: Bridge Replacement | LB9: 1209524.7 | LD9: Replacement
A10: Local | B10: B | C10: 51720403740005 | D10: 30029 | E10: 04 | F10: Pike | G10: 03 - Town or Township Highway Agency | H10: 204 | I10: NEPA RPO | K10: SUGAR HILL CREEK | L10: T-374 MTN VIEW RD | M10: T-374 Bridge, Greene Twp | N10: Town or Township Highway Agency | O10: 37 | P10: 899.1 | Q10: N | R10: Single | S10: 5 | T10: P/S, Box beam - adj | U10: N | V10: N | W10: 09 - Rural - Local | X10: N | Y10: Y | Z10: L | AA10: N | AB10: 06 - Bituminous (applies only to structures with no deck) | AC10: 5 | AD10: N | AE10: N | AF10: 1960 | AG10: 67 | AH10: 50 | AI10: 212 | AJ10: 8 | AK10: POSTED | AL10: 48 | AM10: N | AN10: -- | AO10: P | AP10: N | AQ10: 0 - Not on Federal Route | AR10: N | AS10: N | AT10: Y | AU10: N | AV10: Y | AW10: N | AX10: superstructure rep rehab | AY10: 404595 | AZ10: -- | BA10: 0 | BB10: -- | BC10: 0 | BD10: -- | BE10: 0 | BF10: -- | BG10: 0 | BH10: -- | BI10: 0 | BJ10: -- | BK10: 0 | BL10: -- | BM10: 0 | BN10: -- | BO10: 0 | BP10: -- | BQ10: 0 | BR10: -- | BS10: 0 | BT10: Yes | BU10: -- | BW10: Off | BX10: -- | BY10: -- | BZ10: -- | CA10: -- | CB10: -- | CC10: -- | CD10: -- | CE10: -- | CF10: -- | CG10: -- | CI10: 4.294 | CJ10: 4.302 | CK10: 5.512 | CL10: N | CM10: 12 | CN10: 12 | CO10: 12 | CP10: N | CQ10: 4.294 | CR10: Y | CS10: Y | CU10: 9.99 | CV10: 9.99 | CW10: 6.99 | CX10: N | CY10: 1 | CZ10: 1 | DA10: 1 | DB10: N | DC10: 6.99 | DD10: N | DE10: Y | DF10: BAMS Pick | DH10: NEPA_581 | DI10: Superstructure Rep Rehab | DJ10: 404595 | DL10: Rehabilitation | DO10: 9.79 | DP10: 9.79 | DQ10: 6.931 | DR10: N | DS10: 2 | DT10: 2 | DU10: 2 | DV10: N | DW10: 6.931 | DX10: N | DY10: Y | DZ10: BAMS Pick | EC10: No Treatment | ED10: 0 | EF10: Maintenance | EI10: 9.59 | EJ10: 9.59 | EK10: 6.872 | EL10: N | EM10: 3 | EN10: 3 | EO10: 3 | EP10: N | EQ10: 6.872 | ER10: N | ES10: Y | ET10: BAMS Pick | EW10: No Treatment | EX10: 0 | EZ10: Maintenance | FC10: 9.39 | FD10: 9.39 | FE10: 6.813 | FF10: N | FG10: 4 | FH10: 4 | FI10: 4 | FJ10: N | FK10: 6.813 | FL10: N | FM10: Y | FN10: BAMS Pick | FQ10: No Treatment | FR10: 0 | FT10: Maintenance | FW10: 9.19 | FX10: 9.19 | FY10: 6.754 | FZ10: N | GA10: 5 | GB10: 5 | GC10: 5 | GD10: N | GE10: 6.754 | GF10: N | GG10: Y | GH10: BAMS Pick | GK10: No Treatment | GL10: 0 | GN10: Maintenance | GQ10: 8.99375 | GR10: 8.99685 | GS10: 6.695 | GT10: N | GU10: 1 | GV10: 1 | GW10: 6 | GX10: N | GY10: 6.695 | GZ10: N | HA10: Y | HB10: BAMS Pick | HE10: No Treatment | HF10: 0 | HH10: Maintenance | HK10: 8.86875 | HL10: 8.93385 | HM10: 6.636 | HN10: N | HO10: 2 | HP10: 2 | HQ10: 7 | HR10: N | HS10: 6.636 | HT10: N | HU10: Y | HV10: BAMS Pick | HY10: No Treatment | HZ10: 0 | IB10: Maintenance | IE10: 8.74375 | IF10: 8.87085 | IG10: 6.577 | IH10: N | II10: 3 | IJ10: 3 | IK10: 8 | IL10: N | IM10: 6.577 | IN10: N | IO10: Y | IP10: BAMS Pick | IS10: No Treatment | IT10: 0 | IV10: Maintenance | IY10: 8.61875 | IZ10: 8.80785 | JA10: 6.518 | JB10: N | JC10: 4 | JD10: 4 | JE10: 9 | JF10: N | JG10: 6.518 | JH10: N | JI10: Y | JJ10: BAMS Pick | JM10: No Treatment | JN10: 0 | JP10: Maintenance | JS10: 8.49375 | JT10: 8.74485 | JU10: 6.459 | JV10: N | JW10: 5 | JX10: 5 | JY10: 10 | JZ10: N | KA10: 6.459 | KB10: N | KC10: Y | KD10: BAMS Pick | KG10: No Treatment | KH10: 0 | KJ10: Maintenance | KM10: 8.36875 | KN10: 8.68185 | KO10: 6.4 | KP10: N | KQ10: 6 | KR10: 6 | KS10: 11 | KT10: N | KU10: 6.4 | KV10: N | KW10: Y | KX10: BAMS Pick | LA10: No Treatment | LB10: 0 | LD10: Maintenance
A11: Local | B11: B | C11: 51720403660106 | D11: 30030 | E11: 04 | F11: Pike | G11: 02 - County Highway Agency | H11: 051 | I11: NEPA RPO | K11: TAYLOR CREEK | L11: CARLTON ROAD | M11: PIKE COUNTY BRIDGE #6 | N11: County Highway Agency | O11: 43 | P11: 1040.6 | Q11: N | R11: Single | S11: 5 | T11: P/S, Box beam - adj | U11: N | V11: N | W11: 09 - Rural - Local | X11: N | Y11: Y | Z11: L | AA11: N | AB11: 06 - Bituminous (applies only to structures with no deck) | AC11: 5 | AD11: N | AE11: N | AF11: 1956 | AG11: 71 | AH11: 50 | AI11: 228 | AJ11: 5 | AK11: POSTED | AL11: 34 | AM11: N | AN11: -- | AO11: P | AP11: N | AQ11: 0 - Not on Federal Route | AR11: N | AS11: N | AT11: Y | AU11: N | AV11: Y | AW11: N | AX11: superstructure rep rehab | AY11: 468270 | AZ11: -- | BA11: 0 | BB11: -- | BC11: 0 | BD11: -- | BE11: 0 | BF11: -- | BG11: 0 | BH11: -- | BI11: 0 | BJ11: -- | BK11: 0 | BL11: -- | BM11: 0 | BN11: -- | BO11: 0 | BP11: -- | BQ11: 0 | BR11: general preservation | BS11: 27969.59 | BT11: Yes | BU11: Yes | BW11: Off | BX11: -- | BY11: -- | BZ11: -- | CA11: -- | CB11: -- | CC11: -- | CD11: -- | CE11: -- | CF11: -- | CG11: -- | CI11: 2.956 | CJ11: 2.921 | CK11: 6.519 | CL11: N | CM11: 1 | CN11: 1 | CO11: 12 | CP11: N | CQ11: 2.921 | CR11: Y | CS11: Y | CU11: 9.99 | CV11: 9.99 | CW11: 7.519 | CX11: N | CY11: 1 | CZ11: 1 | DA11: 1 | DB11: N | DC11: 7.519 | DD11: N | DE11: Y | DF11: BAMS Pick | DH11: NEPA_581 | DI11: Superstructure Rep Rehab | DJ11: 468270 | DL11: Rehabilitation | DO11: 9.79 | DP11: 9.79 | DQ11: 7.474 | DR11: N | DS11: 2 | DT11: 2 | DU11: 2 | DV11: N | DW11: 7.474 | DX11: N | DY11: Y | DZ11: BAMS Pick | EC11: No Treatment | ED11: 0 | EF11: Maintenance | EI11: 9.59 | EJ11: 9.59 | EK11: 7.429 | EL11: N | EM11: 3 | EN11: 3 | EO11: 3 | EP11: N | EQ11: 7.429 | ER11: N | ES11: Y | ET11: BAMS Pick | EW11: No Treatment | EX11: 0 | EZ11: Maintenance | FC11: 9.39 | FD11: 9.39 | FE11: 7.384 | FF11: N | FG11: 4 | FH11: 4 | FI11: 4 | FJ11: N | FK11: 7.384 | FL11: N | FM11: Y | FN11: BAMS Pick | FQ11: No Treatment | FR11: 0 | FT11: Maintenance | FW11: 9.19 | FX11: 9.19 | FY11: 7.339 | FZ11: N | GA11: 5 | GB11: 5 | GC11: 5 | GD11: N | GE11: 7.339 | GF11: N | GG11: Y | GH11: BAMS Pick | GK11: No Treatment | GL11: 0 | GN11: Maintenance | GQ11: 8.99375 | GR11: 8.99685 | GS11: 7.294 | GT11: N | GU11: 1 | GV11: 1 | GW11: 6 | GX11: N | GY11: 7.294 | GZ11: N | HA11: Y | HB11: BAMS Pick | HE11: No Treatment | HF11: 0 | HH11: Maintenance | HK11: 8.86875 | HL11: 8.93385 | HM11: 7.249 | HN11: N | HO11: 2 | HP11: 2 | HQ11: 7 | HR11: N | HS11: 7.249 | HT11: N | HU11: Y | HV11: BAMS Pick | HY11: No Treatment | HZ11: 0 | IB11: Maintenance | IE11: 8.74375 | IF11: 8.87085 | IG11: 7.204 | IH11: N | II11: 3 | IJ11: 3 | IK11: 8 | IL11: N | IM11: 7.204 | IN11: N | IO11: Y | IP11: BAMS Pick | IS11: No Treatment | IT11: 0 | IV11: Maintenance | IY11: 8.61875 | IZ11: 8.80785 | JA11: 7.159 | JB11: N | JC11: 4 | JD11: 4 | JE11: 9 | JF11: N | JG11: 7.159 | JH11: N | JI11: Y | JJ11: BAMS Pick | JM11: No Treatment | JN11: 0 | JP11: Maintenance | JS11: 8.49375 | JT11: 8.74485 | JU11: 7.114 | JV11: N | JW11: 5 | JX11: 5 | JY11: 10 | JZ11: N | KA11: 7.114 | KB11: N | KC11: Y | KD11: BAMS Pick | KG11: No Treatment | KH11: 0 | KJ11: Maintenance | KM11: 8.36875 | KN11: 8.68185 | KO11: 7.569 | KP11: N | KQ11: 6 | KR11: 6 | KS11: 11 | KT11: N | KU11: 7.569 | KV11: N | KW11: Y | KX11: BAMS Pick | KZ11: NEPA_581 | LA11: General Preservation | LB11: 27969.59 | LD11: Preservation
A12: Local | B12: B | C12: 51720403720005 | D12: 30031 | E12: 04 | F12: Pike | G12: 03 - Town or Township Highway Agency | H12: 204 | I12: NEPA RPO | K12: BRIDGE CREEK | L12: T-372 SAWMILL ROAD | M12: T-372 Bridge #1, Greene Twp | N12: Town or Township Highway Agency | O12: 71 | P12: 1725.3 | Q12: N | R12: Single | S12: 5 | T12: P/S, Box beam - adj | U12: N | V12: N | W12: 09 - Rural - Local | X12: N | Y12: Y | Z12: L | AA12: N | AB12: 06 - Bituminous (applies only to structures with no deck) | AC12: 6 | AD12: N | AE12: N | AF12: 1970 | AG12: 57 | AH12: 50 | AI12: 294 | AJ12: 7 | AK12: POSTED | AL12: 46 | AM12: N | AN12: -- | AO12: P | AP12: N | AQ12: 0 - Not on Federal Route | AR12: N | AS12: N | AT12: Y | AU12: N | AV12: Y | AW12: N | AX12: superstructure rep rehab | AY12: 776385 | AZ12: -- | BA12: 0 | BB12: -- | BC12: 0 | BD12: -- | BE12: 0 | BF12: -- | BG12: 0 | BH12: -- | BI12: 0 | BJ12: -- | BK12: 0 | BL12: -- | BM12: 0 | BN12: -- | BO12: 0 | BP12: -- | BQ12: 0 | BR12: -- | BS12: 0 | BT12: Yes | BU12: -- | BW12: Off | BX12: -- | BY12: -- | BZ12: -- | CA12: -- | CB12: -- | CC12: -- | CD12: -- | CE12: -- | CF12: -- | CG12: -- | CI12: 4.292 | CJ12: 4.296 | CK12: 5.508 | CL12: N | CM12: 12 | CN12: 12 | CO12: 12 | CP12: N | CQ12: 4.292 | CR12: Y | CS12: Y | CU12: 9.99 | CV12: 9.99 | CW12: 6.99 | CX12: N | CY12: 1 | CZ12: 1 | DA12: 1 | DB12: N | DC12: 6.99 | DD12: N | DE12: Y | DF12: BAMS Pick | DH12: NEPA_581 | DI12: Superstructure Rep Rehab | DJ12: 776385 | DL12: Rehabilitation | DO12: 9.79 | DP12: 9.79 | DQ12: 6.931 | DR12: N | DS12: 2 | DT12: 2 | DU12: 2 | DV12: N | DW12: 6.931 | DX12: N | DY12: Y | DZ12: BAMS Pick | EC12: No Treatment | ED12: 0 | EF12: Maintenance | EI12: 9.59 | EJ12: 9.59 | EK12: 6.872 | EL12: N | EM12: 3 | EN12: 3 | EO12: 3 | EP12: N | EQ12: 6.872 | ER12: N | ES12: Y | ET12: BAMS Pick | EW12: No Treatment | EX12: 0 | EZ12: Maintenance | FC12: 9.39 | FD12: 9.39 | FE12: 6.813 | FF12: N | FG12: 4 | FH12: 4 | FI12: 4 | FJ12: N | FK12: 6.813 | FL12: N | FM12: Y | FN12: BAMS Pick | FQ12: No Treatment | FR12: 0 | FT12: Maintenance | FW12: 9.19 | FX12: 9.19 | FY12: 6.754 | FZ12: N | GA12: 5 | GB12: 5 | GC12: 5 | GD12: N | GE12: 6.754 | GF12: N | GG12: Y | GH12: BAMS Pick | GK12: No Treatment | GL12: 0 | GN12: Maintenance | GQ12: 8.99375 | GR12: 8.99685 | GS12: 6.695 | GT12: N | GU12: 1 | GV12: 1 | GW12: 6 | GX12: N | GY12: 6.695 | GZ12: N | HA12: Y | HB12: BAMS Pick | HE12: No Treatment | HF12: 0 | HH12: Maintenance | HK12: 8.86875 | HL12: 8.93385 | HM12: 6.636 | HN12: N | HO12: 2 | HP12: 2 | HQ12: 7 | HR12: N | HS12: 6.636 | HT12: N | HU12: Y | HV12: BAMS Pick | HY12: No Treatment | HZ12: 0 | IB12: Maintenance | IE12: 8.74375 | IF12: 8.87085 | IG12: 6.577 | IH12: N | II12: 3 | IJ12: 3 | IK12: 8 | IL12: N | IM12: 6.577 | IN12: N | IO12: Y | IP12: BAMS Pick | IS12: No Treatment | IT12: 0 | IV12: Maintenance | IY12: 8.61875 | IZ12: 8.80785 | JA12: 6.518 | JB12: N | JC12: 4 | JD12: 4 | JE12: 9 | JF12: N | JG12: 6.518 | JH12: N | JI12: Y | JJ12: BAMS Pick | JM12: No Treatment | JN12: 0 | JP12: Maintenance | JS12: 8.49375 | JT12: 8.74485 | JU12: 6.459 | JV12: N | JW12: 5 | JX12: 5 | JY12: 10 | JZ12: N | KA12: 6.459 | KB12: N | KC12: Y | KD12: BAMS Pick | KG12: No Treatment | KH12: 0 | KJ12: Maintenance | KM12: 8.36875 | KN12: 8.68185 | KO12: 6.4 | KP12: N | KQ12: 6 | KR12: 6 | KS12: 11 | KT12: N | KU12: 6.4 | KV12: N | KW12: Y | KX12: BAMS Pick | LA12: No Treatment | LB12: 0 | LD12: Maintenance
A13: Local | B13: B | C13: 51720403720010 | D13: 30032 | E13: 04 | F13: Pike | G13: 03 - Town or Township Highway Agency | H13: 204 | I13: NEPA RPO | K13: BRIDGE CREEK | L13: T-372 SAWMILL ROAD | M13: T-372 Bridge #2, Greene Twp | N13: Town or Township Highway Agency | O13: 63 | P13: 1549.8 | Q13: N | R13: Single | S13: 5 | T13: P/S, Box beam - adj | U13: N | V13: N | W13: 09 - Rural - Local | X13: N | Y13: Y | Z13: L | AA13: N | AB13: 06 - Bituminous (applies only to structures with no deck) | AC13: 7 | AD13: N | AE13: N | AF13: 1970 | AG13: 57 | AH13: 50 | AI13: 278 | AJ13: 2 | AK13: POSTED | AL13: 23 | AM13: N | AN13: B | AO13: P | AP13: N | AQ13: 0 - Not on Federal Route | AR13: N | AS13: N | AT13: Y | AU13: N | AV13: Y | AW13: N | AX13: superstructure rep rehab | AY13: 697410 | AZ13: -- | BA13: 0 | BB13: -- | BC13: 0 | BD13: -- | BE13: 0 | BF13: -- | BG13: 0 | BH13: -- | BI13: 0 | BJ13: -- | BK13: 0 | BL13: -- | BM13: 0 | BN13: -- | BO13: 0 | BP13: -- | BQ13: 0 | BR13: -- | BS13: 0 | BT13: Yes | BU13: -- | BW13: Off | BX13: -- | BY13: -- | BZ13: -- | CA13: -- | CB13: -- | CC13: -- | CD13: -- | CE13: -- | CF13: -- | CG13: -- | CI13: 2.941 | CJ13: 2.927 | CK13: 5.818 | CL13: N | CM13: 1 | CN13: 1 | CO13: 3 | CP13: N | CQ13: 2.927 | CR13: Y | CS13: Y | CU13: 9.99 | CV13: 9.99 | CW13: 6.99 | CX13: N | CY13: 1 | CZ13: 1 | DA13: 1 | DB13: N | DC13: 6.99 | DD13: N | DE13: Y | DF13: BAMS Pick | DH13: NEPA_581 | DI13: Superstructure Rep Rehab | DJ13: 697410 | DL13: Rehabilitation | DO13: 9.79 | DP13: 9.79 | DQ13: 6.931 | DR13: N | DS13: 2 | DT13: 2 | DU13: 2 | DV13: N | DW13: 6.931 | DX13: N | DY13: Y | DZ13: BAMS Pick | EC13: No Treatment | ED13: 0 | EF13: Maintenance | EI13: 9.59 | EJ13: 9.59 | EK13: 6.872 | EL13: N | EM13: 3 | EN13: 3 | EO13: 3 | EP13: N | EQ13: 6.872 | ER13: N | ES13: Y | ET13: BAMS Pick | EW13: No Treatment | EX13: 0 | EZ13: Maintenance | FC13: 9.39 | FD13: 9.39 | FE13: 6.813 | FF13: N | FG13: 4 | FH13: 4 | FI13: 4 | FJ13: N | FK13: 6.813 | FL13: N | FM13: Y | FN13: BAMS Pick | FQ13: No Treatment | FR13: 0 | FT13: Maintenance | FW13: 9.19 | FX13: 9.19 | FY13: 6.754 | FZ13: N | GA13: 5 | GB13: 5 | GC13: 5 | GD13: N | GE13: 6.754 | GF13: N | GG13: Y | GH13: BAMS Pick | GK13: No Treatment | GL13: 0 | GN13: Maintenance | GQ13: 8.99375 | GR13: 8.99685 | GS13: 6.695 | GT13: N | GU13: 1 | GV13: 1 | GW13: 6 | GX13: N | GY13: 6.695 | GZ13: N | HA13: Y | HB13: BAMS Pick | HE13: No Treatment | HF13: 0 | HH13: Maintenance | HK13: 8.86875 | HL13: 8.93385 | HM13: 6.636 | HN13: N | HO13: 2 | HP13: 2 | HQ13: 7 | HR13: N | HS13: 6.636 | HT13: N | HU13: Y | HV13: BAMS Pick | HY13: No Treatment | HZ13: 0 | IB13: Maintenance | IE13: 8.74375 | IF13: 8.87085 | IG13: 6.577 | IH13: N | II13: 3 | IJ13: 3 | IK13: 8 | IL13: N | IM13: 6.577 | IN13: N | IO13: Y | IP13: BAMS Pick | IS13: No Treatment | IT13: 0 | IV13: Maintenance | IY13: 8.61875 | IZ13: 8.80785 | JA13: 6.518 | JB13: N | JC13: 4 | JD13: 4 | JE13: 9 | JF13: N | JG13: 6.518 | JH13: N | JI13: Y | JJ13: BAMS Pick | JM13: No Treatment | JN13: 0 | JP13: Maintenance | JS13: 8.49375 | JT13: 8.74485 | JU13: 6.459 | JV13: N | JW13: 5 | JX13: 5 | JY13: 10 | JZ13: N | KA13: 6.459 | KB13: N | KC13: Y | KD13: BAMS Pick | KG13: No Treatment | KH13: 0 | KJ13: Maintenance | KM13: 8.36875 | KN13: 8.68185 | KO13: 6.4 | KP13: N | KQ13: 6 | KR13: 6 | KS13: 11 | KT13: N | KU13: 6.4 | KV13: N | KW13: Y | KX13: BAMS Pick | LA13: No Treatment | LB13: 0 | LD13: Maintenance
A14: Local | B14: B | C14: 51720403780005 | D14: 30033 | E14: 04 | F14: Pike | G14: 03 - Town or Township Highway Agency | H14: 204 | I14: NEPA RPO | K14: E BR WALLENPAUPACK CREEK | L14: T-378 CREEK ROAD | M14: T-378 Bridge, Greene Twp | N14: Town or Township Highway Agency | O14: 63 | P14: 1549.8 | Q14: N | R14: Single | S14: 5 | T14: P/S, Box beam - adj | U14: N | V14: N | W14: 09 - Rural - Local | X14: N | Y14: Y | Z14: L | AA14: N | AB14: 06 - Bituminous (applies only to structures with no deck) | AC14: 5 | AD14: N | AE14: N | AF14: 1970 | AG14: 57 | AH14: 50 | AI14: 278 | AJ14: 6 | AK14: POSTED | AL14: 37 | AM14: N | AN14: -- | AO14: P | AP14: N | AQ14: 0 - Not on Federal Route | AR14: N | AS14: N | AT14: Y | AU14: N | AV14: Y | AW14: N | AX14: superstructure rep rehab | AY14: 697410 | AZ14: -- | BA14: 0 | BB14: -- | BC14: 0 | BD14: -- | BE14: 0 | BF14: -- | BG14: 0 | BH14: -- | BI14: 0 | BJ14: -- | BK14: 0 | BL14: -- | BM14: 0 | BN14: -- | BO14: 0 | BP14: -- | BQ14: 0 | BR14: -- | BS14: 0 | BT14: Yes | BU14: -- | BW14: Off | BX14: -- | BY14: -- | BZ14: -- | CA14: -- | CB14: -- | CC14: -- | CD14: -- | CE14: -- | CF14: -- | CG14: -- | CI14: 4.29 | CJ14: 4.3 | CK14: 5.509 | CL14: N | CM14: 12 | CN14: 12 | CO14: 12 | CP14: N | CQ14: 4.29 | CR14: Y | CS14: Y | CU14: 9.99 | CV14: 9.99 | CW14: 6.99 | CX14: N | CY14: 1 | CZ14: 1 | DA14: 1 | DB14: N | DC14: 6.99 | DD14: N | DE14: Y | DF14: BAMS Pick | DH14: NEPA_581 | DI14: Superstructure Rep Rehab | DJ14: 697410 | DL14: Rehabilitation | DO14: 9.79 | DP14: 9.79 | DQ14: 6.931 | DR14: N | DS14: 2 | DT14: 2 | DU14: 2 | DV14: N | DW14: 6.931 | DX14: N | DY14: Y | DZ14: BAMS Pick | EC14: No Treatment | ED14: 0 | EF14: Maintenance | EI14: 9.59 | EJ14: 9.59 | EK14: 6.872 | EL14: N | EM14: 3 | EN14: 3 | EO14: 3 | EP14: N | EQ14: 6.872 | ER14: N | ES14: Y | ET14: BAMS Pick | EW14: No Treatment | EX14: 0 | EZ14: Maintenance | FC14: 9.39 | FD14: 9.39 | FE14: 6.813 | FF14: N | FG14: 4 | FH14: 4 | FI14: 4 | FJ14: N | FK14: 6.813 | FL14: N | FM14: Y | FN14: BAMS Pick | FQ14: No Treatment | FR14: 0 | FT14: Maintenance | FW14: 9.19 | FX14: 9.19 | FY14: 6.754 | FZ14: N | GA14: 5 | GB14: 5 | GC14: 5 | GD14: N | GE14: 6.754 | GF14: N | GG14: Y | GH14: BAMS Pick | GK14: No Treatment | GL14: 0 | GN14: Maintenance | GQ14: 8.99375 | GR14: 8.99685 | GS14: 6.695 | GT14: N | GU14: 1 | GV14: 1 | GW14: 6 | GX14: N | GY14: 6.695 | GZ14: N | HA14: Y | HB14: BAMS Pick | HE14: No Treatment | HF14: 0 | HH14: Maintenance | HK14: 8.86875 | HL14: 8.93385 | HM14: 6.636 | HN14: N | HO14: 2 | HP14: 2 | HQ14: 7 | HR14: N | HS14: 6.636 | HT14: N | HU14: Y | HV14: BAMS Pick | HY14: No Treatment | HZ14: 0 | IB14: Maintenance | IE14: 8.74375 | IF14: 8.87085 | IG14: 6.577 | IH14: N | II14: 3 | IJ14: 3 | IK14: 8 | IL14: N | IM14: 6.577 | IN14: N | IO14: Y | IP14: BAMS Pick | IS14: No Treatment | IT14: 0 | IV14: Maintenance | IY14: 8.61875 | IZ14: 8.80785 | JA14: 6.518 | JB14: N | JC14: 4 | JD14: 4 | JE14: 9 | JF14: N | JG14: 6.518 | JH14: N | JI14: Y | JJ14: BAMS Pick | JM14: No Treatment | JN14: 0 | JP14: Maintenance | JS14: 8.49375 | JT14: 8.74485 | JU14: 6.459 | JV14: N | JW14: 5 | JX14: 5 | JY14: 10 | JZ14: N | KA14: 6.459 | KB14: N | KC14: Y | KD14: BAMS Pick | KG14: No Treatment | KH14: 0 | KJ14: Maintenance | KM14: 8.36875 | KN14: 8.68185 | KO14: 6.4 | KP14: N | KQ14: 6 | KR14: 6 | KS14: 11 | KT14: N | KU14: 6.4 | KV14: N | KW14: Y | KX14: BAMS Pick | LA14: No Treatment | LB14: 0 | LD14: Maintenance
A15: Local | B15: B | C15: 51720403900005 | D15: 30035 | E15: 04 | F15: Pike | G15: 03 - Town or Township Highway Agency | H15: 204 | I15: NEPA RPO | K15: MOZETTE CREEK | L15: T-390 MOZETTE RD | M15: T-390 Bridge, Greene Twp | N15: Town or Township Highway Agency | O15: 33 | P15: 801.9 | Q15: N | R15: Single | S15: 5 | T15: P/S, Box beam - adj | U15: N | V15: N | W15: 09 - Rural - Local | X15: N | Y15: Y | Z15: L | AA15: N | AB15: 06 - Bituminous (applies only to structures with no deck) | AC15: 5 | AD15: N | AE15: N | AF15: 1960 | AG15: 67 | AH15: 50 | AI15: 200 | AJ15: 5 | AK15: POSTED | AL15: 24 | AM15: N | AN15: -- | AO15: P | AP15: N | AQ15: 0 - Not on Federal Route | AR15: N | AS15: N | AT15: Y | AU15: N | AV15: Y | AW15: N | AX15: superstructure rep rehab | AY15: 360855 | AZ15: -- | BA15: 0 | BB15: -- | BC15: 0 | BD15: -- | BE15: 0 | BF15: -- | BG15: 0 | BH15: -- | BI15: 0 | BJ15: -- | BK15: 0 | BL15: -- | BM15: 0 | BN15: -- | BO15: 0 | BP15: -- | BQ15: 0 | BR15: -- | BS15: 0 | BT15: Yes | BU15: -- | BW15: Off | BX15: -- | BY15: -- | BZ15: -- | CA15: -- | CB15: -- | CC15: -- | CD15: -- | CE15: -- | CF15: -- | CG15: -- | CI15: 3.228 | CJ15: 3.018 | CK15: 5.683 | CL15: N | CM15: 6 | CN15: 9 | CO15: 6 | CP15: N | CQ15: 3.018 | CR15: Y | CS15: Y | CU15: 9.99 | CV15: 9.99 | CW15: 6.99 | CX15: N | CY15: 1 | CZ15: 1 | DA15: 1 | DB15: N | DC15: 6.99 | DD15: N | DE15: Y | DF15: BAMS Pick | DH15: NEPA_581 | DI15: Superstructure Rep Rehab | DJ15: 360855 | DL15: Rehabilitation | DO15: 9.79 | DP15: 9.79 | DQ15: 6.931 | DR15: N | DS15: 2 | DT15: 2 | DU15: 2 | DV15: N | DW15: 6.931 | DX15: N | DY15: Y | DZ15: BAMS Pick | EC15: No Treatment | ED15: 0 | EF15: Maintenance | EI15: 9.59 | EJ15: 9.59 | EK15: 6.872 | EL15: N | EM15: 3 | EN15: 3 | EO15: 3 | EP15: N | EQ15: 6.872 | ER15: N | ES15: Y | ET15: BAMS Pick | EW15: No Treatment | EX15: 0 | EZ15: Maintenance | FC15: 9.39 | FD15: 9.39 | FE15: 6.813 | FF15: N | FG15: 4 | FH15: 4 | FI15: 4 | FJ15: N | FK15: 6.813 | FL15: N | FM15: Y | FN15: BAMS Pick | FQ15: No Treatment | FR15: 0 | FT15: Maintenance | FW15: 9.19 | FX15: 9.19 | FY15: 6.754 | FZ15: N | GA15: 5 | GB15: 5 | GC15: 5 | GD15: N | GE15: 6.754 | GF15: N | GG15: Y | GH15: BAMS Pick | GK15: No Treatment | GL15: 0 | GN15: Maintenance | GQ15: 8.99375 | GR15: 8.99685 | GS15: 6.695 | GT15: N | GU15: 1 | GV15: 1 | GW15: 6 | GX15: N | GY15: 6.695 | GZ15: N | HA15: Y | HB15: BAMS Pick | HE15: No Treatment | HF15: 0 | HH15: Maintenance | HK15: 8.86875 | HL15: 8.93385 | HM15: 6.636 | HN15: N | HO15: 2 | HP15: 2 | HQ15: 7 | HR15: N | HS15: 6.636 | HT15: N | HU15: Y | HV15: BAMS Pick | HY15: No Treatment | HZ15: 0 | IB15: Maintenance | IE15: 8.74375 | IF15: 8.87085 | IG15: 6.577 | IH15: N | II15: 3 | IJ15: 3 | IK15: 8 | IL15: N | IM15: 6.577 | IN15: N | IO15: Y | IP15: BAMS Pick | IS15: No Treatment | IT15: 0 | IV15: Maintenance | IY15: 8.61875 | IZ15: 8.80785 | JA15: 6.518 | JB15: N | JC15: 4 | JD15: 4 | JE15: 9 | JF15: N | JG15: 6.518 | JH15: N | JI15: Y | JJ15: BAMS Pick | JM15: No Treatment | JN15: 0 | JP15: Maintenance | JS15: 8.49375 | JT15: 8.74485 | JU15: 6.459 | JV15: N | JW15: 5 | JX15: 5 | JY15: 10 | JZ15: N | KA15: 6.459 | KB15: N | KC15: Y | KD15: BAMS Pick | KG15: No Treatment | KH15: 0 | KJ15: Maintenance | KM15: 8.36875 | KN15: 8.68185 | KO15: 6.4 | KP15: N | KQ15: 6 | KR15: 6 | KS15: 11 | KT15: N | KU15: 6.4 | KV15: N | KW15: Y | KX15: BAMS Pick | LA15: No Treatment | LB15: 0 | LD15: Maintenance
A16: Local | B16: B | C16: 51720504380005 | D16: 30038 | E16: 04 | F16: Pike | G16: 03 - Town or Township Highway Agency | H16: 205 | I16: NEPA RPO | K16: BALLIARD CREEK | L16: T-438 HERZOG RD | M16: T-438 Bridge, Lackwaxen Twp | N16: Town or Township Highway Agency | O16: 58 | P16: 1426.8 | Q16: N | R16: Single | S16: 5 | T16: P/S, Box beam - adj | U16: N | V16: N | W16: 09 - Rural - Local | X16: N | Y16: Y | Z16: L | AA16: N | AB16: 06 - Bituminous (applies only to structures with no deck) | AC16: 4 | AD16: N | AE16: N | AF16: 1956 | AG16: 71 | AH16: 50 | AI16: 534 | AJ16: 99 | AK16: POSTED | AL16: 17 | AM16: N | AN16: B | AO16: P | AP16: N | AQ16: 0 - Not on Federal Route | AR16: N | AS16: N | AT16: Y | AU16: N | AV16: Y | AW16: N | AX16: bridge replacement | AY16: 1569480 | AZ16: -- | BA16: 0 | BB16: -- | BC16: 0 | BD16: -- | BE16: 0 | BF16: -- | BG16: 0 | BH16: -- | BI16: 0 | BJ16: -- | BK16: 0 | BL16: -- | BM16: 0 | BN16: -- | BO16: 0 | BP16: -- | BQ16: 0 | BR16: -- | BS16: 0 | BT16: Yes | BU16: -- | BW16: Off | BX16: -- | BY16: -- | BZ16: -- | CA16: -- | CB16: -- | CC16: -- | CD16: -- | CE16: -- | CF16: -- | CG16: -- | CI16: 4.243 | CJ16: 4.296 | CK16: 2.862 | CL16: N | CM16: 14 | CN16: 12 | CO16: 1 | CP16: N | CQ16: 2.862 | CR16: Y | CS16: Y | CU16: 9.99 | CV16: 9.99 | CW16: 9.99 | CX16: N | CY16: 1 | CZ16: 1 | DA16: 1 | DB16: N | DC16: 9.99 | DD16: N | DE16: Y | DF16: BAMS Pick | DH16: NEPA_581 | DI16: Bridge Replacement | DJ16: 1569480 | DL16: Replacement | DO16: 9.79 | DP16: 9.79 | DQ16: 9.79 | DR16: N | DS16: 2 | DT16: 2 | DU16: 2 | DV16: N | DW16: 9.79 | DX16: N | DY16: Y | DZ16: BAMS Pick | EC16: No Treatment | ED16: 0 | EF16: Maintenance | EI16: 9.59 | EJ16: 9.59 | EK16: 9.59 | EL16: N | EM16: 3 | EN16: 3 | EO16: 3 | EP16: N | EQ16: 9.59 | ER16: N | ES16: Y | ET16: BAMS Pick | EW16: No Treatment | EX16: 0 | EZ16: Maintenance | FC16: 9.39 | FD16: 9.39 | FE16: 9.39 | FF16: N | FG16: 4 | FH16: 4 | FI16: 4 | FJ16: N | FK16: 9.39 | FL16: N | FM16: Y | FN16: BAMS Pick | FQ16: No Treatment | FR16: 0 | FT16: Maintenance | FW16: 9.19 | FX16: 9.19 | FY16: 9.19 | FZ16: N | GA16: 5 | GB16: 5 | GC16: 5 | GD16: N | GE16: 9.19 | GF16: N | GG16: Y | GH16: BAMS Pick | GK16: No Treatment | GL16: 0 | GN16: Maintenance | GQ16: 8.99375 | GR16: 8.99685 | GS16: 8.99685 | GT16: N | GU16: 1 | GV16: 1 | GW16: 1 | GX16: N | GY16: 8.99375 | GZ16: N | HA16: Y | HB16: BAMS Pick | HE16: No Treatment | HF16: 0 | HH16: Maintenance | HK16: 8.86875 | HL16: 8.93385 | HM16: 8.93385 | HN16: N | HO16: 2 | HP16: 2 | HQ16: 2 | HR16: N | HS16: 8.86875 | HT16: N | HU16: Y | HV16: BAMS Pick | HY16: No Treatment | HZ16: 0 | IB16: Maintenance | IE16: 8.74375 | IF16: 8.87085 | IG16: 8.87085 | IH16: N | II16: 3 | IJ16: 3 | IK16: 3 | IL16: N | IM16: 8.74375 | IN16: N | IO16: Y | IP16: BAMS Pick | IS16: No Treatment | IT16: 0 | IV16: Maintenance | IY16: 8.61875 | IZ16: 8.80785 | JA16: 8.80785 | JB16: N | JC16: 4 | JD16: 4 | JE16: 4 | JF16: N | JG16: 8.61875 | JH16: N | JI16: Y | JJ16: BAMS Pick | JM16: No Treatment | JN16: 0 | JP16: Maintenance | JS16: 8.49375 | JT16: 8.74485 | JU16: 8.74485 | JV16: N | JW16: 5 | JX16: 5 | JY16: 5 | JZ16: N | KA16: 8.49375 | KB16: N | KC16: Y | KD16: BAMS Pick | KG16: No Treatment | KH16: 0 | KJ16: Maintenance | KM16: 8.36875 | KN16: 8.68185 | KO16: 8.68185 | KP16: N | KQ16: 6 | KR16: 6 | KS16: 6 | KT16: N | KU16: 8.36875 | KV16: N | KW16: Y | KX16: BAMS Pick | LA16: No Treatment | LB16: 0 | LD16: Maintenance
A17: Local | B17: B | C17: 51720504920112 | D17: 30040 | E17: 04 | F17: Pike | G17: 02 - County Highway Agency | H17: 051 | I17: NEPA RPO | K17: WEST FALLS CREEK | L17: T-492 CHURCH RD | M17: Co Br #12 (Lackawaxen Twp) | N17: County Highway Agency | O17: 27 | P17: 656.1 | Q17: N | R17: Single | S17: 5 | T17: P/S, Box beam - adj | U17: N | V17: N | W17: 09 - Rural - Local | X17: N | Y17: Y | Z17: L | AA17: N | AB17: 06 - Bituminous (applies only to structures with no deck) | AC17: 6 | AD17: N | AE17: N | AF17: 1956 | AG17: 71 | AH17: 50 | AI17: 362 | AJ17: 99 | AK17: POSTED | AL17: 40 | AM17: N | AN17: B | AO17: P | AP17: N | AQ17: 0 - Not on Federal Route | AR17: N | AS17: N | AT17: Y | AU17: N | AV17: Y | AW17: N | AX17: culvert replacement (box frame | AY17: 1115370 | AZ17: -- | BA17: 0 | BB17: -- | BC17: 0 | BD17: -- | BE17: 0 | BF17: -- | BG17: 0 | BH17: -- | BI17: 0 | BJ17: -- | BK17: 0 | BL17: -- | BM17: 0 | BN17: -- | BO17: 0 | BP17: -- | BQ17: 0 | BR17: -- | BS17: 0 | BT17: Yes | BU17: -- | BW17: Off | BX17: -- | BY17: -- | BZ17: -- | CA17: -- | CB17: -- | CC17: -- | CD17: -- | CE17: -- | CF17: -- | CG17: -- | CI17: 4.31 | CJ17: 4.304 | CK17: 3.302 | CL17: N | CM17: 12 | CN17: 12 | CO17: 6 | CP17: N | CQ17: 3.302 | CR17: Y | CS17: Y | CU17: 9.99 | CV17: 9.99 | CW17: 9.99 | CX17: N | CY17: 1 | CZ17: 1 | DA17: 1 | DB17: N | DC17: 9.99 | DD17: N | DE17: Y | DF17: BAMS Pick | DH17: NEPA_581 | DI17: Culvert Replacement (Box Frame | DJ17: 1115370 | DL17: Replacement | DO17: 9.79 | DP17: 9.79 | DQ17: 9.79 | DR17: N | DS17: 2 | DT17: 2 | DU17: 2 | DV17: N | DW17: 9.79 | DX17: N | DY17: Y | DZ17: BAMS Pick | EC17: No Treatment | ED17: 0 | EF17: Maintenance | EI17: 9.59 | EJ17: 9.59 | EK17: 9.59 | EL17: N | EM17: 3 | EN17: 3 | EO17: 3 | EP17: N | EQ17: 9.59 | ER17: N | ES17: Y | ET17: BAMS Pick | EW17: No Treatment | EX17: 0 | EZ17: Maintenance | FC17: 9.39 | FD17: 9.39 | FE17: 9.39 | FF17: N | FG17: 4 | FH17: 4 | FI17: 4 | FJ17: N | FK17: 9.39 | FL17: N | FM17: Y | FN17: BAMS Pick | FQ17: No Treatment | FR17: 0 | FT17: Maintenance | FW17: 9.19 | FX17: 9.19 | FY17: 9.19 | FZ17: N | GA17: 5 | GB17: 5 | GC17: 5 | GD17: N | GE17: 9.19 | GF17: N | GG17: Y | GH17: BAMS Pick | GK17: No Treatment | GL17: 0 | GN17: Maintenance | GQ17: 8.99375 | GR17: 8.99685 | GS17: 8.99685 | GT17: N | GU17: 1 | GV17: 1 | GW17: 1 | GX17: N | GY17: 8.99375 | GZ17: N | HA17: Y | HB17: BAMS Pick | HE17: No Treatment | HF17: 0 | HH17: Maintenance | HK17: 8.86875 | HL17: 8.93385 | HM17: 8.93385 | HN17: N | HO17: 2 | HP17: 2 | HQ17: 2 | HR17: N | HS17: 8.86875 | HT17: N | HU17: Y | HV17: BAMS Pick | HY17: No Treatment | HZ17: 0 | IB17: Maintenance | IE17: 8.74375 | IF17: 8.87085 | IG17: 8.87085 | IH17: N | II17: 3 | IJ17: 3 | IK17: 3 | IL17: N | IM17: 8.74375 | IN17: N | IO17: Y | IP17: BAMS Pick | IS17: No Treatment | IT17: 0 | IV17: Maintenance | IY17: 8.61875 | IZ17: 8.80785 | JA17: 8.80785 | JB17: N | JC17: 4 | JD17: 4 | JE17: 4 | JF17: N | JG17: 8.61875 | JH17: N | JI17: Y | JJ17: BAMS Pick | JM17: No Treatment | JN17: 0 | JP17: Maintenance | JS17: 8.49375 | JT17: 8.74485 | JU17: 8.74485 | JV17: N | JW17: 5 | JX17: 5 | JY17: 5 | JZ17: N | KA17: 8.49375 | KB17: N | KC17: Y | KD17: BAMS Pick | KG17: No Treatment | KH17: 0 | KJ17: Maintenance | KM17: 8.36875 | KN17: 8.68185 | KO17: 8.68185 | KP17: N | KQ17: 6 | KR17: 6 | KS17: 6 | KT17: N | KU17: 8.36875 | KV17: N | KW17: Y | KX17: BAMS Pick | LA17: No Treatment | LB17: 0 | LD17: Maintenance
A18: Local | B18: B | C18: 51720504950005 | D18: 30041 | E18: 04 | F18: Pike | G18: 03 - Town or Township Highway Agency | H18: 205 | I18: NEPA RPO | K18: DECKER CREEK | L18: T406 HENDERSHOT RD | M18: T-406 Bridge, Lackawaxen Twp | N18: Town or Township Highway Agency | O18: 33 | P18: 801.9 | Q18: N | R18: Single | S18: 5 | T18: P/S, Box beam - adj | U18: N | V18: N | W18: 09 - Rural - Local | X18: N | Y18: Y | Z18: L | AA18: N | AB18: 06 - Bituminous (applies only to structures with no deck) | AC18: 4 | AD18: N | AE18: N | AF18: 1956 | AG18: 71 | AH18: 50 | AI18: 400 | AJ18: 99 | AK18: POSTED | AL18: 33 | AM18: N | AN18: B | AO18: P | AP18: N | AQ18: 0 - Not on Federal Route | AR18: N | AS18: N | AT18: Y | AU18: N | AV18: Y | AW18: N | AX18: bridge replacement | AY18: 900000 | AZ18: -- | BA18: 0 | BB18: -- | BC18: 0 | BD18: -- | BE18: 0 | BF18: -- | BG18: 0 | BH18: -- | BI18: 0 | BJ18: -- | BK18: 0 | BL18: -- | BM18: 0 | BN18: -- | BO18: 0 | BP18: -- | BQ18: 0 | BR18: -- | BS18: 0 | BT18: Yes | BU18: -- | BW18: Off | BX18: -- | BY18: -- | BZ18: -- | CA18: -- | CB18: -- | CC18: -- | CD18: -- | CE18: -- | CF18: -- | CG18: -- | CI18: 3.55 | CJ18: 3.56 | CK18: 3.57 | CL18: N | CM18: 3 | CN18: 3 | CO18: 3 | CP18: N | CQ18: 3.55 | CR18: Y | CS18: Y | CU18: 9.99 | CV18: 9.99 | CW18: 9.99 | CX18: N | CY18: 1 | CZ18: 1 | DA18: 1 | DB18: N | DC18: 9.99 | DD18: N | DE18: Y | DF18: BAMS Pick | DH18: NEPA_581 | DI18: Bridge Replacement | DJ18: 900000 | DL18: Replacement | DO18: 9.79 | DP18: 9.79 | DQ18: 9.79 | DR18: N | DS18: 2 | DT18: 2 | DU18: 2 | DV18: N | DW18: 9.79 | DX18: N | DY18: Y | DZ18: BAMS Pick | EC18: No Treatment | ED18: 0 | EF18: Maintenance | EI18: 9.59 | EJ18: 9.59 | EK18: 9.59 | EL18: N | EM18: 3 | EN18: 3 | EO18: 3 | EP18: N | EQ18: 9.59 | ER18: N | ES18: Y | ET18: BAMS Pick | EW18: No Treatment | EX18: 0 | EZ18: Maintenance | FC18: 9.39 | FD18: 9.39 | FE18: 9.39 | FF18: N | FG18: 4 | FH18: 4 | FI18: 4 | FJ18: N | FK18: 9.39 | FL18: N | FM18: Y | FN18: BAMS Pick | FQ18: No Treatment | FR18: 0 | FT18: Maintenance | FW18: 9.19 | FX18: 9.19 | FY18: 9.19 | FZ18: N | GA18: 5 | GB18: 5 | GC18: 5 | GD18: N | GE18: 9.19 | GF18: N | GG18: Y | GH18: BAMS Pick | GK18: No Treatment | GL18: 0 | GN18: Maintenance | GQ18: 8.99375 | GR18: 8.99685 | GS18: 8.99685 | GT18: N | GU18: 1 | GV18: 1 | GW18: 1 | GX18: N | GY18: 8.99375 | GZ18: N | HA18: Y | HB18: BAMS Pick | HE18: No Treatment | HF18: 0 | HH18: Maintenance | HK18: 8.86875 | HL18: 8.93385 | HM18: 8.93385 | HN18: N | HO18: 2 | HP18: 2 | HQ18: 2 | HR18: N | HS18: 8.86875 | HT18: N | HU18: Y | HV18: BAMS Pick | HY18: No Treatment | HZ18: 0 | IB18: Maintenance | IE18: 8.74375 | IF18: 8.87085 | IG18: 8.87085 | IH18: N | II18: 3 | IJ18: 3 | IK18: 3 | IL18: N | IM18: 8.74375 | IN18: N | IO18: Y | IP18: BAMS Pick | IS18: No Treatment | IT18: 0 | IV18: Maintenance | IY18: 8.61875 | IZ18: 8.80785 | JA18: 8.80785 | JB18: N | JC18: 4 | JD18: 4 | JE18: 4 | JF18: N | JG18: 8.61875 | JH18: N | JI18: Y | JJ18: BAMS Pick | JM18: No Treatment | JN18: 0 | JP18: Maintenance | JS18: 8.49375 | JT18: 8.74485 | JU18: 8.74485 | JV18: N | JW18: 5 | JX18: 5 | JY18: 5 | JZ18: N | KA18: 8.49375 | KB18: N | KC18: Y | KD18: BAMS Pick | KG18: No Treatment | KH18: 0 | KJ18: Maintenance | KM18: 8.36875 | KN18: 8.68185 | KO18: 8.68185 | KP18: N | KQ18: 6 | KR18: 6 | KS18: 6 | KT18: N | KU18: 8.36875 | KV18: N | KW18: Y | KX18: BAMS Pick | LA18: No Treatment | LB18: 0 | LD18: Maintenance
A19: Local | B19: B | C19: 51720603010116 | D19: 30048 | E19: 04 | F19: Pike | G19: 02 - County Highway Agency | H19: 051 | I19: NEPA RPO | K19: LITTLE BUSHKILL CREEK | L19: T301(CO.BR.16) | M19: BUSHKILL,-PETERS MILL | N19: County Highway Agency | O19: 47 | P19: 1212.6 | Q19: N | R19: Single | S19: 1 | T19: Concr. encased steel, I beams | U19: N | V19: N | W19: 09 - Rural - Local | X19: N | Y19: Y | Z19: L | AA19: N | AB19: 06 - Bituminous (applies only to structures with no deck) | AC19: 5 | AD19: 5 | AE19: 6 | AF19: 1931 | AG19: 96 | AH19: 300 | AI19: 603 | AJ19: 5 | AK19: POSTED | AL19: 47 | AM19: N | AN19: B | AO19: P | AP19: N | AQ19: 0 - Not on Federal Route | AR19: N | AS19: N | AT19: Y | AU19: N | AV19: Y | AW19: N | AX19: bridge replacement | AY19: 1333860 | AZ19: -- | BA19: 0 | BB19: -- | BC19: 0 | BD19: -- | BE19: 0 | BF19: -- | BG19: 0 | BH19: -- | BI19: 0 | BJ19: -- | BK19: 0 | BL19: -- | BM19: 0 | BN19: -- | BO19: 0 | BP19: -- | BQ19: 0 | BR19: -- | BS19: 0 | BT19: Yes | BU19: -- | BW19: Off | BX19: -- | BY19: -- | BZ19: -- | CA19: -- | CB19: -- | CC19: -- | CD19: -- | CE19: -- | CF19: -- | CG19: -- | CI19: 5.117 | CJ19: 4.11 | CK19: 4.415 | CL19: N | CM19: 34 | CN19: 24 | CO19: 12 | CP19: N | CQ19: 4.11 | CR19: Y | CS19: Y | CU19: 9.99 | CV19: 9.99 | CW19: 9.99 | CX19: N | CY19: 1 | CZ19: 1 | DA19: 1 | DB19: N | DC19: 9.99 | DD19: N | DE19: Y | DF19: BAMS Pick | DH19: NEPA_581 | DI19: Bridge Replacement | DJ19: 1333860 | DL19: Replacement | DO19: 9.79 | DP19: 9.79 | DQ19: 9.79 | DR19: N | DS19: 2 | DT19: 2 | DU19: 2 | DV19: N | DW19: 9.79 | DX19: N | DY19: Y | DZ19: BAMS Pick | EC19: No Treatment | ED19: 0 | EF19: Maintenance | EI19: 9.59 | EJ19: 9.59 | EK19: 9.59 | EL19: N | EM19: 3 | EN19: 3 | EO19: 3 | EP19: N | EQ19: 9.59 | ER19: N | ES19: Y | ET19: BAMS Pick | EW19: No Treatment | EX19: 0 | EZ19: Maintenance | FC19: 9.39 | FD19: 9.39 | FE19: 9.39 | FF19: N | FG19: 4 | FH19: 4 | FI19: 4 | FJ19: N | FK19: 9.39 | FL19: N | FM19: Y | FN19: BAMS Pick | FQ19: No Treatment | FR19: 0 | FT19: Maintenance | FW19: 9.19 | FX19: 9.19 | FY19: 9.19 | FZ19: N | GA19: 5 | GB19: 5 | GC19: 5 | GD19: N | GE19: 9.19 | GF19: N | GG19: Y | GH19: BAMS Pick | GK19: No Treatment | GL19: 0 | GN19: Maintenance | GQ19: 8.99375 | GR19: 8.99375 | GS19: 8.995 | GT19: N | GU19: 1 | GV19: 1 | GW19: 1 | GX19: N | GY19: 8.99375 | GZ19: N | HA19: Y | HB19: BAMS Pick | HE19: No Treatment | HF19: 0 | HH19: Maintenance | HK19: 8.86875 | HL19: 8.86875 | HM19: 8.895 | HN19: N | HO19: 2 | HP19: 2 | HQ19: 2 | HR19: N | HS19: 8.86875 | HT19: N | HU19: Y | HV19: BAMS Pick | HY19: No Treatment | HZ19: 0 | IB19: Maintenance | IE19: 8.74375 | IF19: 8.74375 | IG19: 8.795 | IH19: N | II19: 3 | IJ19: 3 | IK19: 3 | IL19: N | IM19: 8.74375 | IN19: N | IO19: Y | IP19: BAMS Pick | IS19: No Treatment | IT19: 0 | IV19: Maintenance | IY19: 8.61875 | IZ19: 8.61875 | JA19: 8.695 | JB19: N | JC19: 4 | JD19: 4 | JE19: 4 | JF19: N | JG19: 8.61875 | JH19: N | JI19: Y | JJ19: BAMS Pick | JM19: No Treatment | JN19: 0 | JP19: Maintenance | JS19: 8.49375 | JT19: 8.49375 | JU19: 8.595 | JV19: N | JW19: 5 | JX19: 5 | JY19: 5 | JZ19: N | KA19: 8.49375 | KB19: N | KC19: Y | KD19: BAMS Pick | KG19: No Treatment | KH19: 0 | KJ19: Maintenance | KM19: 8.36875 | KN19: 8.36875 | KO19: 8.495 | KP19: N | KQ19: 6 | KR19: 6 | KS19: 6 | KT19: N | KU19: 8.36875 | KV19: N | KW19: Y | KX19: BAMS Pick | LA19: No Treatment | LB19: 0 | LD19: Maintenance
A20: Local | B20: B | C20: 51720603020119 | D20: 30049 | E20: 04 | F20: Pike | G20: 02 - County Highway Agency | H20: 051 | I20: NEPA RPO | K20: BUSHKILL CREEK | L20: T-301 WINONA FALLS | M20: Co Br #19 (Lehman Twp) | N20: County Highway Agency | O20: 122 | P20: 3403.8 | Q20: N | R20: Multi | S20: 5 | T20: P/S, Box beam - adj | U20: N | V20: N | W20: 09 - Rural - Local | X20: N | Y20: Y | Z20: L | AA20: N | AB20: 06 - Bituminous (applies only to structures with no deck) | AC20: 6 | AD20: N | AE20: N | AF20: 1956 | AG20: 71 | AH20: 1400 | AI20: 2183 | AJ20: 5 | AK20: POSTED | AL20: 22 | AM20: Y | AN20: -- | AO20: P | AP20: N | AQ20: 0 - Not on Federal Route | AR20: N | AS20: N | AT20: Y | AU20: N | AV20: Y | AW20: N | AX20: leaking deck joint replacement | AY20: 17019 | AZ20: superstructure rep rehab | BA20: 1577661.3 | BB20: -- | BC20: 0 | BD20: -- | BE20: 0 | BF20: -- | BG20: 0 | BH20: -- | BI20: 0 | BJ20: -- | BK20: 0 | BL20: -- | BM20: 0 | BN20: -- | BO20: 0 | BP20: -- | BQ20: 0 | BR20: -- | BS20: 0 | BT20: Yes | BU20: Yes | BW20: -- | BX20: Off | BY20: -- | BZ20: -- | CA20: -- | CB20: -- | CC20: -- | CD20: -- | CE20: -- | CF20: -- | CG20: -- | CI20: 4.288 | CJ20: 4.287 | CK20: 6.435 | CL20: N | CM20: 12 | CN20: 12 | CO20: 12 | CP20: N | CQ20: 4.287 | CR20: Y | CS20: Y | CU20: 4.288 | CV20: 4.787 | CW20: 6.685 | CX20: N | CY20: 12 | CZ20: 12 | DA20: 12 | DB20: N | DC20: 4.288 | DD20: Y | DE20: Y | DF20: BAMS Pick | DH20: NEPA_581 | DI20: Leaking Deck Joint Replacement | DJ20: 17019 | DL20: Preservation | DO20: 9.99 | DP20: 9.99 | DQ20: 7.585 | DR20: N | DS20: 1 | DT20: 1 | DU20: 1 | DV20: N | DW20: 7.585 | DX20: N | DY20: Y | DZ20: BAMS Pick | EB20: NEPA_581 | EC20: Superstructure Rep Rehab | ED20: 1577661.3 | EF20: Rehabilitation | EI20: 9.79 | EJ20: 9.79 | EK20: 7.485 | EL20: N | EM20: 2 | EN20: 2 | EO20: 2 | EP20: N | EQ20: 7.485 | ER20: N | ES20: Y | ET20: BAMS Pick | EW20: No Treatment | EX20: 0 | EZ20: Maintenance | FC20: 9.59 | FD20: 9.59 | FE20: 7.385 | FF20: N | FG20: 3 | FH20: 3 | FI20: 3 | FJ20: N | FK20: 7.385 | FL20: N | FM20: Y | FN20: BAMS Pick | FQ20: No Treatment | FR20: 0 | FT20: Maintenance | FW20: 9.39 | FX20: 9.39 | FY20: 7.285 | FZ20: N | GA20: 4 | GB20: 4 | GC20: 4 | GD20: N | GE20: 7.285 | GF20: N | GG20: Y | GH20: BAMS Pick | GK20: No Treatment | GL20: 0 | GN20: Maintenance | GQ20: 9.19 | GR20: 9.19 | GS20: 7.185 | GT20: N | GU20: 5 | GV20: 5 | GW20: 5 | GX20: N | GY20: 7.185 | GZ20: N | HA20: Y | HB20: BAMS Pick | HE20: No Treatment | HF20: 0 | HH20: Maintenance | HK20: 8.995 | HL20: 8.995 | HM20: 7.085 | HN20: N | HO20: 1 | HP20: 1 | HQ20: 6 | HR20: N | HS20: 7.085 | HT20: N | HU20: Y | HV20: BAMS Pick | HY20: No Treatment | HZ20: 0 | IB20: Maintenance | IE20: 8.895 | IF20: 8.895 | IG20: 6.985 | IH20: N | II20: 2 | IJ20: 2 | IK20: 1 | IL20: N | IM20: 6.985 | IN20: N | IO20: Y | IP20: BAMS Pick | IS20: No Treatment | IT20: 0 | IV20: Maintenance | IY20: 8.795 | IZ20: 8.795 | JA20: 6.885 | JB20: N | JC20: 3 | JD20: 3 | JE20: 2 | JF20: N | JG20: 6.885 | JH20: N | JI20: Y | JJ20: BAMS Pick | JM20: No Treatment | JN20: 0 | JP20: Maintenance | JS20: 8.695 | JT20: 8.695 | JU20: 6.785 | JV20: N | JW20: 4 | JX20: 4 | JY20: 3 | JZ20: N | KA20: 6.785 | KB20: N | KC20: Y | KD20: BAMS Pick | KG20: No Treatment | KH20: 0 | KJ20: Maintenance | KM20: 8.595 | KN20: 8.595 | KO20: 6.685 | KP20: N | KQ20: 5 | KR20: 5 | KS20: 4 | KT20: N | KU20: 6.685 | KV20: N | KW20: Y | KX20: BAMS Pick | LA20: No Treatment | LB20: 0 | LD20: Maintenance
A21: Local | B21: B | C21: 51720603050118 | D21: 30050 | E21: 04 | F21: Pike | G21: 02 - County Highway Agency | H21: 051 | I21: NEPA RPO | K21: LITTLE BUSHKILL CREEK | L21: T-305 E SUGAR MTN | M21: Co Br #18 (Lehman Twp) | N21: County Highway Agency | O21: 75 | P21: 1822.5 | Q21: N | R21: Single | S21: 5 | T21: P/S, Box beam - adj | U21: N | V21: N | W21: 09 - Rural - Local | X21: N | Y21: Y | Z21: L | AA21: N | AB21: 06 - Bituminous (applies only to structures with no deck) | AC21: 6 | AD21: N | AE21: N | AF21: 1956 | AG21: 71 | AH21: 300 | AI21: 739 | AJ21: 5 | AK21: POSTED | AL21: 17 | AM21: N | AN21: -- | AO21: P | AP21: N | AQ21: 0 - Not on Federal Route | AR21: N | AS21: N | AT21: Y | AU21: N | AV21: Y | AW21: N | AX21: -- | AY21: 0 | AZ21: bridge replacement | BA21: 2064892.5 | BB21: -- | BC21: 0 | BD21: -- | BE21: 0 | BF21: -- | BG21: 0 | BH21: -- | BI21: 0 | BJ21: -- | BK21: 0 | BL21: -- | BM21: 0 | BN21: -- | BO21: 0 | BP21: -- | BQ21: 0 | BR21: -- | BS21: 0 | BT21: Yes | BU21: -- | BW21: -- | BX21: Off | BY21: -- | BZ21: -- | CA21: -- | CB21: -- | CC21: -- | CD21: -- | CE21: -- | CF21: -- | CG21: -- | CI21: 4.287 | CJ21: 4.3 | CK21: 4.727 | CL21: N | CM21: 12 | CN21: 12 | CO21: 3 | CP21: N | CQ21: 4.287 | CR21: Y | CS21: Y | CU21: 4.287 | CV21: 4.3 | CW21: 4.727 | CX21: N | CY21: 12 | CZ21: 12 | DA21: 3 | DB21: N | DC21: 4.287 | DD21: Y | DE21: Y | DF21: BAMS Pick | DI21: No Treatment | DJ21: 0 | DL21: Maintenance | DO21: 9.99 | DP21: 9.99 | DQ21: 9.99 | DR21: N | DS21: 1 | DT21: 1 | DU21: 1 | DV21: N | DW21: 9.99 | DX21: N | DY21: Y | DZ21: BAMS Pick | EB21: NEPA_581 | EC21: Bridge Replacement | ED21: 2064892.5 | EF21: Replacement | EI21: 9.79 | EJ21: 9.79 | EK21: 9.79 | EL21: N | EM21: 2 | EN21: 2 | EO21: 2 | EP21: N | EQ21: 9.79 | ER21: N | ES21: Y | ET21: BAMS Pick | EW21: No Treatment | EX21: 0 | EZ21: Maintenance | FC21: 9.59 | FD21: 9.59 | FE21: 9.59 | FF21: N | FG21: 3 | FH21: 3 | FI21: 3 | FJ21: N | FK21: 9.59 | FL21: N | FM21: Y | FN21: BAMS Pick | FQ21: No Treatment | FR21: 0 | FT21: Maintenance | FW21: 9.39 | FX21: 9.39 | FY21: 9.39 | FZ21: N | GA21: 4 | GB21: 4 | GC21: 4 | GD21: N | GE21: 9.39 | GF21: N | GG21: Y | GH21: BAMS Pick | GK21: No Treatment | GL21: 0 | GN21: Maintenance | GQ21: 9.19 | GR21: 9.19 | GS21: 9.19 | GT21: N | GU21: 5 | GV21: 5 | GW21: 5 | GX21: N | GY21: 9.19 | GZ21: N | HA21: Y | HB21: BAMS Pick | HE21: No Treatment | HF21: 0 | HH21: Maintenance | HK21: 8.99375 | HL21: 8.99685 | HM21: 8.99685 | HN21: N | HO21: 1 | HP21: 1 | HQ21: 1 | HR21: N | HS21: 8.99375 | HT21: N | HU21: Y | HV21: BAMS Pick | HY21: No Treatment | HZ21: 0 | IB21: Maintenance | IE21: 8.86875 | IF21: 8.93385 | IG21: 8.93385 | IH21: N | II21: 2 | IJ21: 2 | IK21: 2 | IL21: N | IM21: 8.86875 | IN21: N | IO21: Y | IP21: BAMS Pick | IS21: No Treatment | IT21: 0 | IV21: Maintenance | IY21: 8.74375 | IZ21: 8.87085 | JA21: 8.87085 | JB21: N | JC21: 3 | JD21: 3 | JE21: 3 | JF21: N | JG21: 8.74375 | JH21: N | JI21: Y | JJ21: BAMS Pick | JM21: No Treatment | JN21: 0 | JP21: Maintenance | JS21: 8.61875 | JT21: 8.80785 | JU21: 8.80785 | JV21: N | JW21: 4 | JX21: 4 | JY21: 4 | JZ21: N | KA21: 8.61875 | KB21: N | KC21: Y | KD21: BAMS Pick | KG21: No Treatment | KH21: 0 | KJ21: Maintenance | KM21: 8.49375 | KN21: 8.74485 | KO21: 8.74485 | KP21: N | KQ21: 5 | KR21: 5 | KS21: 5 | KT21: N | KU21: 8.49375 | KV21: N | KW21: Y | KX21: BAMS Pick | LA21: No Treatment | LB21: 0 | LD21: Maintenance
A22: Local | B22: B | C22: 51720803510005 | D22: 30059 | E22: 04 | F22: Pike | G22: 03 - Town or Township Highway Agency | H22: 208 | I22: NEPA RPO | K22: KLEINHANS CREEK | L22: T351 OLD GREENTOWN | M22: T-351 Bridge, Palmyra Twp | N22: Town or Township Highway Agency | O22: 29 | P22: 696 | Q22: N | R22: Single | S22: 5 | T22: P/S, Box beam - adj | U22: N | V22: N | W22: 09 - Rural - Local | X22: N | Y22: Y | Z22: L | AA22: N | AB22: 06 - Bituminous (applies only to structures with no deck) | AC22: 6 | AD22: N | AE22: N | AF22: 1958 | AG22: 69 | AH22: 50 | AI22: 280 | AJ22: 25 | AK22: POSTED | AL22: 57 | AM22: N | AN22: -- | AO22: H | AP22: N | AQ22: 0 - Not on Federal Route | AR22: N | AS22: N | AT22: Y | AU22: N | AV22: Y | AW22: N | AX22: culvert replacement (box frame | AY22: 1183200 | AZ22: -- | BA22: 0 | BB22: -- | BC22: 0 | BD22: -- | BE22: 0 | BF22: -- | BG22: 0 | BH22: -- | BI22: 0 | BJ22: -- | BK22: 0 | BL22: -- | BM22: 0 | BN22: -- | BO22: 0 | BP22: -- | BQ22: 0 | BR22: -- | BS22: 0 | BT22: Yes | BU22: -- | BW22: Off | BX22: -- | BY22: -- | BZ22: -- | CA22: -- | CB22: -- | CC22: -- | CD22: -- | CE22: -- | CF22: -- | CG22: -- | CI22: 4.286 | CJ22: 4.313 | CK22: 7.063 | CL22: N | CM22: 12 | CN22: 12 | CO22: 40 | CP22: N | CQ22: 4.286 | CR22: Y | CS22: Y | CU22: 9.99 | CV22: 9.99 | CW22: 9.99 | CX22: N | CY22: 1 | CZ22: 1 | DA22: 1 | DB22: N | DC22: 9.99 | DD22: N | DE22: Y | DF22: BAMS Pick | DH22: NEPA_581 | DI22: Culvert Replacement (Box Frame | DJ22: 1183200 | DL22: Replacement | DO22: 9.79 | DP22: 9.79 | DQ22: 9.79 | DR22: N | DS22: 2 | DT22: 2 | DU22: 2 | DV22: N | DW22: 9.79 | DX22: N | DY22: Y | DZ22: BAMS Pick | EC22: No Treatment | ED22: 0 | EF22: Maintenance | EI22: 9.59 | EJ22: 9.59 | EK22: 9.59 | EL22: N | EM22: 3 | EN22: 3 | EO22: 3 | EP22: N | EQ22: 9.59 | ER22: N | ES22: Y | ET22: BAMS Pick | EW22: No Treatment | EX22: 0 | EZ22: Maintenance | FC22: 9.39 | FD22: 9.39 | FE22: 9.39 | FF22: N | FG22: 4 | FH22: 4 | FI22: 4 | FJ22: N | FK22: 9.39 | FL22: N | FM22: Y | FN22: BAMS Pick | FQ22: No Treatment | FR22: 0 | FT22: Maintenance | FW22: 9.19 | FX22: 9.19 | FY22: 9.19 | FZ22: N | GA22: 5 | GB22: 5 | GC22: 5 | GD22: N | GE22: 9.19 | GF22: N | GG22: Y | GH22: BAMS Pick | GK22: No Treatment | GL22: 0 | GN22: Maintenance | GQ22: 8.99375 | GR22: 8.99685 | GS22: 8.99685 | GT22: N | GU22: 1 | GV22: 1 | GW22: 1 | GX22: N | GY22: 8.99375 | GZ22: N | HA22: Y | HB22: BAMS Pick | HE22: No Treatment | HF22: 0 | HH22: Maintenance | HK22: 8.86875 | HL22: 8.93385 | HM22: 8.93385 | HN22: N | HO22: 2 | HP22: 2 | HQ22: 2 | HR22: N | HS22: 8.86875 | HT22: N | HU22: Y | HV22: BAMS Pick | HY22: No Treatment | HZ22: 0 | IB22: Maintenance | IE22: 8.74375 | IF22: 8.87085 | IG22: 8.87085 | IH22: N | II22: 3 | IJ22: 3 | IK22: 3 | IL22: N | IM22: 8.74375 | IN22: N | IO22: Y | IP22: BAMS Pick | IS22: No Treatment | IT22: 0 | IV22: Maintenance | IY22: 8.61875 | IZ22: 8.80785 | JA22: 8.80785 | JB22: N | JC22: 4 | JD22: 4 | JE22: 4 | JF22: N | JG22: 8.61875 | JH22: N | JI22: Y | JJ22: BAMS Pick | JM22: No Treatment | JN22: 0 | JP22: Maintenance | JS22: 8.49375 | JT22: 8.74485 | JU22: 8.74485 | JV22: N | JW22: 5 | JX22: 5 | JY22: 5 | JZ22: N | KA22: 8.49375 | KB22: N | KC22: Y | KD22: BAMS Pick | KG22: No Treatment | KH22: 0 | KJ22: Maintenance | KM22: 8.36875 | KN22: 8.68185 | KO22: 8.68185 | KP22: N | KQ22: 6 | KR22: 6 | KS22: 6 | KT22: N | KU22: 8.36875 | KV22: N | KW22: Y | KX22: BAMS Pick | LA22: No Treatment | LB22: 0 | LD22: Maintenance
A23: Local | B23: B | C23: 51721004400010 | D23: 30066 | E23: 04 | F23: Pike | G23: 03 - Town or Township Highway Agency | H23: 210 | I23: NEPA RPO | K23: TRIB. TO SHOHOLA CREEK | L23: T440 (TWP. BR. 2) | M23: T-440 Bridge #2, Shohola Twp | N23: Town or Township Highway Agency | O23: 40 | P23: 972 | Q23: N | R23: Single | S23: 5 | T23: P/S, Box beam - adj | U23: N | V23: N | W23: 09 - Rural - Local | X23: N | Y23: Y | Z23: L | AA23: N | AB23: 06 - Bituminous (applies only to structures with no deck) | AC23: 5 | AD23: N | AE23: N | AF23: 1956 | AG23: 71 | AH23: 50 | AI23: 220 | AJ23: 7 | AK23: OPEN | AL23: 66 | AM23: N | AN23: -- | AO23: H | AP23: N | AQ23: 0 - Not on Federal Route | AR23: N | AS23: N | AT23: Y | AU23: N | AV23: Y | AW23: N | AX23: superstructure rep rehab | AY23: 437400 | AZ23: -- | BA23: 0 | BB23: -- | BC23: 0 | BD23: -- | BE23: 0 | BF23: -- | BG23: 0 | BH23: -- | BI23: 0 | BJ23: -- | BK23: 0 | BL23: -- | BM23: 0 | BN23: -- | BO23: 0 | BP23: -- | BQ23: 0 | BR23: -- | BS23: 0 | BT23: Yes | BU23: -- | BW23: Off | BX23: -- | BY23: -- | BZ23: -- | CA23: -- | CB23: -- | CC23: -- | CD23: -- | CE23: -- | CF23: -- | CG23: -- | CI23: 4.587 | CJ23: 4.581 | CK23: 5.512 | CL23: N | CM23: 6 | CN23: 6 | CO23: 12 | CP23: N | CQ23: 4.581 | CR23: Y | CS23: N | CU23: 9.99 | CV23: 9.99 | CW23: 6.99 | CX23: N | CY23: 1 | CZ23: 1 | DA23: 1 | DB23: N | DC23: 6.99 | DD23: N | DE23: N | DF23: BAMS Pick | DH23: NEPA_581 | DI23: Superstructure Rep Rehab | DJ23: 437400 | DL23: Rehabilitation | DO23: 9.79 | DP23: 9.79 | DQ23: 6.931 | DR23: N | DS23: 2 | DT23: 2 | DU23: 2 | DV23: N | DW23: 6.931 | DX23: N | DY23: N | DZ23: BAMS Pick | EC23: No Treatment | ED23: 0 | EF23: Maintenance | EI23: 9.59 | EJ23: 9.59 | EK23: 6.872 | EL23: N | EM23: 3 | EN23: 3 | EO23: 3 | EP23: N | EQ23: 6.872 | ER23: N | ES23: N | ET23: BAMS Pick | EW23: No Treatment | EX23: 0 | EZ23: Maintenance | FC23: 9.39 | FD23: 9.39 | FE23: 6.813 | FF23: N | FG23: 4 | FH23: 4 | FI23: 4 | FJ23: N | FK23: 6.813 | FL23: N | FM23: N | FN23: BAMS Pick | FQ23: No Treatment | FR23: 0 | FT23: Maintenance | FW23: 9.19 | FX23: 9.19 | FY23: 6.754 | FZ23: N | GA23: 5 | GB23: 5 | GC23: 5 | GD23: N | GE23: 6.754 | GF23: N | GG23: N | GH23: BAMS Pick | GK23: No Treatment | GL23: 0 | GN23: Maintenance | GQ23: 8.99375 | GR23: 8.99685 | GS23: 6.695 | GT23: N | GU23: 1 | GV23: 1 | GW23: 6 | GX23: N | GY23: 6.695 | GZ23: N | HA23: N | HB23: BAMS Pick | HE23: No Treatment | HF23: 0 | HH23: Maintenance | HK23: 8.86875 | HL23: 8.93385 | HM23: 6.636 | HN23: N | HO23: 2 | HP23: 2 | HQ23: 7 | HR23: N | HS23: 6.636 | HT23: N | HU23: N | HV23: BAMS Pick | HY23: No Treatment | HZ23: 0 | IB23: Maintenance | IE23: 8.74375 | IF23: 8.87085 | IG23: 6.577 | IH23: N | II23: 3 | IJ23: 3 | IK23: 8 | IL23: N | IM23: 6.577 | IN23: N | IO23: N | IP23: BAMS Pick | IS23: No Treatment | IT23: 0 | IV23: Maintenance | IY23: 8.61875 | IZ23: 8.80785 | JA23: 6.518 | JB23: N | JC23: 4 | JD23: 4 | JE23: 9 | JF23: N | JG23: 6.518 | JH23: N | JI23: N | JJ23: BAMS Pick | JM23: No Treatment | JN23: 0 | JP23: Maintenance | JS23: 8.49375 | JT23: 8.74485 | JU23: 6.459 | JV23: N | JW23: 5 | JX23: 5 | JY23: 10 | JZ23: N | KA23: 6.459 | KB23: N | KC23: N | KD23: BAMS Pick | KG23: No Treatment | KH23: 0 | KJ23: Maintenance | KM23: 8.36875 | KN23: 8.68185 | KO23: 6.4 | KP23: N | KQ23: 6 | KR23: 6 | KS23: 11 | KT23: N | KU23: 6.4 | KV23: N | KW23: N | KX23: BAMS Pick | LA23: No Treatment | LB23: 0 | LD23: Maintenance
A24: Local | B24: B | C24: 51721004400124 | D24: 30067 | E24: 04 | F24: Pike | G24: 02 - County Highway Agency | H24: 051 | I24: NEPA RPO | K24: BALLIARD CREEK | L24: SHOHOLA FALLS ROAD | M24: PIKE COUNTY BRIDGE #24 | N24: County Highway Agency | O24: 36 | P24: 640.8 | Q24: N | R24: Single | S24: 6 | T24: Concrete(in place), Arch deck - closed | U24: N | V24: N | W24: 09 - Rural - Local | X24: N | Y24: Y | Z24: L | AA24: N | AB24: N - Not applicable | AC24: 10 | AD24: N | AE24: N | AF24: 1912 | AG24: 115 | AH24: 50 | AI24: 179 | AJ24: 3 | AK24: POSTED | AL24: 45 | AM24: N | AN24: -- | AO24: P | AP24: N | AQ24: 0 - Not on Federal Route | AR24: N | AS24: N | AT24: Y | AU24: N | AV24: Y | AW24: N | AX24: -- | AY24: 0 | AZ24: -- | BA24: 0 | BB24: -- | BC24: 0 | BD24: -- | BE24: 0 | BF24: -- | BG24: 0 | BH24: bridge replacement | BI24: 1043346.7 | BJ24: -- | BK24: 0 | BL24: -- | BM24: 0 | BN24: -- | BO24: 0 | BP24: -- | BQ24: 0 | BR24: -- | BS24: 0 | BT24: Yes | BU24: -- | BW24: -- | BX24: -- | BY24: -- | BZ24: -- | CA24: -- | CB24: Off | CC24: -- | CD24: -- | CE24: -- | CF24: -- | CG24: -- | CI24: 9.6 | CJ24: 4.597 | CK24: 4.611 | CL24: N | CM24: 1 | CN24: 6 | CO24: 6 | CP24: N | CQ24: 4.597 | CR24: Y | CS24: Y | CU24: 9.6 | CV24: 4.597 | CW24: 4.611 | CX24: N | CY24: 1 | CZ24: 6 | DA24: 6 | DB24: N | DC24: 4.597 | DD24: Y | DE24: Y | DF24: BAMS Pick | DI24: No Treatment | DJ24: 0 | DL24: Maintenance | DO24: 9.4 | DP24: 4.514 | DQ24: 4.534 | DR24: N | DS24: 2 | DT24: 7 | DU24: 7 | DV24: N | DW24: 4.514 | DX24: Y | DY24: Y | DZ24: BAMS Pick | EC24: No Treatment | ED24: 0 | EF24: Maintenance | EI24: 9.2 | EJ24: 4.431 | EK24: 4.457 | EL24: N | EM24: 3 | EN24: 8 | EO24: 8 | EP24: N | EQ24: 4.431 | ER24: Y | ES24: Y | ET24: BAMS Pick | EW24: No Treatment | EX24: 0 | EZ24: Maintenance | FC24: 9 | FD24: 4.348 | FE24: 4.38 | FF24: N | FG24: 4 | FH24: 9 | FI24: 9 | FJ24: N | FK24: 4.348 | FL24: Y | FM24: Y | FN24: BAMS Pick | FQ24: No Treatment | FR24: 0 | FT24: Maintenance | FW24: 8.917 | FX24: 4.265 | FY24: 4.303 | FZ24: N | GA24: 1 | GB24: 10 | GC24: 10 | GD24: N | GE24: 4.265 | GF24: Y | GG24: Y | GH24: BAMS Pick | GK24: No Treatment | GL24: 0 | GN24: Maintenance | GQ24: 9.99 | GR24: 9.99 | GS24: 9.99 | GT24: N | GU24: 1 | GV24: 1 | GW24: 1 | GX24: N | GY24: 9.99 | GZ24: N | HA24: Y | HB24: BAMS Pick | HD24: NEPA_581 | HE24: Bridge Replacement | HF24: 1043346.7 | HH24: Replacement | HK24: 9.79 | HL24: 9.79 | HM24: 9.79 | HN24: N | HO24: 2 | HP24: 2 | HQ24: 2 | HR24: N | HS24: 9.79 | HT24: N | HU24: Y | HV24: BAMS Pick | HY24: No Treatment | HZ24: 0 | IB24: Maintenance | IE24: 9.59 | IF24: 9.59 | IG24: 9.59 | IH24: N | II24: 3 | IJ24: 3 | IK24: 3 | IL24: N | IM24: 9.59 | IN24: N | IO24: Y | IP24: BAMS Pick | IS24: No Treatment | IT24: 0 | IV24: Maintenance | IY24: 9.39 | IZ24: 9.39 | JA24: 9.39 | JB24: N | JC24: 4 | JD24: 4 | JE24: 4 | JF24: N | JG24: 9.39 | JH24: N | JI24: Y | JJ24: BAMS Pick | JM24: No Treatment | JN24: 0 | JP24: Maintenance | JS24: 9.19 | JT24: 9.19 | JU24: 9.19 | JV24: N | JW24: 5 | JX24: 5 | JY24: 5 | JZ24: N | KA24: 9.19 | KB24: N | KC24: Y | KD24: BAMS Pick | KG24: No Treatment | KH24: 0 | KJ24: Maintenance | KM24: 8.99585 | KN24: 8.995 | KO24: 8.995 | KP24: N | KQ24: 1 | KR24: 1 | KS24: 1 | KT24: N | KU24: 8.995 | KV24: N | KW24: Y | KX24: BAMS Pick | LA24: No Treatment | LB24: 0 | LD24: Maintenance
A25: Local | B25: B | C25: 51740203930122 | D25: 30069 | E25: 04 | F25: Pike | G25: 02 - County Highway Agency | H25: 051 | I25: NEPA RPO | K25: VANDERMARK CREEK | L25: BROAD STREET | M25: PIKE COUNTY BRIDGE #22 | N25: County Highway Agency | O25: 24 | P25: 580.8 | Q25: N | R25: Single | S25: 6 | T25: Masonry, Arch deck - closed | U25: N | V25: N | W25: 09 - Rural - Local | X25: N | Y25: Y | Z25: L | AA25: N | AB25: N - Not applicable | AC25: 10 | AD25: N | AE25: N | AF25: 1867 | AG25: 160 | AH25: 50 | AI25: 170 | AJ25: 1 | AK25: OPEN | AL25: 67 | AM25: N | AN25: D | AO25: H | AP25: N | AQ25: 0 - Not on Federal Route | AR25: N | AS25: N | AT25: Y | AU25: N | AV25: Y | AW25: N | AX25: -- | AY25: 0 | AZ25: -- | BA25: 0 | BB25: -- | BC25: 0 | BD25: culvert replacement (box frame | BE25: 1078914.9 | BF25: -- | BG25: 0 | BH25: -- | BI25: 0 | BJ25: -- | BK25: 0 | BL25: -- | BM25: 0 | BN25: -- | BO25: 0 | BP25: -- | BQ25: 0 | BR25: -- | BS25: 0 | BT25: Yes | BU25: -- | BW25: -- | BX25: -- | BY25: -- | BZ25: -- | CA25: -- | CB25: -- | CC25: -- | CD25: -- | CE25: -- | CF25: -- | CG25: -- | CI25: 9.6 | CJ25: 4.703 | CK25: 5.313 | CL25: N | CM25: 1 | CN25: 4 | CO25: 20 | CP25: N | CQ25: 4.703 | CR25: Y | CS25: N | CU25: 9.6 | CV25: 4.703 | CW25: 5.313 | CX25: N | CY25: 1 | CZ25: 4 | DA25: 20 | DB25: N | DC25: 4.703 | DD25: Y | DE25: N | DF25: BAMS Pick | DI25: No Treatment | DJ25: 0 | DL25: Maintenance | DO25: 9.4 | DP25: 4.62 | DQ25: 5.246 | DR25: N | DS25: 2 | DT25: 5 | DU25: 21 | DV25: N | DW25: 4.62 | DX25: Y | DY25: N | DZ25: BAMS Pick | EC25: No Treatment | ED25: 0 | EF25: Maintenance | EI25: 9.2 | EJ25: 4.537 | EK25: 5.179 | EL25: N | EM25: 3 | EN25: 6 | EO25: 22 | EP25: N | EQ25: 4.537 | ER25: Y | ES25: N | ET25: BAMS Pick | EW25: No Treatment | EX25: 0 | EZ25: Maintenance | FC25: 9.99 | FD25: 9.99 | FE25: 9.99 | FF25: N | FG25: 1 | FH25: 1 | FI25: 1 | FJ25: N | FK25: 9.99 | FL25: N | FM25: N | FN25: BAMS Pick | FP25: NEPA_581 | FQ25: Culvert Replacement (Box Frame | FR25: 1078914.9 | FT25: Replacement | FW25: 9.79 | FX25: 9.79 | FY25: 9.79 | FZ25: N | GA25: 2 | GB25: 2 | GC25: 2 | GD25: N | GE25: 9.79 | GF25: N | GG25: N | GH25: BAMS Pick | GK25: No Treatment | GL25: 0 | GN25: Maintenance | GQ25: 9.59 | GR25: 9.59 | GS25: 9.59 | GT25: N | GU25: 3 | GV25: 3 | GW25: 3 | GX25: N | GY25: 9.59 | GZ25: N | HA25: N | HB25: BAMS Pick | HE25: No Treatment | HF25: 0 | HH25: Maintenance | HK25: 9.39 | HL25: 9.39 | HM25: 9.39 | HN25: N | HO25: 4 | HP25: 4 | HQ25: 4 | HR25: N | HS25: 9.39 | HT25: N | HU25: N | HV25: BAMS Pick | HY25: No Treatment | HZ25: 0 | IB25: Maintenance | IE25: 9.19 | IF25: 9.19 | IG25: 9.19 | IH25: N | II25: 5 | IJ25: 5 | IK25: 5 | IL25: N | IM25: 9.19 | IN25: N | IO25: N | IP25: BAMS Pick | IS25: No Treatment | IT25: 0 | IV25: Maintenance | IY25: 8.99585 | IZ25: 8.995 | JA25: 8.995 | JB25: N | JC25: 1 | JD25: 1 | JE25: 1 | JF25: N | JG25: 8.995 | JH25: N | JI25: N | JJ25: BAMS Pick | JM25: No Treatment | JN25: 0 | JP25: Maintenance | JS25: 8.91285 | JT25: 8.895 | JU25: 8.895 | JV25: N | JW25: 2 | JX25: 2 | JY25: 2 | JZ25: N | KA25: 8.895 | KB25: N | KC25: N | KD25: BAMS Pick | KG25: No Treatment | KH25: 0 | KJ25: Maintenance | KM25: 8.82985 | KN25: 8.795 | KO25: 8.795 | KP25: N | KQ25: 3 | KR25: 3 | KS25: 3 | KT25: N | KU25: 8.795 | KV25: N | KW25: N | KX25: BAMS Pick | LA25: No Treatment | LB25: 0 | LD25: Maintenance
A26: Local | B26: B | C26: 51740204250120 | D26: 30070 | E26: 04 | F26: Pike | G26: 02 - County Highway Agency | H26: 051 | I26: NEPA RPO | K26: SAWKILL CREEK | L26: T425(CO.BR.NO.20) | M26: Co Br #20 (Milford Boro) | N26: County Highway Agency | O26: 53 | P26: 1287.9 | Q26: N | R26: Single | S26: 5 | T26: P/S, Box beam - adj | U26: N | V26: N | W26: 09 - Rural - Local | X26: N | Y26: Y | Z26: L | AA26: N | AB26: 06 - Bituminous (applies only to structures with no deck) | AC26: 5 | AD26: N | AE26: N | AF26: 1956 | AG26: 71 | AH26: 50 | AI26: 254 | AJ26: 1 | AK26: POSTED | AL26: 48 | AM26: N | AN26: B | AO26: P | AP26: N | AQ26: 0 - Not on Federal Route | AR26: N | AS26: N | AT26: Y | AU26: N | AV26: Y | AW26: N | AX26: -- | AY26: 0 | AZ26: bridge replacement | BA26: 1459190.7 | BB26: -- | BC26: 0 | BD26: -- | BE26: 0 | BF26: -- | BG26: 0 | BH26: -- | BI26: 0 | BJ26: -- | BK26: 0 | BL26: -- | BM26: 0 | BN26: -- | BO26: 0 | BP26: -- | BQ26: 0 | BR26: -- | BS26: 0 | BT26: Yes | BU26: -- | BW26: -- | BX26: Off | BY26: -- | BZ26: -- | CA26: -- | CB26: -- | CC26: -- | CD26: -- | CE26: -- | CF26: -- | CG26: -- | CI26: 4.304 | CJ26: 4.329 | CK26: 4.225 | CL26: N | CM26: 12 | CN26: 12 | CO26: 16 | CP26: N | CQ26: 4.225 | CR26: Y | CS26: Y | CU26: 4.304 | CV26: 4.329 | CW26: 4.225 | CX26: N | CY26: 12 | CZ26: 12 | DA26: 16 | DB26: N | DC26: 4.225 | DD26: Y | DE26: Y | DF26: BAMS Pick | DI26: No Treatment | DJ26: 0 | DL26: Maintenance | DO26: 9.99 | DP26: 9.99 | DQ26: 9.99 | DR26: N | DS26: 1 | DT26: 1 | DU26: 1 | DV26: N | DW26: 9.99 | DX26: N | DY26: Y | DZ26: BAMS Pick | EB26: NEPA_581 | EC26: Bridge Replacement | ED26: 1459190.7 | EF26: Replacement | EI26: 9.79 | EJ26: 9.79 | EK26: 9.79 | EL26: N | EM26: 2 | EN26: 2 | EO26: 2 | EP26: N | EQ26: 9.79 | ER26: N | ES26: Y | ET26: BAMS Pick | EW26: No Treatment | EX26: 0 | EZ26: Maintenance | FC26: 9.59 | FD26: 9.59 | FE26: 9.59 | FF26: N | FG26: 3 | FH26: 3 | FI26: 3 | FJ26: N | FK26: 9.59 | FL26: N | FM26: Y | FN26: BAMS Pick | FQ26: No Treatment | FR26: 0 | FT26: Maintenance | FW26: 9.39 | FX26: 9.39 | FY26: 9.39 | FZ26: N | GA26: 4 | GB26: 4 | GC26: 4 | GD26: N | GE26: 9.39 | GF26: N | GG26: Y | GH26: BAMS Pick | GK26: No Treatment | GL26: 0 | GN26: Maintenance | GQ26: 9.19 | GR26: 9.19 | GS26: 9.19 | GT26: N | GU26: 5 | GV26: 5 | GW26: 5 | GX26: N | GY26: 9.19 | GZ26: N | HA26: Y | HB26: BAMS Pick | HE26: No Treatment | HF26: 0 | HH26: Maintenance | HK26: 8.99375 | HL26: 8.99685 | HM26: 8.99685 | HN26: N | HO26: 1 | HP26: 1 | HQ26: 1 | HR26: N | HS26: 8.99375 | HT26: N | HU26: Y | HV26: BAMS Pick | HY26: No Treatment | HZ26: 0 | IB26: Maintenance | IE26: 8.86875 | IF26: 8.93385 | IG26: 8.93385 | IH26: N | II26: 2 | IJ26: 2 | IK26: 2 | IL26: N | IM26: 8.86875 | IN26: N | IO26: Y | IP26: BAMS Pick | IS26: No Treatment | IT26: 0 | IV26: Maintenance | IY26: 8.74375 | IZ26: 8.87085 | JA26: 8.87085 | JB26: N | JC26: 3 | JD26: 3 | JE26: 3 | JF26: N | JG26: 8.74375 | JH26: N | JI26: Y | JJ26: BAMS Pick | JM26: No Treatment | JN26: 0 | JP26: Maintenance | JS26: 8.61875 | JT26: 8.80785 | JU26: 8.80785 | JV26: N | JW26: 4 | JX26: 4 | JY26: 4 | JZ26: N | KA26: 8.61875 | KB26: N | KC26: Y | KD26: BAMS Pick | KG26: No Treatment | KH26: 0 | KJ26: Maintenance | KM26: 8.49375 | KN26: 8.74485 | KO26: 8.74485 | KP26: N | KQ26: 5 | KR26: 5 | KS26: 5 | KT26: N | KU26: 8.49375 | KV26: N | KW26: Y | KX26: BAMS Pick | LA26: No Treatment | LB26: 0 | LD26: Maintenance

Sheet Funded Treatment List
A1: BridgeID | B1: BRKey (Hyperlink) | C1: District | D1: County | E1: MPO/RPO | F1: City/Town/Place | G1: Feature intersected | H1: Facility Carried | I1: Location/StructureName | J1: Bridge Length | K1: Deck Area | L1: Large Bridge | M1: Structure Type | N1: Functional Class | O1: BPN | P1: NHS | Q1: Interstate | R1: Risk Score | S1: Analysis Year(s) | U1: Project Pick | V1: Budget | W1: Treatment | X1: Yearly Cost | Y1: Total Project Cost | Z1: Prior GCR | AD1: Prior MIN | AE1: Resulting GCR | AI1: Resulting MIN
S2: Start | T2: End | Z2: DECK | AA2: SUP | AB2: SUB | AC2: CULV | AE2: DECK | AF2: SUP | AG2: SUB | AH2: CULV
A4: 51720104100102 | B4: =HYPERLINK("https://www.google.com/maps/place/41°21'47""N,75°4'31.800000000046566""W/data=!3m1!1e3", "30015") -> 30015 | C4: 4 | D4: Pike | E4: NEPA RPO | G4: SHOHOLA CREEK | H4: SPRING ROAD | I4: PIERSON BRIDGE, PIKE COUNTY BRIDGE #2 | J4: 21 | K4: 342.3 | L4: N | M4: Steel, I beams | N4: 09 - Rural - Local | O4: L | P4: N | Q4: N | R4: 117 | S4: 2026 | T4: 2026 | U4: BAMS Pick CFB | V4: NEPA_581 | W4: Culvert Replacement (Box Frame | X4: 900000 | Y4: 900000 | Z4: 4.724 | AA4: 5.827 | AB4: 4.448 | AC4: N | AD4: 4.448 | AE4: 9.99 | AF4: 9.99 | AG4: 9.99 | AH4: N | AI4: 9.99
A5: 51720104140101 | B5: =HYPERLINK("https://www.google.com/maps/place/41°22'23.010000000009313""N,75°9'7.4200000000419095""W/data=!3m1!1e3", "30016") -> 30016 | C5: 4 | D5: Pike | E5: NEPA RPO | G5: BLOOMING GROVE CREEK | H5: CHRISTOPHER WAY | I5: Co Br #1 (Blooming Grove Twp) | J5: 53 | K5: 1287.9 | L5: N | M5: P/S, Box beam - adj | N5: 09 - Rural - Local | O5: L | P5: N | Q5: N | R5: 440 | S5: 2026 | T5: 2026 | U5: BAMS Pick CFB | V5: NEPA_581 | W5: Superstructure Rep Rehab | X5: 579555 | Y5: 579555 | Z5: 4.294 | AA5: 4.303 | AB5: 5.748 | AC5: N | AD5: 4.294 | AE5: 9.99 | AF5: 9.99 | AG5: 6.99 | AH5: N | AI5: 6.99
A6: 51720203140005 | B6: =HYPERLINK("https://www.google.com/maps/place/41°12'6.669999999983702""N,74°55'18.599999999976717""W/data=!3m1!1e3", "30018") -> 30018 | C6: 4 | D6: Pike | E6: NEPA RPO | G6: HORNBECKS CREEK | H6: T314 LOG & TWIG RD | I6: T-314, Delaware Twp | J6: 39 | K6: 947.7 | L6: N | M6: P/S, Box beam - adj | N6: 09 - Rural - Local | O6: L | P6: N | Q6: N | R6: 524 | S6: 2026 | T6: 2026 | U6: BAMS Pick CFB | V6: NEPA_581 | W6: Superstructure Rep Rehab | X6: 426465 | Y6: 426465 | Z6: 4.588 | AA6: 4.584 | AB6: 5.639 | AC6: N | AD6: 4.584 | AE6: 9.99 | AF6: 9.99 | AG6: 6.99 | AH6: N | AI6: 6.99
A7: 51720304240105 | B7: =HYPERLINK("https://www.google.com/maps/place/41°21'49.52000000001863""N,74°57'54.27000000001863""W/data=!3m1!1e3", "30026") -> 30026 | C7: 4 | D7: Pike | E7: NEPA RPO | G7: RATTLESNAKE CREEK | H7: SPRING BROOK ROAD | I7: PIKE COUNTY BRIDGE #5 | J7: 33 | K7: 574.2 | L7: N | M7: Concr. encased steel, I beams | N7: 09 - Rural - Local | O7: L | P7: N | Q7: N | R7: 503 | S7: 2036 | T7: 2036 | U7: BAMS Pick CFB | V7: NEPA_581 | W7: Bridge Replacement | X7: 1209524.7 | Y7: 1209524.7 | Z7: 5.61736 | AA7: 4.8908542 | AB7: 4.066 | AC7: N | AD7: 4.066 | AE7: 9.99 | AF7: 9.99 | AG7: 9.99 | AH7: N | AI7: 9.99
A8: 51720403740005 | B8: =HYPERLINK("https://www.google.com/maps/place/41°17'14.309999999997672""N,75°19'24.319999999948777""W/data=!3m1!1e3", "30029") -> 30029 | C8: 4 | D8: Pike | E8: NEPA RPO | G8: SUGAR HILL CREEK | H8: T-374 MTN VIEW RD | I8: T-374 Bridge, Greene Twp | J8: 37 | K8: 899.1 | L8: N | M8: P/S, Box beam - adj | N8: 09 - Rural - Local | O8: L | P8: N | Q8: N | R8: 212 | S8: 2026 | T8: 2026 | U8: BAMS Pick CFB | V8: NEPA_581 | W8: Superstructure Rep Rehab | X8: 404595 | Y8: 404595 | Z8: 4.294 | AA8: 4.302 | AB8: 5.512 | AC8: N | AD8: 4.294 | AE8: 9.99 | AF8: 9.99 | AG8: 6.99 | AH8: N | AI8: 6.99
A9: 51720403660106 | B9: =HYPERLINK("https://www.google.com/maps/place/41°14'52.61999999999534""N,75°19'58.02000000001863""W/data=!3m1!1e3", "30030") -> 30030 | C9: 4 | D9: Pike | E9: NEPA RPO | G9: TAYLOR CREEK | H9: CARLTON ROAD | I9: PIKE COUNTY BRIDGE #6 | J9: 43 | K9: 1040.6 | L9: N | M9: P/S, Box beam - adj | N9: 09 - Rural - Local | O9: L | P9: N | Q9: N | R9: 228 | S9: 2026 | T9: 2026 | U9: BAMS Pick CFB | V9: NEPA_581 | W9: Superstructure Rep Rehab | X9: 468270 | Y9: 468270 | Z9: 2.956 | AA9: 2.921 | AB9: 6.519 | AC9: N | AD9: 2.921 | AE9: 9.99 | AF9: 9.99 | AG9: 7.519 | AH9: N | AI9: 7.519
A10: 51720403660106 | B10: =HYPERLINK("https://www.google.com/maps/place/41°14'52.61999999999534""N,75°19'58.02000000001863""W/data=!3m1!1e3", "30030") -> 30030 | C10: 4 | D10: Pike | E10: NEPA RPO | G10: TAYLOR CREEK | H10: CARLTON ROAD | I10: PIKE COUNTY BRIDGE #6 | J10: 43 | K10: 1040.6 | L10: N | M10: P/S, Box beam - adj | N10: 09 - Rural - Local | O10: L | P10: N | Q10: N | R10: 228 | S10: 2036 | T10: 2036 | U10: BAMS Pick CFB | V10: NEPA_581 | W10: General Preservation | X10: 27969.588 | Y10: 27969.588 | Z10: 8.49375 | AA10: 8.74485 | AB10: 7.114 | AC10: N | AD10: 7.114 | AE10: 8.36875 | AF10: 8.68185 | AG10: 7.569 | AH10: N | AI10: 7.569
A11: 51720403720005 | B11: =HYPERLINK("https://www.google.com/maps/place/41°18'17.40999999997439""N,75°17'1.040000000037253""W/data=!3m1!1e3", "30031") -> 30031 | C11: 4 | D11: Pike | E11: NEPA RPO | G11: BRIDGE CREEK | H11: T-372 SAWMILL ROAD | I11: T-372 Bridge #1, Greene Twp | J11: 71 | K11: 1725.3 | L11: N | M11: P/S, Box beam - adj | N11: 09 - Rural - Local | O11: L | P11: N | Q11: N | R11: 294 | S11: 2026 | T11: 2026 | U11: BAMS Pick CFB | V11: NEPA_581 | W11: Superstructure Rep Rehab | X11: 776385 | Y11: 776385 | Z11: 4.292 | AA11: 4.296 | AB11: 5.508 | AC11: N | AD11: 4.292 | AE11: 9.99 | AF11: 9.99 | AG11: 6.99 | AH11: N | AI11: 6.99
A12: 51720403720010 | B12: =HYPERLINK("https://www.google.com/maps/place/41°17'18.95000000001164""N,75°15'19.300000000046566""W/data=!3m1!1e3", "30032") -> 30032 | C12: 4 | D12: Pike | E12: NEPA RPO | G12: BRIDGE CREEK | H12: T-372 SAWMILL ROAD | I12: T-372 Bridge #2, Greene Twp | J12: 63 | K12: 1549.8 | L12: N | M12: P/S, Box beam - adj | N12: 09 - Rural - Local | O12: L | P12: N | Q12: N | R12: 278 | S12: 2026 | T12: 2026 | U12: BAMS Pick CFB | V12: NEPA_581 | W12: Superstructure Rep Rehab | X12: 697410 | Y12: 697410 | Z12: 2.941 | AA12: 2.927 | AB12: 5.818 | AC12: N | AD12: 2.927 | AE12: 9.99 | AF12: 9.99 | AG12: 6.99 | AH12: N | AI12: 6.99
A13: 51720403780005 | B13: =HYPERLINK("https://www.google.com/maps/place/41°18'54.53000000002794""N,75°17'8.619999999995343""W/data=!3m1!1e3", "30033") -> 30033 | C13: 4 | D13: Pike | E13: NEPA RPO | G13: E BR WALLENPAUPACK CREEK | H13: T-378 CREEK ROAD | I13: T-378 Bridge, Greene Twp | J13: 63 | K13: 1549.8 | L13: N | M13: P/S, Box beam - adj | N13: 09 - Rural - Local | O13: L | P13: N | Q13: N | R13: 278 | S13: 2026 | T13: 2026 | U13: BAMS Pick CFB | V13: NEPA_581 | W13: Superstructure Rep Rehab | X13: 697410 | Y13: 697410 | Z13: 4.29 | AA13: 4.3 | AB13: 5.509 | AC13: N | AD13: 4.29 | AE13: 9.99 | AF13: 9.99 | AG13: 6.99 | AH13: N | AI13: 6.99
A14: 51720403900005 | B14: =HYPERLINK("https://www.google.com/maps/place/41°16'23.880000000004657""N,75°15'10.339999999967404""W/data=!3m1!1e3", "30035") -> 30035 | C14: 4 | D14: Pike | E14: NEPA RPO | G14: MOZETTE CREEK | H14: T-390 MOZETTE RD | I14: T-390 Bridge, Greene Twp | J14: 33 | K14: 801.9 | L14: N | M14: P/S, Box beam - adj | N14: 09 - Rural - Local | O14: L | P14: N | Q14: N | R14: 200 | S14: 2026 | T14: 2026 | U14: BAMS Pick CFB | V14: NEPA_581 | W14: Superstructure Rep Rehab | X14: 360855 | Y14: 360855 | Z14: 3.228 | AA14: 3.018 | AB14: 5.683 | AC14: N | AD14: 3.018 | AE14: 9.99 | AF14: 9.99 | AG14: 6.99 | AH14: N | AI14: 6.99
A15: 51720504380005 | B15: =HYPERLINK("https://www.google.com/maps/place/41°25'11.60999999998603""N,74°59'26.60999999998603""W/data=!3m1!1e3", "30038") -> 30038 | C15: 4 | D15: Pike | E15: NEPA RPO | G15: BALLIARD CREEK | H15: T-438 HERZOG RD | I15: T-438 Bridge, Lackwaxen Twp | J15: 58 | K15: 1426.8 | L15: N | M15: P/S, Box beam - adj | N15: 09 - Rural - Local | O15: L | P15: N | Q15: N | R15: 534 | S15: 2026 | T15: 2026 | U15: BAMS Pick CFB | V15: NEPA_581 | W15: Bridge Replacement | X15: 1569480 | Y15: 1569480 | Z15: 4.243 | AA15: 4.296 | AB15: 2.862 | AC15: N | AD15: 2.862 | AE15: 9.99 | AF15: 9.99 | AG15: 9.99 | AH15: N | AI15: 9.99
A16: 51720504920112 | B16: =HYPERLINK("https://www.google.com/maps/place/41°27'48.15000000002328""N,75°3'0.8100000000558794""W/data=!3m1!1e3", "30040") -> 30040 | C16: 4 | D16: Pike | E16: NEPA RPO | G16: WEST FALLS CREEK | H16: T-492 CHURCH RD | I16: Co Br #12 (Lackawaxen Twp) | J16: 27 | K16: 656.1 | L16: N | M16: P/S, Box beam - adj | N16: 09 - Rural - Local | O16: L | P16: N | Q16: N | R16: 362 | S16: 2026 | T16: 2026 | U16: BAMS Pick CFB | V16: NEPA_581 | W16: Culvert Replacement (Box Frame | X16: 1115370 | Y16: 1115370 | Z16: 4.31 | AA16: 4.304 | AB16: 3.302 | AC16: N | AD16: 3.302 | AE16: 9.99 | AF16: 9.99 | AG16: 9.99 | AH16: N | AI16: 9.99
A17: 51720504950005 | B17: =HYPERLINK("https://www.google.com/maps/place/41°27'52.25""N,75°7'36.36999999999534""W/data=!3m1!1e3", "30041") -> 30041 | C17: 4 | D17: Pike | E17: NEPA RPO | G17: DECKER CREEK | H17: T406 HENDERSHOT RD | I17: T-406 Bridge, Lackawaxen Twp | J17: 33 | K17: 801.9 | L17: N | M17: P/S, Box beam - adj | N17: 09 - Rural - Local | O17: L | P17: N | Q17: N | R17: 400 | S17: 2026 | T17: 2026 | U17: BAMS Pick CFB | V17: NEPA_581 | W17: Bridge Replacement | X17: 900000 | Y17: 900000 | Z17: 3.55 | AA17: 3.56 | AB17: 3.57 | AC17: N | AD17: 3.55 | AE17: 9.99 | AF17: 9.99 | AG17: 9.99 | AH17: N | AI17: 9.99
A18: 51720603010116 | B18: =HYPERLINK("https://www.google.com/maps/place/41°5'29.64000000001397""N,75°0'14.25""W/data=!3m1!1e3", "30048") -> 30048 | C18: 4 | D18: Pike | E18: NEPA RPO | G18: LITTLE BUSHKILL CREEK | H18: T301(CO.BR.16) | I18: BUSHKILL,-PETERS MILL | J18: 47 | K18: 1212.6 | L18: N | M18: Concr. encased steel, I beams | N18: 09 - Rural - Local | O18: L | P18: N | Q18: N | R18: 603 | S18: 2026 | T18: 2026 | U18: BAMS Pick CFB | V18: NEPA_581 | W18: Bridge Replacement | X18: 1333860 | Y18: 1333860 | Z18: 5.117 | AA18: 4.11 | AB18: 4.415 | AC18: N | AD18: 4.11 | AE18: 9.99 | AF18: 9.99 | AG18: 9.99 | AH18: N | AI18: 9.99
A19: 51720603020119 | B19: =HYPERLINK("https://www.google.com/maps/place/41°5'18.510000000009313""N,75°2'16.650000000023283""W/data=!3m1!1e3", "30049") -> 30049 | C19: 4 | D19: Pike | E19: NEPA RPO | G19: BUSHKILL CREEK | H19: T-301 WINONA FALLS | I19: Co Br #19 (Lehman Twp) | J19: 122 | K19: 3403.8 | L19: N | M19: P/S, Box beam - adj | N19: 09 - Rural - Local | O19: L | P19: N | Q19: N | R19: 2183 | S19: 2026 | T19: 2026 | U19: BAMS Pick CFB | V19: NEPA_581 | W19: Leaking Deck Joint Replacement | X19: 17019 | Y19: 17019 | Z19: 4.288 | AA19: 4.287 | AB19: 6.435 | AC19: N | AD19: 4.287 | AE19: 4.288 | AF19: 4.787 | AG19: 6.685 | AH19: N | AI19: 4.288
A20: 51720603020119 | B20: =HYPERLINK("https://www.google.com/maps/place/41°5'18.510000000009313""N,75°2'16.650000000023283""W/data=!3m1!1e3", "30049") -> 30049 | C20: 4 | D20: Pike | E20: NEPA RPO | G20: BUSHKILL CREEK | H20: T-301 WINONA FALLS | I20: Co Br #19 (Lehman Twp) | J20: 122 | K20: 3403.8 | L20: N | M20: P/S, Box beam - adj | N20: 09 - Rural - Local | O20: L | P20: N | Q20: N | R20: 2183 | S20: 2027 | T20: 2027 | U20: BAMS Pick CFB | V20: NEPA_581 | W20: Superstructure Rep Rehab | X20: 1577661.3 | Y20: 1577661.3 | Z20: 4.288 | AA20: 4.787 | AB20: 6.685 | AC20: N | AD20: 4.288 | AE20: 9.99 | AF20: 9.99 | AG20: 7.585 | AH20: N | AI20: 7.585
A21: 51720603050118 | B21: =HYPERLINK("https://www.google.com/maps/place/41°5'51.90999999997439""N,75°0'13.849999999976717""W/data=!3m1!1e3", "30050") -> 30050 | C21: 4 | D21: Pike | E21: NEPA RPO | G21: LITTLE BUSHKILL CREEK | H21: T-305 E SUGAR MTN | I21: Co Br #18 (Lehman Twp) | J21: 75 | K21: 1822.5 | L21: N | M21: P/S, Box beam - adj | N21: 09 - Rural - Local | O21: L | P21: N | Q21: N | R21: 739 | S21: 2027 | T21: 2027 | U21: BAMS Pick CFB | V21: NEPA_581 | W21: Bridge Replacement | X21: 2064892.5 | Y21: 2064892.5 | Z21: 4.287 | AA21: 4.3 | AB21: 4.727 | AC21: N | AD21: 4.287 | AE21: 9.99 | AF21: 9.99 | AG21: 9.99 | AH21: N | AI21: 9.99
A22: 51720803510005 | B22: =HYPERLINK("https://www.google.com/maps/place/41°20'58.40000000002328""N,75°13'44.96999999997206""W/data=!3m1!1e3", "30059") -> 30059 | C22: 4 | D22: Pike | E22: NEPA RPO | G22: KLEINHANS CREEK | H22: T351 OLD GREENTOWN | I22: T-351 Bridge, Palmyra Twp | J22: 29 | K22: 696 | L22: N | M22: P/S, Box beam - adj | N22: 09 - Rural - Local | O22: L | P22: N | Q22: N | R22: 280 | S22: 2026 | T22: 2026 | U22: BAMS Pick CFB | V22: NEPA_581 | W22: Culvert Replacement (Box Frame | X22: 1183200 | Y22: 1183200 | Z22: 4.286 | AA22: 4.313 | AB22: 7.063 | AC22: N | AD22: 4.286 | AE22: 9.99 | AF22: 9.99 | AG22: 9.99 | AH22: N | AI22: 9.99
A23: 51721004400010 | B23: =HYPERLINK("https://www.google.com/maps/place/41°24'27.229999999981374""N,74°58'50.71999999997206""W/data=!3m1!1e3", "30066") -> 30066 | C23: 4 | D23: Pike | E23: NEPA RPO | G23: TRIB. TO SHOHOLA CREEK | H23: T440 (TWP. BR. 2) | I23: T-440 Bridge #2, Shohola Twp | J23: 40 | K23: 972 | L23: N | M23: P/S, Box beam - adj | N23: 09 - Rural - Local | O23: L | P23: N | Q23: N | R23: 220 | S23: 2026 | T23: 2026 | U23: BAMS Pick CFB | V23: NEPA_581 | W23: Superstructure Rep Rehab | X23: 437400 | Y23: 437400 | Z23: 4.587 | AA23: 4.581 | AB23: 5.512 | AC23: N | AD23: 4.581 | AE23: 9.99 | AF23: 9.99 | AG23: 6.99 | AH23: N | AI23: 6.99
A24: 51721004400124 | B24: =HYPERLINK("https://www.google.com/maps/place/41°25'9.309999999997672""N,74°58'52.839999999967404""W/data=!3m1!1e3", "30067") -> 30067 | C24: 4 | D24: Pike | E24: NEPA RPO | G24: BALLIARD CREEK | H24: SHOHOLA FALLS ROAD | I24: PIKE COUNTY BRIDGE #24 | J24: 36 | K24: 640.8 | L24: N | M24: Concrete(in place), Arch deck - closed | N24: 09 - Rural - Local | O24: L | P24: N | Q24: N | R24: 179 | S24: 2031 | T24: 2031 | U24: BAMS Pick CFB | V24: NEPA_581 | W24: Bridge Replacement | X24: 1043346.7 | Y24: 1043346.7 | Z24: 8.917 | AA24: 4.265 | AB24: 4.303 | AC24: N | AD24: 4.265 | AE24: 9.99 | AF24: 9.99 | AG24: 9.99 | AH24: N | AI24: 9.99
A25: 51740203930122 | B25: =HYPERLINK("https://www.google.com/maps/place/41°19'37.54999999998836""N,74°47'49.56000000005588""W/data=!3m1!1e3", "30069") -> 30069 | C25: 4 | D25: Pike | E25: NEPA RPO | G25: VANDERMARK CREEK | H25: BROAD STREET | I25: PIKE COUNTY BRIDGE #22 | J25: 24 | K25: 580.8 | L25: N | M25: Masonry, Arch deck - closed | N25: 09 - Rural - Local | O25: L | P25: N | Q25: N | R25: 170 | S25: 2029 | T25: 2029 | U25: BAMS Pick CFB | V25: NEPA_581 | W25: Culvert Replacement (Box Frame | X25: 1078914.9 | Y25: 1078914.9 | Z25: 9.2 | AA25: 4.537 | AB25: 5.179 | AC25: N | AD25: 4.537 | AE25: 9.99 | AF25: 9.99 | AG25: 9.99 | AH25: N | AI25: 9.99
A26: 51740204250120 | B26: =HYPERLINK("https://www.google.com/maps/place/41°19'0.47999999998137355""N,74°47'57.10999999998603""W/data=!3m1!1e3", "30070") -> 30070 | C26: 4 | D26: Pike | E26: NEPA RPO | G26: SAWKILL CREEK | H26: T425(CO.BR.NO.20) | I26: Co Br #20 (Milford Boro) | J26: 53 | K26: 1287.9 | L26: N | M26: P/S, Box beam - adj | N26: 09 - Rural - Local | O26: L | P26: N | Q26: N | R26: 254 | S26: 2027 | T26: 2027 | U26: BAMS Pick CFB | V26: NEPA_581 | W26: Bridge Replacement | X26: 1459190.7 | Y26: 1459190.7 | Z26: 4.304 | AA26: 4.329 | AB26: 4.225 | AC26: N | AD26: 4.225 | AE26: 9.99 | AF26: 9.99 | AG26: 9.99 | AH26: N | AI26: 9.99

Sheet Unfunded Treatment - Final List
A1: BridgeID | B1: BRKey (Hyperlink) | C1: District | D1: County | E1: MPO/RPO | F1: City/Town/Place | G1: Feature intersected | H1: Facility Carried | I1: Location/StructureName | J1: Bridge Length | K1: Deck Area | L1: Large Bridge | M1: Structure Type | N1: Functional Class | O1: BPN | P1: NHS | Q1: Interstate | R1: Risk Score | S1: Bridge Funding | Y1: Analysis Year | Z1: GCR DECK | AA1: GCR SUP | AB1: GCR SUB | AC1: GCR CULV | AD1: DECK DUR | AE1: SUP DUR | AF1: SUB DUR | AG1: CULV DUR | AH1: Unfunded Treatment | AI1: Cost | AK1: Total Unfunded Amount:
S2: NHPP | T2: STP | U2: BOF | V2: BRIP | W2: STATE | X2: N/A | AK2: ==SUM(AI:AI)

Sheet Unfunded Treatment - Time
A1: BridgeID | B1: BRKey (Hyperlink) | C1: District | D1: County | E1: MPO/RPO | F1: City/Town/Place | G1: Feature intersected | H1: Facility Carried | I1: Location/StructureName | J1: Bridge Length | K1: Deck Area | L1: Large Bridge | M1: Structure Type | N1: Functional Class | O1: BPN | P1: NHS | Q1: Interstate | R1: Risk Score | S1: Bridge Funding | Y1: Analysis Year | Z1: GCR DECK | AA1: GCR SUP | AB1: GCR SUB | AC1: GCR CULV | AD1: DECK DUR | AE1: SUP DUR | AF1: SUB DUR | AG1: CULV DUR | AH1: Unfunded Treatment | AI1: Cost
S2: NHPP | T2: STP | U2: BOF | V2: BRIP | W2: STATE | X2: N/A

Sheet Bridge Work Summary
C2: Budget Analysis
C3: 2026 | D3: 2027 | E3: 2028 | F3: 2029 | G3: 2030 | H3: 2031 | I3: 2032 | J3: 2033 | K3: 2034 | L3: 2035 | M3: 2036 | N3: Total Remaining Budget(all years)
A4: Remaining Budget | C4: 0 | D4: 0 | E4: 0 | F4: 0 | G4: 0 | H4: 0 | I4: 0 | J4: 0 | K4: 0 | L4: 0 | M4: 0 | N4: =SUM(C4:M4) -> 0 | O4: =N4/764577265.00000000000000000000 -> 0 | P4: Percentage of Total Budget that was Unspent
A5: Percent Budget Spent BAMS | C5: 0 | D5: 0 | E5: 0 | F5: 0 | G5: 0 | H5: 0 | I5: 0 | J5: 0 | K5: 0 | L5: 0 | M5: 0
A6: Percent Budget Spent Committed | C6: 0 | D6: 0 | E6: 0 | F6: 0 | G6: 0 | H6: 0 | I6: 0 | J6: 0 | K6: 0 | L6: 0 | M6: 0
A7: Percent Budget Spent MPMS | C7: 0 | D7: 0 | E7: 0 | F7: 0 | G7: 0 | H7: 0 | I7: 0 | J7: 0 | K7: 0 | L7: 0 | M7: 0
A8: Percent Budget Spent SAP | C8: 0 | D8: 0 | E8: 0 | F8: 0 | G8: 0 | H8: 0 | I8: 0 | J8: 0 | K8: 0 | L8: 0 | M8: 0
A9: Percent Budget Spent Project Builder | C9: 0 | D9: 0 | E9: 0 | F9: 0 | G9: 0 | H9: 0 | I9: 0 | J9: 0 | K9: 0 | L9: 0 | M9: 0
A11: Committed Work Type | C11: Cost of Committed Work
C12: 2026 | D12: 2027 | E12: 2028 | F12: 2029 | G12: 2030 | H12: 2031 | I12: 2032 | J12: 2033 | K12: 2034 | L12: 2035 | M12: 2036
A13: Committed Total | C13: 0 | D13: 0 | E13: 0 | F13: 0 | G13: 0 | H13: 0 | I13: 0 | J13: 0 | K13: 0 | L13: 0 | M13: 0
A15: MPMS Work Type | C15: Cost of MPMS Work
C16: 2026 | D16: 2027 | E16: 2028 | F16: 2029 | G16: 2030 | H16: 2031 | I16: 2032 | J16: 2033 | K16: 2034 | L16: 2035 | M16: 2036
A17: Committed Total | C17: 0 | D17: 0 | E17: 0 | F17: 0 | G17: 0 | H17: 0 | I17: 0 | J17: 0 | K17: 0 | L17: 0 | M17: 0
A19: SAP Work Type | C19: Cost of SAP Work
C20: 2026 | D20: 2027 | E20: 2028 | F20: 2029 | G20: 2030 | H20: 2031 | I20: 2032 | J20: 2033 | K20: 2034 | L20: 2035 | M20: 2036
A21: SAP Total | C21: - | D21: - | E21: - | F21: - | G21: - | H21: - | I21: - | J21: - | K21: - | L21: - | M21: -
A23: Project Builder Work Type | C23: Cost of Project Builder Work
C24: 2026 | D24: 2027 | E24: 2028 | F24: 2029 | G24: 2030 | H24: 2031 | I24: 2032 | J24: 2033 | K24: 2034 | L24: 2035 | M24: 2036
A25: Project Builder Total | C25: - | D25: - | E25: - | F25: - | G25: - | H25: - | I25: - | J25: - | K25: - | L25: - | M25: -
A27: BAMS Culvert Work Type | C27: Cost of BAMS Culvert Work
C28: 2026 | D28: 2027 | E28: 2028 | F28: 2029 | G28: 2030 | H28: 2031 | I28: 2032 | J28: 2033 | K28: 2034 | L28: 2035 | M28: 2036
A29: Culvert Rehab (Other) | C29: 0 | D29: 0 | E29: 0 | F29: 0 | G29: 0 | H29: 0 | I29: 0 | J29: 0 | K29: 0 | L29: 0 | M29: 0
A30: Culvert Replacement (Box Frame | C30: 3198570 | D30: 0 | E30: 0 | F30: 1078914.9 | G30: 0 | H30: 0 | I30: 0 | J30: 0 | K30: 0 | L30: 0 | M30: 0
A31: Culvert Replacement (Other) | C31: 0 | D31: 0 | E31: 0 | F31: 0 | G31: 0 | H31: 0 | I31: 0 | J31: 0 | K31: 0 | L31: 0 | M31: 0
A32: Culvert Replacement (Pipe) | C32: 0 | D32: 0 | E32: 0 | F32: 0 | G32: 0 | H32: 0 | I32: 0 | J32: 0 | K32: 0 | L32: 0 | M32: 0
A33: Culvert Total | C33: 3198570 | D33: 0 | E33: 0 | F33: 1078914.9 | G33: 0 | H33: 0 | I33: 0 | J33: 0 | K33: 0 | L33: 0 | M33: 0
A35: BAMS Bridge Work Type | C35: Cost of BAMS Bridge Work
C36: 2026 | D36: 2027 | E36: 2028 | F36: 2029 | G36: 2030 | H36: 2031 | I36: 2032 | J36: 2033 | K36: 2034 | L36: 2035 | M36: 2036
A37: Bituminous Overlay | C37: 0 | D37: 0 | E37: 0 | F37: 0 | G37: 0 | H37: 0 | I37: 0 | J37: 0 | K37: 0 | L37: 0 | M37: 0
A38: Bridge Replacement | C38: 3803340 | D38: 3524083.2 | E38: 0 | F38: 0 | G38: 0 | H38: 1043346.7 | I38: 0 | J38: 0 | K38: 0 | L38: 0 | M38: 1209524.7
A39: Deck Replacement | C39: 0 | D39: 0 | E39: 0 | F39: 0 | G39: 0 | H39: 0 | I39: 0 | J39: 0 | K39: 0 | L39: 0 | M39: 0
A40: Epoxy Joint Glands Coatings | C40: 0 | D40: 0 | E40: 0 | F40: 0 | G40: 0 | H40: 0 | I40: 0 | J40: 0 | K40: 0 | L40: 0 | M40: 0
A41: General Preservation | C41: 0 | D41: 0 | E41: 0 | F41: 0 | G41: 0 | H41: 0 | I41: 0 | J41: 0 | K41: 0 | L41: 0 | M41: 27969.59
A42: Leaking Deck Joint Replacement | C42: 17019 | D42: 0 | E42: 0 | F42: 0 | G42: 0 | H42: 0 | I42: 0 | J42: 0 | K42: 0 | L42: 0 | M42: 0
A43: Maintenance | C43: 0 | D43: 0 | E43: 0 | F43: 0 | G43: 0 | H43: 0 | I43: 0 | J43: 0 | K43: 0 | L43: 0 | M43: 0
A44: Painting (Full) | C44: 0 | D44: 0 | E44: 0 | F44: 0 | G44: 0 | H44: 0 | I44: 0 | J44: 0 | K44: 0 | L44: 0 | M44: 0
A45: Painting (Joint Spot Zone) | C45: 0 | D45: 0 | E45: 0 | F45: 0 | G45: 0 | H45: 0 | I45: 0 | J45: 0 | K45: 0 | L45: 0 | M45: 0
A46: Preservation | C46: 0 | D46: 0 | E46: 0 | F46: 0 | G46: 0 | H46: 0 | I46: 0 | J46: 0 | K46: 0 | L46: 0 | M46: 0
A47: Rehabilitation | C47: 0 | D47: 0 | E47: 0 | F47: 0 | G47: 0 | H47: 0 | I47: 0 | J47: 0 | K47: 0 | L47: 0 | M47: 0
A48: Removal | C48: 0 | D48: 0 | E48: 0 | F48: 0 | G48: 0 | H48: 0 | I48: 0 | J48: 0 | K48: 0 | L48: 0 | M48: 0
... A54: Bridge Total | C54: 8668704 | D54: 5101744.5 | E54: 0 | F54: 0 | G54: 0 | H54: 1043346.7 | I54: 0 | J54: 0 | K54: 0 | L54: 0 | M54: 1237494.3
A56: Work Type Totals
C57: 2026 | D57: 2027 | E57: 2028 | F57: 2029 | G57: 2030 | H57: 2031 | I57: 2032 | J57: 2033 | K57: 2034 | L57: 2035 | M57: 2036 | N57: Total (all years)
A58: Maintenance | N58: =Sum(C58:M58) -> 0 | O58: =(N58/N66) -> 0 | P58: Percentage Spent on MAINTENANCE
A59: Preservation | C59: 17019 | D59: 0 | E59: 0 | F59: 0 | G59: 0 | H59: 0 | I59: 0 | J59: 0 | K59: 0 | L59: 0 | M59: 27969.59 | N59: =Sum(C59:M59) -> 44988.59 | O59: =(N59/N66) -> 0.0022130498 | P59: Percentage Spent on PRESERVATION
A60: Rehabilitation | C60: 4848345 | D60: 1577661.3 | E60: 0 | F60: 0 | G60: 0 | H60: 0 | I60: 0 | J60: 0 | K60: 0 | L60: 0 | M60: 0 | N60: =Sum(C60:M60) -> 6426006.3 | O60: =(N60/N66) -> 0.31610397 | P60: Percentage Spent on REHABILITATION
A61: Replacement | C61: 7001910 | D61: 3524083.2 | E61: 0 | F61: 1078914.9 | G61: 0 | H61: 1043346.7 | I61: 0 | J61: 0 | K61: 0 | L61: 0 | M61: 1209524.7 | N61: =Sum(C61:M61) -> 13857780 | O61: =(N61/N66) -> 0.68168298 | P61: Percentage Spent on REPLACEMENT
A62: Capacity Adding | N62: =Sum(C62:M62) -> 0 | O62: =(N62/N66) -> 0 | P62: Percentage Spent on CAPACITY ADDING
A63: Other | N63: =Sum(C63:M63) -> 0 | O63: =(N63/N66) -> 0 | P63: Percentage Spent on OTHER
A64: Bundled | N64: =Sum(C64:M64) -> 0 | O64: =(N64/N66) -> 0 | P64: Percentage Spent on BUNDLED
A66: Total Spent | C66: =Sum(C58:C65) -> 11867274 | D66: =Sum(D58:D65) -> 5101744.5 | E66: =Sum(E58:E65) -> 0 | F66: =Sum(F58:F65) -> 1078914.9 | G66: =Sum(G58:G65) -> 0 | H66: =Sum(H58:H65) -> 1043346.7 | I66: =Sum(I58:I65) -> 0 | J66: =Sum(J58:J65) -> 0 | ... M66: =Sum(M58:M65) -> 1237494.3 | N66: =Sum(C66:M66) -> 20328774
A68: Total Bridge Care Budget | C68: 11867274 | D68: 5101744.5 | E68: 0 | F68: 1078914.9 | G68: 0 | H68: 1043346.7 | I68: 0 | J68: 0 | K68: 0 | L68: 0 | M68: 1237494.3 | N68: =Sum(C68:M68) -> 20328774
A70: Work Outside Scope/Jurisdiction
C71: 2026 | D71: 2027 | E71: 2028 | F71: 2029 | G71: 2030 | H71: 2031 | I71: 2032 | J71: 2033 | K71: 2034 | L71: 2035 | M71: 2036
C72: 0 | D72: 0 | E72: 0 | F72: 0 | G72: 0 | H72: 0 | I72: 0 | J72: 0 | K72: 0 | L72: 0 | M72: 0 | N72: =Sum(C72:M72) -> 0
A74: BPN | C74: Total Cost Per BPN
C75: 2026 | D75: 2027 | E75: 2028 | F75: 2029 | G75: 2030 | H75: 2031 | I75: 2032 | J75: 2033 | K75: 2034 | L75: 2035 | M75: 2036
A76: BPN 1 | C76: 0 | D76: 0 | E76: 0 | F76: 0 | G76: 0 | H76: 0 | I76: 0 | J76: 0 | K76: 0 | L76: 0 | M76: 0
A77: BPN 2 | C77: 0 | D77: 0 | E77: 0 | F77: 0 | G77: 0 | H77: 0 | I77: 0 | J77: 0 | K77: 0 | L77: 0 | M77: 0
A78: BPN 3 | C78: 0 | D78: 0 | E78: 0 | F78: 0 | G78: 0 | H78: 0 | I78: 0 | J78: 0 | K78: 0 | L78: 0 | M78: 0
A79: BPN 4 | C79: 0 | D79: 0 | E79: 0 | F79: 0 | G79: 0 | H79: 0 | I79: 0 | J79: 0 | K79: 0 | L79: 0 | M79: 0
A80: BPN L | C80: 11867274 | D80: 5101744.5 | E80: 0 | F80: 1078914.9 | G80: 0 | H80: 1043346.7 | I80: 0 | J80: 0 | K80: 0 | L80: 0 | M80: 1237494.3
A81: BPN Other (BPN D, BPN H,BPN N, BPN T) | C81: 0 | D81: 0 | E81: 0 | F81: 0 | G81: 0 | H81: 0 | I81: 0 | J81: 0 | K81: 0 | L81: 0 | M81: 0
A82: Total BPN Cost | C82: 11867274 | D82: 5101744.5 | E82: 0 | F82: 1078914.9 | G82: 0 | H82: 1043346.7 | I82: 0 | J82: 0 | K82: 0 | L82: 0 | M82: 1237494.3
A86: MPMS Work Type | C86: Number of MPMS Projects Worked On
C87: 2026 | D87: 2027 | E87: 2028 | F87: 2029 | G87: 2030 | H87: 2031 | I87: 2032 | J87: 2033 | K87: 2034 | L87: 2035 | M87: 2036
A88: Total | C88: 0 | D88: 0 | E88: 0 | F88: 0 | G88: 0 | H88: 0 | I88: 0 | J88: 0 | K88: 0 | L88: 0 | M88: 0
A90: Culvert Work Type | C90: Number of Culverts Worked on
C91: 2026 | D91: 2027 | E91: 2028 | F91: 2029 | G91: 2030 | H91: 2031 | I91: 2032 | J91: 2033 | K91: 2034 | L91: 2035 | M91: 2036
A92: No Treatment | C92: 0 | D92: 0 | E92: 0 | F92: 0 | G92: 0 | H92: 0 | I92: 0 | J92: 0 | K92: 0 | L92: 0 | M92: 0
A93: Culvert Rehab (Other) | C93: 0 | D93: 0 | E93: 0 | F93: 0 | G93: 0 | H93: 0 | I93: 0 | J93: 0 | K93: 0 | L93: 0 | M93: 0
A94: Culvert Replacement (Box Frame | C94: 3 | D94: 0 | E94: 0 | F94: 1 | G94: 0 | H94: 0 | I94: 0 | J94: 0 | K94: 0 | L94: 0 | M94: 0
A95: Culvert Replacement (Other) | C95: 0 | D95: 0 | E95: 0 | F95: 0 | G95: 0 | H95: 0 | I95: 0 | J95: 0 | K95: 0 | L95: 0 | M95: 0
A96: Culvert Replacement (Pipe) | C96: 0 | D96: 0 | E96: 0 | F96: 0 | G96: 0 | H96: 0 | I96: 0 | J96: 0 | K96: 0 | L96: 0 | M96: 0
A97: Total | C97: 3 | D97: 0 | E97: 0 | F97: 1 | G97: 0 | H97: 0 | I97: 0 | J97: 0 | K97: 0 | L97: 0 | M97: 0
A99: Bridge Work Type | C99: Number of Bridges Worked on
C100: 2026 | D100: 2027 | E100: 2028 | F100: 2029 | G100: 2030 | H100: 2031 | I100: 2032 | J100: 2033 | K100: 2034 | L100: 2035 | M100: 2036
A101: No Treatment | C101: 5 | D101: 18 | E101: 21 | F101: 20 | G101: 21 | H101: 20 | I101: 21 | J101: 21 | K101: 21 | L101: 21 | M101: 19
A102: Bituminous Overlay | C102: 0 | D102: 0 | E102: 0 | F102: 0 | G102: 0 | H102: 0 | I102: 0 | J102: 0 | K102: 0 | L102: 0 | M102: 0
A103: Bridge Replacement | C103: 3 | D103: 2 | E103: 0 | F103: 0 | G103: 0 | H103: 1 | I103: 0 | J103: 0 | K103: 0 | L103: 0 | M103: 1
A104: Deck Replacement | C104: 0 | D104: 0 | E104: 0 | F104: 0 | G104: 0 | H104: 0 | I104: 0 | J104: 0 | K104: 0 | L104: 0 | M104: 0
A105: Epoxy Joint Glands Coatings | C105: 0 | D105: 0 | E105: 0 | F105: 0 | G105: 0 | H105: 0 | I105: 0 | J105: 0 | K105: 0 | L105: 0 | M105: 0
A106: General Preservation | C106: 0 | D106: 0 | E106: 0 | F106: 0 | G106: 0 | H106: 0 | I106: 0 | J106: 0 | K106: 0 | L106: 0 | M106: 1
A107: Leaking Deck Joint Replacement | C107: 1 | D107: 0 | E107: 0 | F107: 0 | G107: 0 | H107: 0 | I107: 0 | J107: 0 | K107: 0 | L107: 0 | M107: 0
A108: Maintenance | C108: 0 | D108: 0 | E108: 0 | F108: 0 | G108: 0 | H108: 0 | I108: 0 | J108: 0 | K108: 0 | L108: 0 | M108: 0
A109: Painting (Full) | C109: 0 | D109: 0 | E109: 0 | F109: 0 | G109: 0 | H109: 0 | I109: 0 | J109: 0 | K109: 0 | L109: 0 | M109: 0
A110: Painting (Joint Spot Zone) | C110: 0 | D110: 0 | E110: 0 | F110: 0 | G110: 0 | H110: 0 | I110: 0 | J110: 0 | K110: 0 | L110: 0 | M110: 0
A111: Preservation | C111: 0 | D111: 0 | E111: 0 | F111: 0 | G111: 0 | H111: 0 | I111: 0 | J111: 0 | K111: 0 | L111: 0 | M111: 0
A112: Rehabilitation | C112: 0 | D112: 0 | E112: 0 | F112: 0 | G112: 0 | H112: 0 | I112: 0 | J112: 0 | K112: 0 | L112: 0 | M112: 0
... A119: Total | C119: 13 | D119: 3 | E119: 0 | F119: 0 | G119: 0 | H119: 1 | I119: 0 | J119: 0 | K119: 0 | L119: 0 | M119: 2
A121: Bridge and Culvert Work Types | C121: Number of Bridges and Culverts Worked on
C122: 2026 | D122: 2027 | E122: 2028 | F122: 2029 | G122: 2030 | H122: 2031 | I122: 2032 | J122: 2033 | K122: 2034 | L122: 2035 | M122: 2036
A123: No Treatment | C123: 5 | D123: 18 | E123: 21 | F123: 20 | G123: 21 | H123: 20 | I123: 21 | J123: 21 | K123: 21 | L123: 21 | M123: 19
A124: Bituminous Overlay | C124: 0 | D124: 0 | E124: 0 | F124: 0 | G124: 0 | H124: 0 | I124: 0 | J124: 0 | K124: 0 | L124: 0 | M124: 0
A125: Bridge Replacement | C125: 3 | D125: 2 | E125: 0 | F125: 0 | G125: 0 | H125: 1 | I125: 0 | J125: 0 | K125: 0 | L125: 0 | M125: 1
A126: Culvert Rehab (Other) | C126: 0 | D126: 0 | E126: 0 | F126: 0 | G126: 0 | H126: 0 | I126: 0 | J126: 0 | K126: 0 | L126: 0 | M126: 0
A127: Culvert Replacement (Box Frame | C127: 3 | D127: 0 | E127: 0 | F127: 1 | G127: 0 | H127: 0 | I127: 0 | J127: 0 | K127: 0 | L127: 0 | M127: 0
A128: Culvert Replacement (Other) | C128: 0 | D128: 0 | E128: 0 | F128: 0 | G128: 0 | H128: 0 | I128: 0 | J128: 0 | K128: 0 | L128: 0 | M128: 0
A129: Culvert Replacement (Pipe) | C129: 0 | D129: 0 | E129: 0 | F129: 0 | G129: 0 | H129: 0 | I129: 0 | J129: 0 | K129: 0 | L129: 0 | M129: 0
...

Sheet Bridge Work Summary By Budget
A2: WAYNE_BRIP
C5: Budget Analysis
C6: 2026 | D6: 2027 | E6: 2028 | F6: 2029 | G6: 2030 | H6: 2031 | I6: 2032 | J6: 2033 | K6: 2034 | L6: 2035 | M6: 2036
A7: Remaining Budget | C7: 0 | D7: 0 | E7: 0 | F7: 0 | G7: 0 | H7: 0 | I7: 0 | J7: 0 | K7: 0 | L7: 0 | M7: 0
A8: Percent Budget Spent BAMS | C8: 0 | D8: 0 | E8: 0 | F8: 0 | G8: 0 | H8: 0 | I8: 0 | J8: 0 | K8: 0 | L8: 0 | M8: 0
A9: Percent Budget Spent Committed | C9: 0 | D9: 0 | E9: 0 | F9: 0 | G9: 0 | H9: 0 | I9: 0 | J9: 0 | K9: 0 | L9: 0 | M9: 0
A10: Percent Budget Spent MPMS | C10: 0 | D10: 0 | E10: 0 | F10: 0 | G10: 0 | H10: 0 | I10: 0 | J10: 0 | K10: 0 | L10: 0 | M10: 0
A11: Percent Budget Spent SAP | C11: 0 | D11: 0 | E11: 0 | F11: 0 | G11: 0 | H11: 0 | I11: 0 | J11: 0 | K11: 0 | L11: 0 | M11: 0
A12: Percent Budget Spent Project Builder | C12: 0 | D12: 0 | E12: 0 | F12: 0 | G12: 0 | H12: 0 | I12: 0 | J12: 0 | K12: 0 | L12: 0 | M12: 0
A16: Work Type Totals
C17: 2026 | D17: 2027 | E17: 2028 | F17: 2029 | G17: 2030 | H17: 2031 | I17: 2032 | J17: 2033 | K17: 2034 | L17: 2035 | M17: 2036 | N17: Total (all years)
A18: Maintenance | C18: 0 | D18: 0 | E18: 0 | F18: 0 | G18: 0 | H18: 0 | I18: 0 | J18: 0 | K18: 0 | L18: 0 | M18: 0 | N18: =Sum(C18:M18) -> 0 | O18: =(N18/N25) -> #DIV/0! | P18: Percentage Spent on MAINTENANCE
A19: Preservation | C19: 0 | D19: 0 | E19: 0 | F19: 0 | G19: 0 | H19: 0 | I19: 0 | J19: 0 | K19: 0 | L19: 0 | M19: 0 | N19: =Sum(C19:M19) -> 0 | O19: =(N19/N25) -> #DIV/0! | P19: Percentage Spent on PRESERVATION
A20: Rehabilitation | C20: 0 | D20: 0 | E20: 0 | F20: 0 | G20: 0 | H20: 0 | I20: 0 | J20: 0 | K20: 0 | L20: 0 | M20: 0 | N20: =Sum(C20:M20) -> 0 | O20: =(N20/N25) -> #DIV/0! | P20: Percentage Spent on REHABILITATION
A21: Replacement | C21: 0 | D21: 0 | E21: 0 | F21: 0 | G21: 0 | H21: 0 | I21: 0 | J21: 0 | K21: 0 | L21: 0 | M21: 0 | N21: =Sum(C21:M21) -> 0 | O21: =(N21/N25) -> #DIV/0! | P21: Percentage Spent on REPLACEMENT
A22: Capacity Adding | C22: 0 | D22: 0 | E22: 0 | F22: 0 | G22: 0 | H22: 0 | I22: 0 | J22: 0 | K22: 0 | L22: 0 | M22: 0 | N22: =Sum(C22:M22) -> 0 | O22: =(N22/N25) -> #DIV/0! | P22: Percentage Spent on CAPACITY ADDING
A23: Other | C23: 0 | D23: 0 | E23: 0 | F23: 0 | G23: 0 | H23: 0 | I23: 0 | J23: 0 | K23: 0 | L23: 0 | M23: 0 | N23: =Sum(C23:M23) -> 0 | O23: =(N23/N25) -> #DIV/0! | P23: Percentage Spent on OTHER
A24: Bundled | C24: 0 | D24: 0 | E24: 0 | F24: 0 | G24: 0 | H24: 0 | I24: 0 | J24: 0 | K24: 0 | L24: 0 | M24: 0 | N24: =Sum(C24:M24) -> 0 | O24: =(N24/N25) -> #DIV/0! | P24: Percentage Spent on BUNDLED
A25: Total Spent | N25: =Sum(C25:M25) -> 0
A27: Total Bridge Care Budget | C27: 0 | D27: 0 | E27: 0 | F27: 0 | G27: 0 | H27: 0 | I27: 0 | J27: 0 | K27: 0 | L27: 0 | M27: 0 | N27: =Sum(C27:M27) -> 0
A29: Work Outside Scope/Jurisdiction
C30: 2026 | D30: 2027 | E30: 2028 | F30: 2029 | G30: 2030 | H30: 2031 | I30: 2032 | J30: 2033 | K30: 2034 | L30: 2035 | M30: 2036
N31: =Sum(C31:M31) -> 0
A34: BPN | C34: Total Cost Per BPN
C35: 2026 | D35: 2027 | E35: 2028 | F35: 2029 | G35: 2030 | H35: 2031 | I35: 2032 | J35: 2033 | K35: 2034 | L35: 2035 | M35: 2036
A36: BPN 1 | C36: 0 | D36: 0 | E36: 0 | F36: 0 | G36: 0 | H36: 0 | I36: 0 | J36: 0 | K36: 0 | L36: 0 | M36: 0
A37: BPN 2 | C37: 0 | D37: 0 | E37: 0 | F37: 0 | G37: 0 | H37: 0 | I37: 0 | J37: 0 | K37: 0 | L37: 0 | M37: 0
A38: BPN 3 | C38: 0 | D38: 0 | E38: 0 | F38: 0 | G38: 0 | H38: 0 | I38: 0 | J38: 0 | K38: 0 | L38: 0 | M38: 0
A39: BPN 4 | C39: 0 | D39: 0 | E39: 0 | F39: 0 | G39: 0 | H39: 0 | I39: 0 | J39: 0 | K39: 0 | L39: 0 | M39: 0
A40: BPN L | C40: 0 | D40: 0 | E40: 0 | F40: 0 | G40: 0 | H40: 0 | I40: 0 | J40: 0 | K40: 0 | L40: 0 | M40: 0
A41: BPN Other (BPN D, BPN H,BPN N, BPN T) | C41: 0 | D41: 0 | E41: 0 | F41: 0 | G41: 0 | H41: 0 | I41: 0 | J41: 0 | K41: 0 | L41: 0 | M41: 0
A42: Total BPN Cost | C42: 0 | D42: 0 | F42: 0 | H42: 0 | M42: 0
A44: LLTS_185
C47: Budget Analysis
C48: 2026 | D48: 2027 | E48: 2028 | F48: 2029 | G48: 2030 | H48: 2031 | I48: 2032 | J48: 2033 | K48: 2034 | L48: 2035 | M48: 2036
A49: Remaining Budget | C49: 0 | D49: 0 | E49: 0 | F49: 0 | G49: 0 | H49: 0 | I49: 0 | J49: 0 | K49: 0 | L49: 0 | M49: 0
A50: Percent Budget Spent BAMS | C50: 0 | D50: 0 | E50: 0 | F50: 0 | G50: 0 | H50: 0 | I50: 0 | J50: 0 | K50: 0 | L50: 0 | M50: 0
A51: Percent Budget Spent Committed | C51: 0 | D51: 0 | E51: 0 | F51: 0 | G51: 0 | H51: 0 | I51: 0 | J51: 0 | K51: 0 | L51: 0 | M51: 0
A52: Percent Budget Spent MPMS | C52: 0 | D52: 0 | E52: 0 | F52: 0 | G52: 0 | H52: 0 | I52: 0 | J52: 0 | K52: 0 | L52: 0 | M52: 0
A53: Percent Budget Spent SAP | C53: 0 | D53: 0 | E53: 0 | F53: 0 | G53: 0 | H53: 0 | I53: 0 | J53: 0 | K53: 0 | L53: 0 | M53: 0
A54: Percent Budget Spent Project Builder | C54: 0 | D54: 0 | E54: 0 | F54: 0 | G54: 0 | H54: 0 | I54: 0 | J54: 0 | K54: 0 | L54: 0 | M54: 0
A58: Work Type Totals
C59: 2026 | D59: 2027 | E59: 2028 | F59: 2029 | G59: 2030 | H59: 2031 | I59: 2032 | J59: 2033 | K59: 2034 | L59: 2035 | M59: 2036 | N59: Total (all years)
A60: Maintenance | C60: 0 | D60: 0 | E60: 0 | F60: 0 | G60: 0 | H60: 0 | I60: 0 | J60: 0 | K60: 0 | L60: 0 | M60: 0 | N60: =Sum(C60:M60) -> 0 | O60: =(N60/N67) -> #DIV/0! | P60: Percentage Spent on MAINTENANCE
A61: Preservation | C61: 0 | D61: 0 | E61: 0 | F61: 0 | G61: 0 | H61: 0 | I61: 0 | J61: 0 | K61: 0 | L61: 0 | M61: 0 | N61: =Sum(C61:M61) -> 0 | O61: =(N61/N67) -> #DIV/0! | P61: Percentage Spent on PRESERVATION
A62: Rehabilitation | C62: 0 | D62: 0 | E62: 0 | F62: 0 | G62: 0 | H62: 0 | I62: 0 | J62: 0 | K62: 0 | L62: 0 | M62: 0 | N62: =Sum(C62:M62) -> 0 | O62: =(N62/N67) -> #DIV/0! | P62: Percentage Spent on REHABILITATION
A63: Replacement | C63: 0 | D63: 0 | E63: 0 | F63: 0 | G63: 0 | H63: 0 | I63: 0 | J63: 0 | K63: 0 | L63: 0 | M63: 0 | N63: =Sum(C63:M63) -> 0 | O63: =(N63/N67) -> #DIV/0! | P63: Percentage Spent on REPLACEMENT
A64: Capacity Adding | C64: 0 | D64: 0 | E64: 0 | F64: 0 | G64: 0 | H64: 0 | I64: 0 | J64: 0 | K64: 0 | L64: 0 | M64: 0 | N64: =Sum(C64:M64) -> 0 | O64: =(N64/N67) -> #DIV/0! | P64: Percentage Spent on CAPACITY ADDING
A65: Other | C65: 0 | D65: 0 | E65: 0 | F65: 0 | G65: 0 | H65: 0 | I65: 0 | J65: 0 | K65: 0 | L65: 0 | M65: 0 | N65: =Sum(C65:M65) -> 0 | O65: =(N65/N67) -> #DIV/0! | P65: Percentage Spent on OTHER
A66: Bundled | C66: 0 | D66: 0 | E66: 0 | F66: 0 | G66: 0 | H66: 0 | I66: 0 | J66: 0 | K66: 0 | L66: 0 | M66: 0 | N66: =Sum(C66:M66) -> 0 | O66: =(N66/N67) -> #DIV/0! | P66: Percentage Spent on BUNDLED
A67: Total Spent | N67: =Sum(C67:M67) -> 0
A69: Total Bridge Care Budget | C69: 0 | D69: 0 | E69: 0 | F69: 0 | G69: 0 | H69: 0 | I69: 0 | J69: 0 | K69: 0 | L69: 0 | M69: 0 | N69: =Sum(C69:M69) -> 0
A71: Work Outside Scope/Jurisdiction
C72: 2026 | D72: 2027 | E72: 2028 | F72: 2029 | G72: 2030 | H72: 2031 | I72: 2032 | J72: 2033 | K72: 2034 | L72: 2035 | M72: 2036
N73: =Sum(C73:M73) -> 0
A76: BPN | C76: Total Cost Per BPN
C77: 2026 | D77: 2027 | E77: 2028 | F77: 2029 | G77: 2030 | H77: 2031 | I77: 2032 | J77: 2033 | K77: 2034 | L77: 2035 | M77: 2036
A78: BPN 1 | C78: 0 | D78: 0 | E78: 0 | F78: 0 | G78: 0 | H78: 0 | I78: 0 | J78: 0 | K78: 0 | L78: 0 | M78: 0
A79: BPN 2 | C79: 0 | D79: 0 | E79: 0 | F79: 0 | G79: 0 | H79: 0 | I79: 0 | J79: 0 | K79: 0 | L79: 0 | M79: 0
A80: BPN 3 | C80: 0 | D80: 0 | E80: 0 | F80: 0 | G80: 0 | H80: 0 | I80: 0 | J80: 0 | K80: 0 | L80: 0 | M80: 0
A81: BPN 4 | C81: 0 | D81: 0 | E81: 0 | F81: 0 | G81: 0 | H81: 0 | I81: 0 | J81: 0 | K81: 0 | L81: 0 | M81: 0
A82: BPN L | C82: 0 | D82: 0 | E82: 0 | F82: 0 | G82: 0 | H82: 0 | I82: 0 | J82: 0 | K82: 0 | L82: 0 | M82: 0
A83: BPN Other (BPN D, BPN H,BPN N, BPN T) | C83: 0 | D83: 0 | E83: 0 | F83: 0 | G83: 0 | H83: 0 | I83: 0 | J83: 0 | K83: 0 | L83: 0 | M83: 0
A84: Total BPN Cost | C84: 0 | D84: 0 | F84: 0 | H84: 0 | M84: 0
A86: WAYNE_STU
C89: Budget Analysis
C90: 2026 | D90: 2027 | E90: 2028 | F90: 2029 | G90: 2030 | H90: 2031 | I90: 2032 | J90: 2033 | K90: 2034 | L90: 2035 | M90: 2036
A91: Remaining Budget | C91: 0 | D91: 0 | E91: 0 | F91: 0 | G91: 0 | H91: 0 | I91: 0 | J91: 0 | K91: 0 | L91: 0 | M91: 0
A92: Percent Budget Spent BAMS | C92: 0 | D92: 0 | E92: 0 | F92: 0 | G92: 0 | H92: 0 | I92: 0 | J92: 0 | K92: 0 | L92: 0 | M92: 0
A93: Percent Budget Spent Committed | C93: 0 | D93: 0 | E93: 0 | F93: 0 | G93: 0 | H93: 0 | I93: 0 | J93: 0 | K93: 0 | L93: 0 | M93: 0
A94: Percent Budget Spent MPMS | C94: 0 | D94: 0 | E94: 0 | F94: 0 | G94: 0 | H94: 0 | I94: 0 | J94: 0 | K94: 0 | L94: 0 | M94: 0
A95: Percent Budget Spent SAP | C95: 0 | D95: 0 | E95: 0 | F95: 0 | G95: 0 | H95: 0 | I95: 0 | J95: 0 | K95: 0 | L95: 0 | M95: 0
A96: Percent Budget Spent Project Builder | C96: 0 | D96: 0 | E96: 0 | F96: 0 | G96: 0 | H96: 0 | I96: 0 | J96: 0 | K96: 0 | L96: 0 | M96: 0
A100: Work Type Totals
C101: 2026 | D101: 2027 | E101: 2028 | F101: 2029 | G101: 2030 | H101: 2031 | I101: 2032 | J101: 2033 | K101: 2034 | L101: 2035 | M101: 2036 | N101: Total (all years)
A102: Maintenance | C102: 0 | D102: 0 | E102: 0 | F102: 0 | G102: 0 | H102: 0 | I102: 0 | J102: 0 | K102: 0 | L102: 0 | M102: 0 | N102: =Sum(C102:M102) -> 0 | O102: =(N102/N109) -> #DIV/0! | P102: Percentage Spent on MAINTENANCE
A103: Preservation | C103: 0 | D103: 0 | E103: 0 | F103: 0 | G103: 0 | H103: 0 | I103: 0 | J103: 0 | K103: 0 | L103: 0 | M103: 0 | N103: =Sum(C103:M103) -> 0 | O103: =(N103/N109) -> #DIV/0! | P103: Percentage Spent on PRESERVATION
A104: Rehabilitation | C104: 0 | D104: 0 | E104: 0 | F104: 0 | G104: 0 | H104: 0 | I104: 0 | J104: 0 | K104: 0 | L104: 0 | M104: 0 | N104: =Sum(C104:M104) -> 0 | O104: =(N104/N109) -> #DIV/0! | P104: Percentage Spent on REHABILITATION
A105: Replacement | C105: 0 | D105: 0 | E105: 0 | F105: 0 | G105: 0 | H105: 0 | I105: 0 | J105: 0 | K105: 0 | L105: 0 | M105: 0 | N105: =Sum(C105:M105) -> 0 | O105: =(N105/N109) -> #DIV/0! | P105: Percentage Spent on REPLACEMENT
A106: Capacity Adding | C106: 0 | D106: 0 | E106: 0 | F106: 0 | G106: 0 | H106: 0 | I106: 0 | J106: 0 | K106: 0 | L106: 0 | M106: 0 | N106: =Sum(C106:M106) -> 0 | O106: =(N106/N109) -> #DIV/0! | P106: Percentage Spent on CAPACITY ADDING
A107: Other | C107: 0 | D107: 0 | E107: 0 | F107: 0 | G107: 0 | H107: 0 | I107: 0 | J107: 0 | K107: 0 | L107: 0 | M107: 0 | N107: =Sum(C107:M107) -> 0 | O107: =(N107/N109) -> #DIV/0! | P107: Percentage Spent on OTHER
A108: Bundled | C108: 0 | D108: 0 | E108: 0 | F108: 0 | G108: 0 | H108: 0 | I108: 0 | J108: 0 | K108: 0 | L108: 0 | M108: 0 | N108: =Sum(C108:M108) -> 0 | O108: =(N108/N109) -> #DIV/0! | P108: Percentage Spent on BUNDLED
A109: Total Spent | N109: =Sum(C109:M109) -> 0
A111: Total Bridge Care Budget | C111: 0 | D111: 0 | E111: 0 | F111: 0 | G111: 0 | H111: 0 | I111: 0 | J111: 0 | K111: 0 | L111: 0 | M111: 0 | N111: =Sum(C111:M111) -> 0
A113: Work Outside Scope/Jurisdiction
C114: 2026 | D114: 2027 | E114: 2028 | F114: 2029 | G114: 2030 | H114: 2031 | I114: 2032 | J114: 2033 | K114: 2034 | L114: 2035 | M114: 2036
N115: =Sum(C115:M115) -> 0
A118: BPN | C118: Total Cost Per BPN
C119: 2026 | D119: 2027 | E119: 2028 | F119: 2029 | G119: 2030 | H119: 2031 | I119: 2032 | J119: 2033 | K119: 2034 | L119: 2035 | M119: 2036
A120: BPN 1 | C120: 0 | D120: 0 | E120: 0 | F120: 0 | G120: 0 | H120: 0 | I120: 0 | J120: 0 | K120: 0 | L120: 0 | M120: 0
A121: BPN 2 | C121: 0 | D121: 0 | E121: 0 | F121: 0 | G121: 0 | H121: 0 | I121: 0 | J121: 0 | K121: 0 | L121: 0 | M121: 0
A122: BPN 3 | C122: 0 | D122: 0 | E122: 0 | F122: 0 | G122: 0 | H122: 0 | I122: 0 | J122: 0 | K122: 0 | L122: 0 | M122: 0
A123: BPN 4 | C123: 0 | D123: 0 | E123: 0 | F123: 0 | G123: 0 | H123: 0 | I123: 0 | J123: 0 | K123: 0 | L123: 0 | M123: 0
A124: BPN L | C124: 0 | D124: 0 | E124: 0 | F124: 0 | G124: 0 | H124: 0 | I124: 0 | J124: 0 | K124: 0 | L124: 0 | M124: 0
A125: BPN Other (BPN D, BPN H,BPN N, BPN T) | C125: 0 | D125: 0 | E125: 0 | F125: 0 | G125: 0 | H125: 0 | I125: 0 | J125: 0 | K125: 0 | L125: 0 | M125: 0
A126: Total BPN Cost | C126: 0 | D126: 0 | F126: 0 | H126: 0 | M126: 0
A128: N TIER_185
C131: Budget Analysis
C132: 2026 | D132: 2027 | E132: 2028 | F132: 2029 | G132: 2030 | H132: 2031 | I132: 2032 | J132: 2033 | K132: 2034 | L132: 2035 | M132: 2036
A133: Remaining Budget | C133: 0 | D133: 0 | E133: 0 | F133: 0 | G133: 0 | H133: 0 | I133: 0 | J133: 0 | K133: 0 | L133: 0 | M133: 0
...

Sheet District County Totals
A1: Dollars Spent on MPMS Projects by County | B1: Dollars Spent on MPMS Projects by County | C1: Dollars Spent on MPMS Projects by County | D1: Dollars Spent on MPMS Projects by County | E1: Dollars Spent on MPMS Projects by County | F1: Dollars Spent on MPMS Projects by County | G1: Dollars Spent on MPMS Projects by County | H1: Dollars Spent on MPMS Projects by County | I1: Dollars Spent on MPMS Projects by County | J1: Dollars Spent on MPMS Projects by County | K1: Dollars Spent on MPMS Projects by County | L1: Dollars Spent on MPMS Projects by County | M1: Dollars Spent on MPMS Projects by County
A2: District | B2: County | C2: 2026 | D2: 2027 | E2: 2028 | F2: 2029 | G2: 2030 | H2: 2031 | I2: 2032 | J2: 2033 | K2: 2034 | L2: 2035 | M2: 2036
A3: District: 4 | B3: District: 4 | C3: District: 4 | D3: District: 4 | E3: District: 4 | F3: District: 4 | G3: District: 4 | H3: District: 4 | I3: District: 4 | J3: District: 4 | K3: District: 4 | L3: District: 4 | M3: District: 4
A4: 4 | B4: LACKAWANNA | C4: 0 | D4: 0 | E4: 0 | F4: 0 | G4: 0 | H4: 0 | I4: 0 | J4: 0 | K4: 0 | L4: 0 | M4: 0
A5: 4 | B5: LUZERNE | C5: 0 | D5: 0 | E5: 0 | F5: 0 | G5: 0 | H5: 0 | I5: 0 | J5: 0 | K5: 0 | L5: 0 | M5: 0
A6: 4 | B6: PIKE | C6: 0 | D6: 0 | E6: 0 | F6: 0 | G6: 0 | H6: 0 | I6: 0 | J6: 0 | K6: 0 | L6: 0 | M6: 0
A7: 4 | B7: SUSQUEHANNA | C7: 0 | D7: 0 | E7: 0 | F7: 0 | G7: 0 | H7: 0 | I7: 0 | J7: 0 | K7: 0 | L7: 0 | M7: 0
A8: 4 | B8: WAYNE | C8: 0 | D8: 0 | E8: 0 | F8: 0 | G8: 0 | H8: 0 | I8: 0 | J8: 0 | K8: 0 | L8: 0 | M8: 0
A9: 4 | B9: WYOMING | C9: 0 | D9: 0 | E9: 0 | F9: 0 | G9: 0 | H9: 0 | I9: 0 | J9: 0 | K9: 0 | L9: 0 | M9: 0
A10: District 04 Total | B10: District 04 Total | C10: 0 | D10: 0 | E10: 0 | F10: 0 | G10: 0 | H10: 0 | I10: 0 | J10: 0 | K10: 0 | L10: 0 | M10: 0
A11: Turnpike | B11: Turnpike | C11: 0 | D11: 0 | E11: 0 | F11: 0 | G11: 0 | H11: 0 | I11: 0 | J11: 0 | K11: 0 | L11: 0 | M11: 0
A12: State Total | B12: State Total | C12: 0 | D12: 0 | E12: 0 | F12: 0 | G12: 0 | H12: 0 | I12: 0 | J12: 0 | K12: 0 | L12: 0 | M12: 0
A14: Dollars Spent on BAMS Projects by County | B14: Dollars Spent on BAMS Projects by County | C14: Dollars Spent on BAMS Projects by County | D14: Dollars Spent on BAMS Projects by County | E14: Dollars Spent on BAMS Projects by County | F14: Dollars Spent on BAMS Projects by County | G14: Dollars Spent on BAMS Projects by County | H14: Dollars Spent on BAMS Projects by County | I14: Dollars Spent on BAMS Projects by County | J14: Dollars Spent on BAMS Projects by County | K14: Dollars Spent on BAMS Projects by County | L14: Dollars Spent on BAMS Projects by County | M14: Dollars Spent on BAMS Projects by County
A15: District | B15: County | C15: 2026 | D15: 2027 | E15: 2028 | F15: 2029 | G15: 2030 | H15: 2031 | I15: 2032 | J15: 2033 | K15: 2034 | L15: 2035 | M15: 2036
A16: District: 4 | B16: District: 4 | C16: District: 4 | D16: District: 4 | E16: District: 4 | F16: District: 4 | G16: District: 4 | H16: District: 4 | I16: District: 4 | J16: District: 4 | K16: District: 4 | L16: District: 4 | M16: District: 4
A17: 4 | B17: LACKAWANNA | C17: 0 | D17: 0 | E17: 0 | F17: 0 | G17: 0 | H17: 0 | I17: 0 | J17: 0 | K17: 0 | L17: 0 | M17: 0
A18: 4 | B18: LUZERNE | C18: 0 | D18: 0 | E18: 0 | F18: 0 | G18: 0 | H18: 0 | I18: 0 | J18: 0 | K18: 0 | L18: 0 | M18: 0
A19: 4 | B19: PIKE | C19: 11867274 | D19: 5101744.5 | E19: 0 | F19: 1078914.9 | G19: 0 | H19: 1043346.7 | I19: 0 | J19: 0 | K19: 0 | L19: 0 | M19: 1237494.3
A20: 4 | B20: SUSQUEHANNA | C20: 0 | D20: 0 | E20: 0 | F20: 0 | G20: 0 | H20: 0 | I20: 0 | J20: 0 | K20: 0 | L20: 0 | M20: 0
A21: 4 | B21: WAYNE | C21: 0 | D21: 0 | E21: 0 | F21: 0 | G21: 0 | H21: 0 | I21: 0 | J21: 0 | K21: 0 | L21: 0 | M21: 0
A22: 4 | B22: WYOMING | C22: 0 | D22: 0 | E22: 0 | F22: 0 | G22: 0 | H22: 0 | I22: 0 | J22: 0 | K22: 0 | L22: 0 | M22: 0
A23: District 04 Total | B23: District 04 Total | C23: 11867274 | D23: 5101744.5 | E23: 0 | F23: 1078914.9 | G23: 0 | H23: 1043346.7 | I23: 0 | J23: 0 | K23: 0 | L23: 0 | M23: 1237494.3
A24: Turnpike | B24: Turnpike | C24: 0 | D24: 0 | E24: 0 | F24: 0 | G24: 0 | H24: 0 | I24: 0 | J24: 0 | K24: 0 | L24: 0 | M24: 0
A25: State Total | B25: State Total | C25: 11867274 | D25: 5101744.5 | E25: 0 | F25: 1078914.9 | G25: 0 | H25: 1043346.7 | I25: 0 | J25: 0 | K25: 0 | L25: 0 | M25: 1237494.3
A27: Overall Dollars Spent on Projects by District | B27: Overall Dollars Spent on Projects by District | C27: Overall Dollars Spent on Projects by District | D27: Overall Dollars Spent on Projects by District | E27: Overall Dollars Spent on Projects by District | F27: Overall Dollars Spent on Projects by District | G27: Overall Dollars Spent on Projects by District | H27: Overall Dollars Spent on Projects by District | I27: Overall Dollars Spent on Projects by District | J27: Overall Dollars Spent on Projects by District | K27: Overall Dollars Spent on Projects by District | L27: Overall Dollars Spent on Projects by District | M27: Overall Dollars Spent on Projects by District
A28: District | B28: County | C28: 2026 | D28: 2027 | E28: 2028 | F28: 2029 | G28: 2030 | H28: 2031 | I28: 2032 | J28: 2033 | K28: 2034 | L28: 2035 | M28: 2036
A29: District: 4 | B29: District: 4 | C29: District: 4 | D29: District: 4 | E29: District: 4 | F29: District: 4 | G29: District: 4 | H29: District: 4 | I29: District: 4 | J29: District: 4 | K29: District: 4 | L29: District: 4 | M29: District: 4
A30: 4 | B30: LACKAWANNA | C30: 0 | D30: 0 | E30: 0 | F30: 0 | G30: 0 | H30: 0 | I30: 0 | J30: 0 | K30: 0 | L30: 0 | M30: 0
A31: 4 | B31: LUZERNE | C31: 0 | D31: 0 | E31: 0 | F31: 0 | G31: 0 | H31: 0 | I31: 0 | J31: 0 | K31: 0 | L31: 0 | M31: 0
A32: 4 | B32: PIKE | C32: 11867274 | D32: 5101744.5 | E32: 0 | F32: 1078914.9 | G32: 0 | H32: 1043346.7 | I32: 0 | J32: 0 | K32: 0 | L32: 0 | M32: 1237494.3
A33: 4 | B33: SUSQUEHANNA | C33: 0 | D33: 0 | E33: 0 | F33: 0 | G33: 0 | H33: 0 | I33: 0 | J33: 0 | K33: 0 | L33: 0 | M33: 0
A34: 4 | B34: WAYNE | C34: 0 | D34: 0 | E34: 0 | F34: 0 | G34: 0 | H34: 0 | I34: 0 | J34: 0 | K34: 0 | L34: 0 | M34: 0
A35: 4 | B35: WYOMING | C35: 0 | D35: 0 | E35: 0 | F35: 0 | G35: 0 | H35: 0 | I35: 0 | J35: 0 | K35: 0 | L35: 0 | M35: 0
A36: District 04 Total | B36: District 04 Total | C36: 11867274 | D36: 5101744.5 | E36: 0 | F36: 1078914.9 | G36: 0 | H36: 1043346.7 | I36: 0 | J36: 0 | K36: 0 | L36: 0 | M36: 1237494.3
A37: Turnpike | B37: Turnpike | C37: 0 | D37: 0 | E37: 0 | F37: 0 | G37: 0 | H37: 0 | I37: 0 | J37: 0 | K37: 0 | L37: 0 | M37: 0
A38: State Total | B38: State Total | C38: 11867274 | D38: 5101744.5 | E38: 0 | F38: 1078914.9 | G38: 0 | H38: 1043346.7 | I38: 0 | J38: 0 | K38: 0 | L38: 0 | M38: 1237494.3
A40: % of Overall Dollars Spent on Projects by District | B40: % of Overall Dollars Spent on Projects by District | C40: % of Overall Dollars Spent on Projects by District | D40: % of Overall Dollars Spent on Projects by District | E40: % of Overall Dollars Spent on Projects by District | F40: % of Overall Dollars Spent on Projects by District | G40: % of Overall Dollars Spent on Projects by District | H40: % of Overall Dollars Spent on Projects by District | I40: % of Overall Dollars Spent on Projects by District | J40: % of Overall Dollars Spent on Projects by District | K40: % of Overall Dollars Spent on Projects by District | L40: % of Overall Dollars Spent on Projects by District | M40: % of Overall Dollars Spent on Projects by District
A41: District | B41: County | C41: 2026 | D41: 2027 | E41: 2028 | F41: 2029 | G41: 2030 | H41: 2031 | I41: 2032 | J41: 2033 | K41: 2034 | L41: 2035 | M41: 2036
A42: District: 4 | B42: District: 4 | C42: District: 4 | D42: District: 4 | E42: District: 4 | F42: District: 4 | G42: District: 4 | H42: District: 4 | I42: District: 4 | J42: District: 4 | K42: District: 4 | L42: District: 4 | M42: District: 4
A43: 4 | B43: LACKAWANNA | C43: 0 | D43: 0 | E43: 0 | F43: 0 | G43: 0 | H43: 0 | I43: 0 | J43: 0 | K43: 0 | L43: 0 | M43: 0
A44: 4 | B44: LUZERNE | C44: 0 | D44: 0 | E44: 0 | F44: 0 | G44: 0 | H44: 0 | I44: 0 | J44: 0 | K44: 0 | L44: 0 | M44: 0
A45: 4 | B45: PIKE | C45: 1 | D45: 1 | E45: 0 | F45: 1 | G45: 0 | H45: 1 | I45: 0 | J45: 0 | K45: 0 | L45: 0 | M45: 1
A46: 4 | B46: SUSQUEHANNA | C46: 0 | D46: 0 | E46: 0 | F46: 0 | G46: 0 | H46: 0 | I46: 0 | J46: 0 | K46: 0 | L46: 0 | M46: 0
A47: 4 | B47: WAYNE | C47: 0 | D47: 0 | E47: 0 | F47: 0 | G47: 0 | H47: 0 | I47: 0 | J47: 0 | K47: 0 | L47: 0 | M47: 0
A48: 4 | B48: WYOMING | C48: 0 | D48: 0 | E48: 0 | F48: 0 | G48: 0 | H48: 0 | I48: 0 | J48: 0 | K48: 0 | L48: 0 | M48: 0
A49: District 04 Total | B49: District 04 Total | C49: 1 | D49: 1 | E49: 0 | F49: 1 | G49: 0 | H49: 1 | I49: 0 | J49: 0 | K49: 0 | L49: 0 | M49: 1
A50: Turnpike | B50: Turnpike | C50: 0 | D50: 0 | E50: 0 | F50: 0 | G50: 0 | H50: 0 | I50: 0 | J50: 0 | K50: 0 | L50: 0 | M50: 0

Sheet NHS Count

Sheet NHS DA

Sheet Non NHS Count

Sheet Non NHS DA

Sheet Combined Count

Sheet Combined DA

Sheet Graph Data
A1: =='Bridge Work Summary'!A222 | G1: =='Bridge Work Summary'!A249 | M1: =='Bridge Work Summary'!A236 | S1: =='Bridge Work Summary'!A263 | Y1: =='Bridge Work Summary'!A194 | AE1: =='Bridge Work Summary'!A208
A2: Year | B2: =='Bridge Work Summary'!A224 | C2: =='Bridge Work Summary'!A225 | D2: =='Bridge Work Summary'!A226 | E2: =='Bridge Work Summary'!A227 | G2: Year | H2: =='Bridge Work Summary'!A251 | I2: =='Bridge Work Summary'!A252 | J2: =='Bridge Work Summary'!A253 | K2: =='Bridge Work Summary'!A254 | M2: Year | N2: =='Bridge Work Summary'!A238 | O2: =='Bridge Work Summary'!A239 | P2: =='Bridge Work Summary'!A240 | Q2: =='Bridge Work Summary'!A241 | S2: Year | T2: =='Bridge Work Summary'!A265 | U2: =='Bridge Work Summary'!A266 | V2: =='Bridge Work Summary'!A267 | W2: =='Bridge Work Summary'!A268 | Y2: Year | Z2: =='Bridge Work Summary'!A196 | AA2: =='Bridge Work Summary'!A197 | AB2: =='Bridge Work Summary'!A198 | AC2: =='Bridge Work Summary'!A199 | AE2: Year | AF2: =='Bridge Work Summary'!A210 | AG2: =='Bridge Work Summary'!A211 | AH2: =='Bridge Work Summary'!A212 | AI2: =='Bridge Work Summary'!A213
A3: =='Bridge Work Summary'!B223 | B3: =='Bridge Work Summary'!B224 | C3: =='Bridge Work Summary'!B225 | D3: =='Bridge Work Summary'!B226 | G3: =='Bridge Work Summary'!B250 | H3: =='Bridge Work Summary'!B251 | I3: =='Bridge Work Summary'!B252 | J3: =='Bridge Work Summary'!B253 | M3: =='Bridge Work Summary'!B237 | N3: =='Bridge Work Summary'!B238 | O3: =='Bridge Work Summary'!B239 | P3: =='Bridge Work Summary'!B240 | S3: =='Bridge Work Summary'!B264 | T3: =='Bridge Work Summary'!B265 | U3: =='Bridge Work Summary'!B266 | V3: =='Bridge Work Summary'!B267 | Y3: =='Bridge Work Summary'!B195 | Z3: =='Bridge Work Summary'!B196 | AA3: =='Bridge Work Summary'!B197 | AB3: =='Bridge Work Summary'!B198 | AE3: =='Bridge Work Summary'!B209 | AF3: =='Bridge Work Summary'!B210 | AG3: =='Bridge Work Summary'!B211 | AH3: =='Bridge Work Summary'!B212
E4: =='Bridge Work Summary'!B227 | K4: =='Bridge Work Summary'!B254 | Q4: =='Bridge Work Summary'!B241 | W4: =='Bridge Work Summary'!B268 | AC4: =='Bridge Work Summary'!B199 | AI4: =='Bridge Work Summary'!B213
A6: =='Bridge Work Summary'!C223 | B6: =='Bridge Work Summary'!C224 | C6: =='Bridge Work Summary'!C225 | D6: =='Bridge Work Summary'!C226 | G6: =='Bridge Work Summary'!C250 | H6: =='Bridge Work Summary'!C251 | I6: =='Bridge Work Summary'!C252 | J6: =='Bridge Work Summary'!C253 | M6: =='Bridge Work Summary'!C237 | N6: =='Bridge Work Summary'!C238 | O6: =='Bridge Work Summary'!C239 | P6: =='Bridge Work Summary'!C240 | S6: =='Bridge Work Summary'!C264 | T6: =='Bridge Work Summary'!C265 | U6: =='Bridge Work Summary'!C266 | V6: =='Bridge Work Summary'!C267 | Y6: =='Bridge Work Summary'!C195 | Z6: =='Bridge Work Summary'!C196 | AA6: =='Bridge Work Summary'!C197 | AB6: =='Bridge Work Summary'!C198 | AE6: =='Bridge Work Summary'!C209 | AF6: =='Bridge Work Summary'!C210 | AG6: =='Bridge Work Summary'!C211 | AH6: =='Bridge Work Summary'!C212
E7: =='Bridge Work Summary'!C227 | K7: =='Bridge Work Summary'!C254 | Q7: =='Bridge Work Summary'!C241 | W7: =='Bridge Work Summary'!C268 | AC7: =='Bridge Work Summary'!C199 | AI7: =='Bridge Work Summary'!C213
A9: =='Bridge Work Summary'!D223 | B9: =='Bridge Work Summary'!D224 | C9: =='Bridge Work Summary'!D225 | D9: =='Bridge Work Summary'!D226 | G9: =='Bridge Work Summary'!D250 | H9: =='Bridge Work Summary'!D251 | I9: =='Bridge Work Summary'!D252 | J9: =='Bridge Work Summary'!D253 | M9: =='Bridge Work Summary'!D237 | N9: =='Bridge Work Summary'!D238 | O9: =='Bridge Work Summary'!D239 | P9: =='Bridge Work Summary'!D240 | S9: =='Bridge Work Summary'!D264 | T9: =='Bridge Work Summary'!D265 | U9: =='Bridge Work Summary'!D266 | V9: =='Bridge Work Summary'!D267 | Y9: =='Bridge Work Summary'!D195 | Z9: =='Bridge Work Summary'!D196 | AA9: =='Bridge Work Summary'!D197 | AB9: =='Bridge Work Summary'!D198 | AE9: =='Bridge Work Summary'!D209 | AF9: =='Bridge Work Summary'!D210 | AG9: =='Bridge Work Summary'!D211 | AH9: =='Bridge Work Summary'!D212
E10: =='Bridge Work Summary'!D227 | K10: =='Bridge Work Summary'!D254 | Q10: =='Bridge Work Summary'!D241 | W10: =='Bridge Work Summary'!D268 | AC10: =='Bridge Work Summary'!D199 | AI10: =='Bridge Work Summary'!D213
A12: =='Bridge Work Summary'!E223 | B12: =='Bridge Work Summary'!E224 | C12: =='Bridge Work Summary'!E225 | D12: =='Bridge Work Summary'!E226 | G12: =='Bridge Work Summary'!E250 | H12: =='Bridge Work Summary'!E251 | I12: =='Bridge Work Summary'!E252 | J12: =='Bridge Work Summary'!E253 | M12: =='Bridge Work Summary'!E237 | N12: =='Bridge Work Summary'!E238 | O12: =='Bridge Work Summary'!E239 | P12: =='Bridge Work Summary'!E240 | S12: =='Bridge Work Summary'!E264 | T12: =='Bridge Work Summary'!E265 | U12: =='Bridge Work Summary'!E266 | V12: =='Bridge Work Summary'!E267 | Y12: =='Bridge Work Summary'!E195 | Z12: =='Bridge Work Summary'!E196 | AA12: =='Bridge Work Summary'!E197 | AB12: =='Bridge Work Summary'!E198 | AE12: =='Bridge Work Summary'!E209 | AF12: =='Bridge Work Summary'!E210 | AG12: =='Bridge Work Summary'!E211 | AH12: =='Bridge Work Summary'!E212
E13: =='Bridge Work Summary'!E227 | K13: =='Bridge Work Summary'!E254 | Q13: =='Bridge Work Summary'!E241 | W13: =='Bridge Work Summary'!E268 | AC13: =='Bridge Work Summary'!E199 | AI13: =='Bridge Work Summary'!E213
A15: =='Bridge Work Summary'!F223 | B15: =='Bridge Work Summary'!F224 | C15: =='Bridge Work Summary'!F225 | D15: =='Bridge Work Summary'!F226 | G15: =='Bridge Work Summary'!F250 | H15: =='Bridge Work Summary'!F251 | I15: =='Bridge Work Summary'!F252 | J15: =='Bridge Work Summary'!F253 | M15: =='Bridge Work Summary'!F237 | N15: =='Bridge Work Summary'!F238 | O15: =='Bridge Work Summary'!F239 | P15: =='Bridge Work Summary'!F240 | S15: =='Bridge Work Summary'!F264 | T15: =='Bridge Work Summary'!F265 | U15: =='Bridge Work Summary'!F266 | V15: =='Bridge Work Summary'!F267 | Y15: =='Bridge Work Summary'!F195 | Z15: =='Bridge Work Summary'!F196 | AA15: =='Bridge Work Summary'!F197 | AB15: =='Bridge Work Summary'!F198 | AE15: =='Bridge Work Summary'!F209 | AF15: =='Bridge Work Summary'!F210 | AG15: =='Bridge Work Summary'!F211 | AH15: =='Bridge Work Summary'!F212
E16: =='Bridge Work Summary'!F227 | K16: =='Bridge Work Summary'!F254 | Q16: =='Bridge Work Summary'!F241 | W16: =='Bridge Work Summary'!F268 | AC16: =='Bridge Work Summary'!F199 | AI16: =='Bridge Work Summary'!F213
A18: =='Bridge Work Summary'!G223 | B18: =='Bridge Work Summary'!G224 | C18: =='Bridge Work Summary'!G225 | D18: =='Bridge Work Summary'!G226 | G18: =='Bridge Work Summary'!G250 | H18: =='Bridge Work Summary'!G251 | I18: =='Bridge Work Summary'!G252 | J18: =='Bridge Work Summary'!G253 | M18: =='Bridge Work Summary'!G237 | N18: =='Bridge Work Summary'!G238 | O18: =='Bridge Work Summary'!G239 | P18: =='Bridge Work Summary'!G240 | S18: =='Bridge Work Summary'!G264 | T18: =='Bridge Work Summary'!G265 | U18: =='Bridge Work Summary'!G266 | V18: =='Bridge Work Summary'!G267 | Y18: =='Bridge Work Summary'!G195 | Z18: =='Bridge Work Summary'!G196 | AA18: =='Bridge Work Summary'!G197 | AB18: =='Bridge Work Summary'!G198 | AE18: =='Bridge Work Summary'!G209 | AF18: =='Bridge Work Summary'!G210 | AG18: =='Bridge Work Summary'!G211 | AH18: =='Bridge Work Summary'!G212
E19: =='Bridge Work Summary'!G227 | K19: =='Bridge Work Summary'!G254 | Q19: =='Bridge Work Summary'!G241 | W19: =='Bridge Work Summary'!G268 | AC19: =='Bridge Work Summary'!G199 | AI19: =='Bridge Work Summary'!G213
A21: =='Bridge Work Summary'!H223 | B21: =='Bridge Work Summary'!H224 | C21: =='Bridge Work Summary'!H225 | D21: =='Bridge Work Summary'!H226 | G21: =='Bridge Work Summary'!H250 | H21: =='Bridge Work Summary'!H251 | I21: =='Bridge Work Summary'!H252 | J21: =='Bridge Work Summary'!H253 | M21: =='Bridge Work Summary'!H237 | N21: =='Bridge Work Summary'!H238 | O21: =='Bridge Work Summary'!H239 | P21: =='Bridge Work Summary'!H240 | S21: =='Bridge Work Summary'!H264 | T21: =='Bridge Work Summary'!H265 | U21: =='Bridge Work Summary'!H266 | V21: =='Bridge Work Summary'!H267 | Y21: =='Bridge Work Summary'!H195 | Z21: =='Bridge Work Summary'!H196 | AA21: =='Bridge Work Summary'!H197 | AB21: =='Bridge Work Summary'!H198 | AE21: =='Bridge Work Summary'!H209 | AF21: =='Bridge Work Summary'!H210 | AG21: =='Bridge Work Summary'!H211 | AH21: =='Bridge Work Summary'!H212
E22: =='Bridge Work Summary'!H227 | K22: =='Bridge Work Summary'!H254 | Q22: =='Bridge Work Summary'!H241 | W22: =='Bridge Work Summary'!H268 | AC22: =='Bridge Work Summary'!H199 | AI22: =='Bridge Work Summary'!H213
A24: =='Bridge Work Summary'!I223 | B24: =='Bridge Work Summary'!I224 | C24: =='Bridge Work Summary'!I225 | D24: =='Bridge Work Summary'!I226 | G24: =='Bridge Work Summary'!I250 | H24: =='Bridge Work Summary'!I251 | I24: =='Bridge Work Summary'!I252 | J24: =='Bridge Work Summary'!I253 | M24: =='Bridge Work Summary'!I237 | N24: =='Bridge Work Summary'!I238 | O24: =='Bridge Work Summary'!I239 | P24: =='Bridge Work Summary'!I240 | S24: =='Bridge Work Summary'!I264 | T24: =='Bridge Work Summary'!I265 | U24: =='Bridge Work Summary'!I266 | V24: =='Bridge Work Summary'!I267 | Y24: =='Bridge Work Summary'!I195 | Z24: =='Bridge Work Summary'!I196 | AA24: =='Bridge Work Summary'!I197 | AB24: =='Bridge Work Summary'!I198 | AE24: =='Bridge Work Summary'!I209 | AF24: =='Bridge Work Summary'!I210 | AG24: =='Bridge Work Summary'!I211 | AH24: =='Bridge Work Summary'!I212
E25: =='Bridge Work Summary'!I227 | K25: =='Bridge Work Summary'!I254 | Q25: =='Bridge Work Summary'!I241 | W25: =='Bridge Work Summary'!I268 | AC25: =='Bridge Work Summary'!I199 | AI25: =='Bridge Work Summary'!I213
A27: =='Bridge Work Summary'!J223 | B27: =='Bridge Work Summary'!J224 | C27: =='Bridge Work Summary'!J225 | D27: =='Bridge Work Summary'!J226 | G27: =='Bridge Work Summary'!J250 | H27: =='Bridge Work Summary'!J251 | I27: =='Bridge Work Summary'!J252 | J27: =='Bridge Work Summary'!J253 | M27: =='Bridge Work Summary'!J237 | N27: =='Bridge Work Summary'!J238 | O27: =='Bridge Work Summary'!J239 | P27: =='Bridge Work Summary'!J240 | S27: =='Bridge Work Summary'!J264 | T27: =='Bridge Work Summary'!J265 | U27: =='Bridge Work Summary'!J266 | V27: =='Bridge Work Summary'!J267 | Y27: =='Bridge Work Summary'!J195 | Z27: =='Bridge Work Summary'!J196 | AA27: =='Bridge Work Summary'!J197 | AB27: =='Bridge Work Summary'!J198 | AE27: =='Bridge Work Summary'!J209 | AF27: =='Bridge Work Summary'!J210 | AG27: =='Bridge Work Summary'!J211 | AH27: =='Bridge Work Summary'!J212
E28: =='Bridge Work Summary'!J227 | K28: =='Bridge Work Summary'!J254 | Q28: =='Bridge Work Summary'!J241 | W28: =='Bridge Work Summary'!J268 | AC28: =='Bridge Work Summary'!J199 | AI28: =='Bridge Work Summary'!J213
A30: =='Bridge Work Summary'!K223 | B30: =='Bridge Work Summary'!K224 | C30: =='Bridge Work Summary'!K225 | D30: =='Bridge Work Summary'!K226 | G30: =='Bridge Work Summary'!K250 | H30: =='Bridge Work Summary'!K251 | I30: =='Bridge Work Summary'!K252 | J30: =='Bridge Work Summary'!K253 | M30: =='Bridge Work Summary'!K237 | N30: =='Bridge Work Summary'!K238 | O30: =='Bridge Work Summary'!K239 | P30: =='Bridge Work Summary'!K240 | S30: =='Bridge Work Summary'!K264 | T30: =='Bridge Work Summary'!K265 | U30: =='Bridge Work Summary'!K266 | V30: =='Bridge Work Summary'!K267 | Y30: =='Bridge Work Summary'!K195 | Z30: =='Bridge Work Summary'!K196 | AA30: =='Bridge Work Summary'!K197 | AB30: =='Bridge Work Summary'!K198 | AE30: =='Bridge Work Summary'!K209 | AF30: =='Bridge Work Summary'!K210 | AG30: =='Bridge Work Summary'!K211 | AH30: =='Bridge Work Summary'!K212
E31: =='Bridge Work Summary'!K227 | K31: =='Bridge Work Summary'!K254 | Q31: =='Bridge Work Summary'!K241 | W31: =='Bridge Work Summary'!K268 | AC31: =='Bridge Work Summary'!K199 | AI31: =='Bridge Work Summary'!K213
A33: =='Bridge Work Summary'!L223 | B33: =='Bridge Work Summary'!L224 | C33: =='Bridge Work Summary'!L225 | D33: =='Bridge Work Summary'!L226 | G33: =='Bridge Work Summary'!L250 | H33: =='Bridge Work Summary'!L251 | I33: =='Bridge Work Summary'!L252 | J33: =='Bridge Work Summary'!L253 | M33: =='Bridge Work Summary'!L237 | N33: =='Bridge Work Summary'!L238 | O33: =='Bridge Work Summary'!L239 | P33: =='Bridge Work Summary'!L240 | S33: =='Bridge Work Summary'!L264 | T33: =='Bridge Work Summary'!L265 | U33: =='Bridge Work Summary'!L266 | V33: =='Bridge Work Summary'!L267 | Y33: =='Bridge Work Summary'!L195 | Z33: =='Bridge Work Summary'!L196 | AA33: =='Bridge Work Summary'!L197 | AB33: =='Bridge Work Summary'!L198 | AE33: =='Bridge Work Summary'!L209 | AF33: =='Bridge Work Summary'!L210 | AG33: =='Bridge Work Summary'!L211 | AH33: =='Bridge Work Summary'!L212
E34: =='Bridge Work Summary'!L227 | K34: =='Bridge Work Summary'!L254 | Q34: =='Bridge Work Summary'!L241 | W34: =='Bridge Work Summary'!L268 | AC34: =='Bridge Work Summary'!L199 | AI34: =='Bridge Work Summary'!L213
